Workbook

Sheet Summary
F2: Most-likely | G2: Face value
F3: Optimistic | G3: Might take lesser effort
F4: Pessimistic | G4: Might take more effort
F5: Calculated Man-Days | G5: Calibrated estimate
B6: MAN-DAYS
E7: ="50%" -> 50% | F7: ="10%" -> 10%
B8: # of Epics | C8: Product | D8: Most-likely Man-days | E8: ="Optimistic Man-days ("&E7&")" -> Optimistic Man-days (50%) | F8: ="Pessimistic ("& F7&")" -> Pessimistic (10%) | G8: Calculated Man-Days | H8: TK Approved
B9: =COUNTA('OmniConnect RMI'!D:D) -> 51 | C9: OmniConnect | D9: =SUM('OmniConnect RMI'!V:V) -> 810 | E9: =SUM('OmniConnect RMI'!W:W) -> 405 | F9: =SUM('OmniConnect RMI'!X:X) -> 1012.5 | G9: =SUM('OmniConnect RMI'!Y:Y) -> 776.25 | H9: =G9/2 -> 388.125
B10: =COUNTA('Fintech Fuel RMI'!D:D) -> 54 | C10: Fintech Fuel | D10: =SUM('Fintech Fuel RMI'!V:V) -> 1210 | E10: =SUM('Fintech Fuel RMI'!W:W) -> 605 | F10: =SUM('Fintech Fuel RMI'!X:X) -> 1331 | G10: =SUM('Fintech Fuel RMI'!Y:Y) -> 1129.3333 | H10: =G10/2 -> 564.66667
B11: =COUNTA('OmniChat RMI'!D:D) -> 14 | C11: OmniChat | D11: =SUM('OmniChat RMI'!V:V) -> 413 | E11: =SUM('OmniChat RMI'!W:W) -> 206.5 | F11: =SUM('OmniChat RMI'!X:X) -> 454.3 | G11: =SUM('OmniChat RMI'!Y:Y) -> 400.46667 | H11: =G11/2 -> 200.23333
B12: =COUNTA('Digital Log RMI'!D:D) -> 31 | C12: Digital Log | D12: =SUM('Digital Log RMI'!V:V) -> 972 | E12: =SUM('Digital Log RMI'!W:W) -> 486 | F12: =SUM('Digital Log RMI'!X:X) -> 1215 | G12: =SUM('Digital Log RMI'!Y:Y) -> 931.5 | H12: =G12/2 -> 465.75
C13: Support (3 person) | D13: 176 | E13: 88 | F13: 193.6 | G13: 164.26667 | H13: =G13 -> 164.26667
C14: Total | D14: =SUM(D9:D12,D13) -> 3581 | E14: =SUM(E9:E12,E13) -> 1790.5 | F14: =SUM(F9:F12,F13) -> 4206.4 | G14: =SUM(G9:G12,G13) -> 3401.8167 | H14: =SUM(H9:H12,H13) -> 1783.0417

Sheet OmniConnect RMI
A1: OmniConnect Roadmap Items | H1: BHW | I1: TK | J1: AA | K1: TS | M1: RnD Most likely | W1: TK Budgeted | AQ1: `=($Y3-($M3+$T3+$Q3)) * (SUBSTITUTE(MID(AH$2, SEARCH("(", AH$2) + 1, 5), "%)", "") / 100)
A2: Sr # | B2: Category | C2: Components | D2: Road Map Items | E2: Jira ID | F2: Originator | G2: Value | H2: Priority | I2: Priority | J2: Priority | K2: Priority | L2: Plan Status | M2: Prc Design | N2: R/URS | O2: R/DDS | P2: Dev | Q2: SQA | R2: Prc Test | S2: Doc | T2: Reg SQA | U2: Release | V2: Man Days | W2: ="Optimistic ("&Summary!E7&")" -> Optimistic (50%) | X2: Pessimistic (10%) | Y2: Est Formula | Z2: TK's TARGET | AA2: Start Date | AB2: Dev End | AC2: SQA HO | AD2: Prod Date | AE2: Prc Design | AF2: R/URS (5%) | AG2: R/DDS (10%) | AH2: Dev (40%) | AI2: Handover | AJ2: SQA (15%) | AK2: Bug Fixing (15%) | AL2: Prc Test | AM2: Doc (5%) | AN2: Reg SQA (10%) | AO2: Release
A3: 1 | B3: Input | C3: Streaming | D3: OC Streaming (80% done) | E3: https://octopusdtlsupport.atlassian.net/browse/O2-793 | F3: RnD | H3: 1 | K3: 1 | L3: Plan | N3: 2 | O3: 20 | P3: 40 | Q3: 20 | S3: 0 | T3: 2 | V3: =SUM(M3:U3) -> 84 | W3: =V3 - (V3 * (SUBSTITUTE(SUBSTITUTE($W$2, "Optimistic (", ""), "%)", "") / 100)) -> 42 | X3: =V3 + (W3 * (SUBSTITUTE(SUBSTITUTE($W$2, "Optimistic (", ""), "%)", "") / 100)) -> 105 | Y3: =(W3+(4*V3)+X3)/6 -> 80.5 | Z3: =Y3/2 -> 40.25 | AD3: =AC3+5 -> 5 | AE3: =IF($Z3="",0,IF($M3="",0,$M3)) -> 0 | AF3: =IF(OR($Z3="",$N3=""),0,$Z3*5%) -> 2.0125 | AG3: =IF(OR($Z3="",$O3=""),0,$Z3*10%) -> 4.025 | AH3: =IF($Z3="",0,IF(AND($P3="",$Q3=""),($Z3-$AE3-$AF3-$AG3-$AI3-$AK3-$AL3-$AM3-$AN3-$AO3),IF($P3="",0,IF($Q3="",($Z3-$AE3-$AF3-$AG3-$AI3-$AK3-$AL3-$AM3-$AN3-$AO3),($Z3-$AE3-$AF3-$AG3-$AI3-$AK3-$AL3-$AM3-$AN3-$AO3)*40%/(40%+15%))))) -> 15.736364 | AI3: =IF($Z3="",0,IF($P3="",0,0.5)) -> 0.5 | AJ3: =IF($Z3="",0,IF(AND($P3="",$Q3=""),0,IF($Q3="",0,IF($P3="",($Z3-$AE3-$AF3-$AG3-$AI3-$AK3-$AL3-$AM3-$AN3-$AO3),($Z3-$AE3-$AF3-$AG3-$AI3-$AK3-$AL3-$AM3-$AN3-$AO3)*15%/(40%+15%))))) -> 5.9011364 | AK3: =IF($Z3="",0,$Z3*15%) -> 6.0375 | AL3: =IF($Z3="",0,IF($R3="",0,$R3)) -> 0 | AM3: =IF(OR($Z3="",$S3=""),0,$Z3*5%) -> 2.0125 | AN3: =IF(OR($Z3="",$T3=""),0,$Z3*10%) -> 4.025 | AO3: =IF($Z3="",0,IF($U3="",0,$U3)) -> 0 | AP3: =SUM(AE3:AM3) -> 36.225
A4: 2 | D4: OC streaming on Pub Sub | F4: Imp Team | H4: 1 | K4: 1 | L4: UnPlan | V4: =SUM(M4:U4) -> 0 | W4: =V4 - (V4 * (SUBSTITUTE(SUBSTITUTE($W$2, "Optimistic (", ""), "%)", "") / 100)) -> 0 | X4: =V4 + (W4 * (SUBSTITUTE(SUBSTITUTE($W$2, "Optimistic (", ""), "%)", "") / 100)) -> 0 | Y4: =(W4+(4*V4)+X4)/6 -> 0 | Z4: =Y4/2 -> 0 | AE4: =IF($Z4="",0,IF($M4="",0,$M4)) -> 0 | AF4: =IF(OR($Z4="",$N4=""),0,$Z4*5%) -> 0 | AG4: =IF(OR($Z4="",$O4=""),0,$Z4*10%) -> 0 | AH4: =IF($Z4="",0,IF(AND($P4="",$Q4=""),($Z4-$AE4-$AF4-$AG4-$AI4-$AK4-$AL4-$AM4-$AN4-$AO4),IF($P4="",0,IF($Q4="",($Z4-$AE4-$AF4-$AG4-$AI4-$AK4-$AL4-$AM4-$AN4-$AO4),($Z4-$AE4-$AF4-$AG4-$AI4-$AK4-$AL4-$AM4-$AN4-$AO4)*40%/(40%+15%))))) -> 0 | AI4: =IF($Z4="",0,IF($P4="",0,0.5)) -> 0 | AJ4: =IF($Z4="",0,IF(AND($P4="",$Q4=""),0,IF($Q4="",0,IF($P4="",($Z4-$AE4-$AF4-$AG4-$AI4-$AK4-$AL4-$AM4-$AN4-$AO4),($Z4-$AE4-$AF4-$AG4-$AI4-$AK4-$AL4-$AM4-$AN4-$AO4)*15%/(40%+15%))))) -> 0 | AK4: =IF($Z4="",0,$Z4*15%) -> 0 | AL4: =IF($Z4="",0,IF($R4="",0,$R4)) -> 0 | AM4: =IF(OR($Z4="",$S4=""),0,$Z4*5%) -> 0 | AN4: =IF(OR($Z4="",$T4=""),0,$Z4*10%) -> 0 | AO4: =IF($Z4="",0,IF($U4="",0,$U4)) -> 0 | AP4: =SUM(AE4:AM4) -> 0
A5: 3 | C5: Bulk Device creation | D5: BULK DEVICE CREATION FOR NON SMART DEVICES (on hold, no further thought process undertaken) Current feature is to bulk create MQTT/IOT devices which has ability to directly connect to Azure IOT hub as an independent devices. It does not cover the schenario where multiple non smart devices are connected to one gateway from where the data is send to cloud. Now need is to replicate such non smart devices (connected to gateway) on OC as logical devices. | F5: Management | H5: 2 | K5: 2 | Q5: 5 | U5: 1 | V5: =SUM(M5:U5) -> 6 | W5: =V5 - (V5 * (SUBSTITUTE(SUBSTITUTE($W$2, "Optimistic (", ""), "%)", "") / 100)) -> 3 | X5: =V5 + (W5 * (SUBSTITUTE(SUBSTITUTE($W$2, "Optimistic (", ""), "%)", "") / 100)) -> 7.5 | Y5: =(W5+(4*V5)+X5)/6 -> 5.75 | Z5: =Y5/2 -> 2.875 | AE5: =IF($Z5="",0,IF($M5="",0,$M5)) -> 0 | AF5: =IF(OR($Z5="",$N5=""),0,$Z5*5%) -> 0 | AG5: =IF(OR($Z5="",$O5=""),0,$Z5*10%) -> 0 | AH5: =IF($Z5="",0,IF(AND($P5="",$Q5=""),($Z5-$AE5-$AF5-$AG5-$AI5-$AK5-$AL5-$AM5-$AN5-$AO5),IF($P5="",0,IF($Q5="",($Z5-$AE5-$AF5-$AG5-$AI5-$AK5-$AL5-$AM5-$AN5-$AO5),($Z5-$AE5-$AF5-$AG5-$AI5-$AK5-$AL5-$AM5-$AN5-$AO5)*40%/(40%+15%))))) -> 0 | AI5: =IF($Z5="",0,IF($P5="",0,0.5)) -> 0 | AJ5: =IF($Z5="",0,IF(AND($P5="",$Q5=""),0,IF($Q5="",0,IF($P5="",($Z5-$AE5-$AF5-$AG5-$AI5-$AK5-$AL5-$AM5-$AN5-$AO5),($Z5-$AE5-$AF5-$AG5-$AI5-$AK5-$AL5-$AM5-$AN5-$AO5)*15%/(40%+15%))))) -> 1.44375 | AK5: =IF($Z5="",0,$Z5*15%) -> 0.43125 | AL5: =IF($Z5="",0,IF($R5="",0,$R5)) -> 0 | AM5: =IF(OR($Z5="",$S5=""),0,$Z5*5%) -> 0 | AN5: =IF(OR($Z5="",$T5=""),0,$Z5*10%) -> 0 | AO5: =IF($Z5="",0,IF($U5="",0,$U5)) -> 1 | AP5: =SUM(AE5:AM5) -> 1.875
A6: 4 | C6: Import Site Layout | D6: Import Site Layout catchup till date | F6: RnD | H6: 2 | K6: 3 | L6: UnPlan | V6: =SUM(M6:U6) -> 0 | W6: =V6 - (V6 * (SUBSTITUTE(SUBSTITUTE($W$2, "Optimistic (", ""), "%)", "") / 100)) -> 0 | X6: =V6 + (W6 * (SUBSTITUTE(SUBSTITUTE($W$2, "Optimistic (", ""), "%)", "") / 100)) -> 0 | Y6: =(W6+(4*V6)+X6)/6 -> 0 | Z6: =Y6/2 -> 0 | AE6: =IF($Z6="",0,IF($M6="",0,$M6)) -> 0 | AF6: =IF(OR($Z6="",$N6=""),0,$Z6*5%) -> 0 | AG6: =IF(OR($Z6="",$O6=""),0,$Z6*10%) -> 0 | AH6: =IF($Z6="",0,IF(AND($P6="",$Q6=""),($Z6-$AE6-$AF6-$AG6-$AI6-$AK6-$AL6-$AM6-$AN6-$AO6),IF($P6="",0,IF($Q6="",($Z6-$AE6-$AF6-$AG6-$AI6-$AK6-$AL6-$AM6-$AN6-$AO6),($Z6-$AE6-$AF6-$AG6-$AI6-$AK6-$AL6-$AM6-$AN6-$AO6)*40%/(40%+15%))))) -> 0 | AI6: =IF($Z6="",0,IF($P6="",0,0.5)) -> 0 | AJ6: =IF($Z6="",0,IF(AND($P6="",$Q6=""),0,IF($Q6="",0,IF($P6="",($Z6-$AE6-$AF6-$AG6-$AI6-$AK6-$AL6-$AM6-$AN6-$AO6),($Z6-$AE6-$AF6-$AG6-$AI6-$AK6-$AL6-$AM6-$AN6-$AO6)*15%/(40%+15%))))) -> 0 | AK6: =IF($Z6="",0,$Z6*15%) -> 0 | AL6: =IF($Z6="",0,IF($R6="",0,$R6)) -> 0 | AM6: =IF(OR($Z6="",$S6=""),0,$Z6*5%) -> 0 | AN6: =IF(OR($Z6="",$T6=""),0,$Z6*10%) -> 0 | AO6: =IF($Z6="",0,IF($U6="",0,$U6)) -> 0 | AP6: =SUM(AE6:AM6) -> 0
A7: 5 | C7: Scheduled Pull | D7: Support for Wide tables from SQL Source | E7: https://octopusdtlsupport.atlassian.net/browse/O2-2188 | F7: RnD | K7: 2 | P7: =10+2 -> 12 | Q7: 2 | S7: 2 | T7: 5 | U7: =(10+2)/3 -> 4 | V7: =SUM(M7:U7) -> 25 | W7: =V7 - (V7 * (SUBSTITUTE(SUBSTITUTE($W$2, "Optimistic (", ""), "%)", "") / 100)) -> 12.5 | X7: =V7 + (W7 * (SUBSTITUTE(SUBSTITUTE($W$2, "Optimistic (", ""), "%)", "") / 100)) -> 31.25 | Y7: =(W7+(4*V7)+X7)/6 -> 23.958333 | Z7: =Y7/2 -> 11.979167 | AA7: 46150 | AB7: 46156 | AC7: 46157 | AD7: 46161 | AE7: =IF($Z7="",0,IF($M7="",0,$M7)) -> 0 | AF7: =IF(OR($Z7="",$N7=""),0,$Z7*5%) -> 0 | AG7: =IF(OR($Z7="",$O7=""),0,$Z7*10%) -> 0 | AH7: =IF($Z7="",0,IF(AND($P7="",$Q7=""),($Z7-$AE7-$AF7-$AG7-$AI7-$AK7-$AL7-$AM7-$AN7-$AO7),IF($P7="",0,IF($Q7="",($Z7-$AE7-$AF7-$AG7-$AI7-$AK7-$AL7-$AM7-$AN7-$AO7),($Z7-$AE7-$AF7-$AG7-$AI7-$AK7-$AL7-$AM7-$AN7-$AO7)*40%/(40%+15%))))) -> 2.8257576 | AI7: =IF($Z7="",0,IF($P7="",0,0.5)) -> 0.5 | AJ7: =IF($Z7="",0,IF(AND($P7="",$Q7=""),0,IF($Q7="",0,IF($P7="",($Z7-$AE7-$AF7-$AG7-$AI7-$AK7-$AL7-$AM7-$AN7-$AO7),($Z7-$AE7-$AF7-$AG7-$AI7-$AK7-$AL7-$AM7-$AN7-$AO7)*15%/(40%+15%))))) -> 1.0596591 | AK7: =IF($Z7="",0,$Z7*15%) -> 1.796875 | AL7: =IF($Z7="",0,IF($R7="",0,$R7)) -> 0 | AM7: =IF(OR($Z7="",$S7=""),0,$Z7*5%) -> 0.59895833 | AN7: =IF(OR($Z7="",$T7=""),0,$Z7*10%) -> 1.1979167 | AO7: =IF($Z7="",0,IF($U7="",0,$U7)) -> 4 | AP7: =SUM(AE7:AM7) -> 6.78125 | AQ7: Need to understand this
A8: 6 | D8: Support for Wide tables from API Source | E8: https://octopusdtlsupport.atlassian.net/browse/O2-2189 | F8: RnD | K8: 2 | P8: =10+2 -> 12 | Q8: 2 | S8: 2 | T8: 5 | U8: =(10+2)/3 -> 4 | V8: =SUM(M8:U8) -> 25 | W8: =V8 - (V8 * (SUBSTITUTE(SUBSTITUTE($W$2, "Optimistic (", ""), "%)", "") / 100)) -> 12.5 | X8: =V8 + (W8 * (SUBSTITUTE(SUBSTITUTE($W$2, "Optimistic (", ""), "%)", "") / 100)) -> 31.25 | Y8: =(W8+(4*V8)+X8)/6 -> 23.958333 | Z8: =Y8/2 -> 11.979167 | AA8: 46164 | AB8: 46170 | AC8: 46171 | AD8: 46175 | AE8: =IF($Z8="",0,IF($M8="",0,$M8)) -> 0 | AF8: =IF(OR($Z8="",$N8=""),0,$Z8*5%) -> 0 | AG8: =IF(OR($Z8="",$O8=""),0,$Z8*10%) -> 0 | AH8: =IF($Z8="",0,IF(AND($P8="",$Q8=""),($Z8-$AE8-$AF8-$AG8-$AI8-$AK8-$AL8-$AM8-$AN8-$AO8),IF($P8="",0,IF($Q8="",($Z8-$AE8-$AF8-$AG8-$AI8-$AK8-$AL8-$AM8-$AN8-$AO8),($Z8-$AE8-$AF8-$AG8-$AI8-$AK8-$AL8-$AM8-$AN8-$AO8)*40%/(40%+15%))))) -> 2.8257576 | AI8: =IF($Z8="",0,IF($P8="",0,0.5)) -> 0.5 | AJ8: =IF($Z8="",0,IF(AND($P8="",$Q8=""),0,IF($Q8="",0,IF($P8="",($Z8-$AE8-$AF8-$AG8-$AI8-$AK8-$AL8-$AM8-$AN8-$AO8),($Z8-$AE8-$AF8-$AG8-$AI8-$AK8-$AL8-$AM8-$AN8-$AO8)*15%/(40%+15%))))) -> 1.0596591 | AK8: =IF($Z8="",0,$Z8*15%) -> 1.796875 | AL8: =IF($Z8="",0,IF($R8="",0,$R8)) -> 0 | AM8: =IF(OR($Z8="",$S8=""),0,$Z8*5%) -> 0.59895833 | AN8: =IF(OR($Z8="",$T8=""),0,$Z8*10%) -> 1.1979167 | AO8: =IF($Z8="",0,IF($U8="",0,$U8)) -> 4 | AP8: =SUM(AE8:AM8) -> 6.78125 | AQ8: Need to understand this
A9: 7 | D9: Support for Wide tables from SFTP Source | E9: https://octopusdtlsupport.atlassian.net/browse/O2-2190 | F9: RnD | K9: 2 | M9: 0 | P9: =10+2 -> 12 | Q9: 2 | R9: 0 | S9: 2 | T9: 5 | U9: =(10+2)/3 -> 4 | V9: =SUM(M9:U9) -> 25 | W9: =V9 - (V9 * (SUBSTITUTE(SUBSTITUTE($W$2, "Optimistic (", ""), "%)", "") / 100)) -> 12.5 | X9: =V9 + (W9 * (SUBSTITUTE(SUBSTITUTE($W$2, "Optimistic (", ""), "%)", "") / 100)) -> 31.25 | Y9: =(W9+(4*V9)+X9)/6 -> 23.958333 | Z9: =Y9/2 -> 11.979167 | AA9: 46176 | AB9: 46182 | AC9: 46183 | AD9: 46185 | AE9: =IF($Z9="",0,IF($M9="",0,$M9)) -> 0 | AF9: =IF(OR($Z9="",$N9=""),0,$Z9*5%) -> 0 | AG9: =IF(OR($Z9="",$O9=""),0,$Z9*10%) -> 0 | AH9: =IF($Z9="",0,IF(AND($P9="",$Q9=""),($Z9-$AE9-$AF9-$AG9-$AI9-$AK9-$AL9-$AM9-$AN9-$AO9),IF($P9="",0,IF($Q9="",($Z9-$AE9-$AF9-$AG9-$AI9-$AK9-$AL9-$AM9-$AN9-$AO9),($Z9-$AE9-$AF9-$AG9-$AI9-$AK9-$AL9-$AM9-$AN9-$AO9)*40%/(40%+15%))))) -> 2.8257576 | AI9: =IF($Z9="",0,IF($P9="",0,0.5)) -> 0.5 | AJ9: =IF($Z9="",0,IF(AND($P9="",$Q9=""),0,IF($Q9="",0,IF($P9="",($Z9-$AE9-$AF9-$AG9-$AI9-$AK9-$AL9-$AM9-$AN9-$AO9),($Z9-$AE9-$AF9-$AG9-$AI9-$AK9-$AL9-$AM9-$AN9-$AO9)*15%/(40%+15%))))) -> 1.0596591 | AK9: =IF($Z9="",0,$Z9*15%) -> 1.796875 | AL9: =IF($Z9="",0,IF($R9="",0,$R9)) -> 0 | AM9: =IF(OR($Z9="",$S9=""),0,$Z9*5%) -> 0.59895833 | AN9: =IF(OR($Z9="",$T9=""),0,$Z9*10%) -> 1.1979167 | AO9: =IF($Z9="",0,IF($U9="",0,$U9)) -> 4 | AP9: =SUM(AE9:AM9) -> 6.78125 | AQ9: Need to understand this
D10: OmniEdge diagnostics metrics collection | E10: https://octopusdtlsupport.atlassian.net/browse/O2-2269 | F10: RnD | M10: 2 | N10: 2 | O10: 3 | P10: 2 | Q10: 1 | R10: 0 | S10: 0 | T10: 0 | U10: 3 | V10: 17 | W10: =V10 - (V10 * (SUBSTITUTE(SUBSTITUTE($W$2, "Optimistic (", ""), "%)", "") / 100)) -> 8.5 | X10: =V10 + (W10 * (SUBSTITUTE(SUBSTITUTE($W$2, "Optimistic (", ""), "%)", "") / 100)) -> 21.25 | Y10: =(W10+(4*V10)+X10)/6 -> 16.291667 | Z10: =Y10/2 -> 8.1458333 | AA10: =DATEVALUE("04/08/2026") -> 46120 | AB10: =DATEVALUE("04/17/2026") -> 46129 | AC10: 46136 | AD10: 46142 | AE10: =IF($Z10="",0,IF($M10="",0,$M10)) -> 2 | AF10: =IF(OR($Z10="",$N10=""),0,$Z10*5%) -> 0.40729167 | AG10: =IF(OR($Z10="",$O10=""),0,$Z10*10%) -> 0.81458333 | AH10: =IF($Z10="",0,IF(AND($P10="",$Q10=""),($Z10-$AE10-$AF10-$AG10-$AI10-$AK10-$AL10-$AM10-$AN10-$AO10),IF($P10="",0,IF($Q10="",($Z10-$AE10-$AF10-$AG10-$AI10-$AK10-$AL10-$AM10-$AN10-$AO10),($Z10-$AE10-$AF10-$AG10-$AI10-$AK10-$AL10-$AM10-$AN10-$AO10)*40%/(40%+15%))))) -> -0.74166667 | AI10: =IF($Z10="",0,IF($P10="",0,0.5)) -> 0.5 | AJ10: =IF($Z10="",0,IF(AND($P10="",$Q10=""),0,IF($Q10="",0,IF($P10="",($Z10-$AE10-$AF10-$AG10-$AI10-$AK10-$AL10-$AM10-$AN10-$AO10),($Z10-$AE10-$AF10-$AG10-$AI10-$AK10-$AL10-$AM10-$AN10-$AO10)*15%/(40%+15%))))) -> -0.278125 | AK10: =IF($Z10="",0,$Z10*15%) -> 1.221875 | AL10: =IF($Z10="",0,IF($R10="",0,$R10)) -> 0 | AM10: =IF(OR($Z10="",$S10=""),0,$Z10*5%) -> 0.40729167 | AN10: =IF(OR($Z10="",$T10=""),0,$Z10*10%) -> 0.81458333 | AO10: =IF($Z10="",0,IF($U10="",0,$U10)) -> 3 | AP10: =SUM(AE10:AM10) -> 4.33125
A11: 8 | B11: Enrichment | C11: APX | D11: APX - WhatIf Pump | F11: Process Team | H11: 1 | K11: 1 | L11: Plan | M11: 0 | Q11: 1 | R11: =4+4 -> 8 | T11: 1 | U11: 1 | V11: =SUM(M11:U11) -> 11 | W11: =V11 - (V11 * (SUBSTITUTE(SUBSTITUTE($W$2, "Optimistic (", ""), "%)", "") / 100)) -> 5.5 | X11: =V11 + (W11 * (SUBSTITUTE(SUBSTITUTE($W$2, "Optimistic (", ""), "%)", "") / 100)) -> 13.75 | Y11: =(W11+(4*V11)+X11)/6 -> 10.541667 | Z11: =Y11/2 -> 5.2708333 | AE11: =IF($Z11="",0,IF($M11="",0,$M11)) -> 0 | AF11: =IF(OR($Z11="",$N11=""),0,$Z11*5%) -> 0 | AG11: =IF(OR($Z11="",$O11=""),0,$Z11*10%) -> 0 | AH11: =IF($Z11="",0,IF(AND($P11="",$Q11=""),($Z11-$AE11-$AF11-$AG11-$AI11-$AK11-$AL11-$AM11-$AN11-$AO11),IF($P11="",0,IF($Q11="",($Z11-$AE11-$AF11-$AG11-$AI11-$AK11-$AL11-$AM11-$AN11-$AO11),($Z11-$AE11-$AF11-$AG11-$AI11-$AK11-$AL11-$AM11-$AN11-$AO11)*40%/(40%+15%))))) -> 0 | AI11: =IF($Z11="",0,IF($P11="",0,0.5)) -> 0 | AJ11: =IF($Z11="",0,IF(AND($P11="",$Q11=""),0,IF($Q11="",0,IF($P11="",($Z11-$AE11-$AF11-$AG11-$AI11-$AK11-$AL11-$AM11-$AN11-$AO11),($Z11-$AE11-$AF11-$AG11-$AI11-$AK11-$AL11-$AM11-$AN11-$AO11)*15%/(40%+15%))))) -> -5.046875 | AK11: =IF($Z11="",0,$Z11*15%) -> 0.790625 | AL11: =IF($Z11="",0,IF($R11="",0,$R11)) -> 8 | AM11: =IF(OR($Z11="",$S11=""),0,$Z11*5%) -> 0 | AN11: =IF(OR($Z11="",$T11=""),0,$Z11*10%) -> 0.52708333 | AO11: =IF($Z11="",0,IF($U11="",0,$U11)) -> 1 | AP11: =SUM(AE11:AM11) -> 3.74375
A12: 9 | D12: APX - WhatIf Compressor | F12: Process Team | H12: 1 | K12: 1 | L12: Plan | M12: 0 | Q12: 1 | R12: 3 | T12: 1 | U12: 1 | V12: =SUM(M12:U12) -> 6 | W12: =V12 - (V12 * (SUBSTITUTE(SUBSTITUTE($W$2, "Optimistic (", ""), "%)", "") / 100)) -> 3 | X12: =V12 + (W12 * (SUBSTITUTE(SUBSTITUTE($W$2, "Optimistic (", ""), "%)", "") / 100)) -> 7.5 | Y12: =(W12+(4*V12)+X12)/6 -> 5.75 | Z12: =Y12/2 -> 2.875 | AE12: =IF($Z12="",0,IF($M12="",0,$M12)) -> 0 | AF12: =IF(OR($Z12="",$N12=""),0,$Z12*5%) -> 0 | AG12: =IF(OR($Z12="",$O12=""),0,$Z12*10%) -> 0 | AH12: =IF($Z12="",0,IF(AND($P12="",$Q12=""),($Z12-$AE12-$AF12-$AG12-$AI12-$AK12-$AL12-$AM12-$AN12-$AO12),IF($P12="",0,IF($Q12="",($Z12-$AE12-$AF12-$AG12-$AI12-$AK12-$AL12-$AM12-$AN12-$AO12),($Z12-$AE12-$AF12-$AG12-$AI12-$AK12-$AL12-$AM12-$AN12-$AO12)*40%/(40%+15%))))) -> 0 | AI12: =IF($Z12="",0,IF($P12="",0,0.5)) -> 0 | AJ12: =IF($Z12="",0,IF(AND($P12="",$Q12=""),0,IF($Q12="",0,IF($P12="",($Z12-$AE12-$AF12-$AG12-$AI12-$AK12-$AL12-$AM12-$AN12-$AO12),($Z12-$AE12-$AF12-$AG12-$AI12-$AK12-$AL12-$AM12-$AN12-$AO12)*15%/(40%+15%))))) -> -1.84375 | AK12: =IF($Z12="",0,$Z12*15%) -> 0.43125 | AL12: =IF($Z12="",0,IF($R12="",0,$R12)) -> 3 | AM12: =IF(OR($Z12="",$S12=""),0,$Z12*5%) -> 0 | AN12: =IF(OR($Z12="",$T12=""),0,$Z12*10%) -> 0.2875 | AO12: =IF($Z12="",0,IF($U12="",0,$U12)) -> 1 | AP12: =SUM(AE12:AM12) -> 1.5875
A13: 10 | D13: APX - WhatIf Condenser | F13: Process Team | H13: 1 | K13: 1 | L13: Plan | M13: 0 | Q13: 1 | R13: 5 | T13: 1 | U13: 1 | V13: =SUM(M13:U13) -> 8 | W13: =V13 - (V13 * (SUBSTITUTE(SUBSTITUTE($W$2, "Optimistic (", ""), "%)", "") / 100)) -> 4 | X13: =V13 + (W13 * (SUBSTITUTE(SUBSTITUTE($W$2, "Optimistic (", ""), "%)", "") / 100)) -> 10 | Y13: =(W13+(4*V13)+X13)/6 -> 7.6666667 | Z13: =Y13/2 -> 3.8333333 | AE13: =IF($Z13="",0,IF($M13="",0,$M13)) -> 0 | AF13: =IF(OR($Z13="",$N13=""),0,$Z13*5%) -> 0 | AG13: =IF(OR($Z13="",$O13=""),0,$Z13*10%) -> 0 | AH13: =IF($Z13="",0,IF(AND($P13="",$Q13=""),($Z13-$AE13-$AF13-$AG13-$AI13-$AK13-$AL13-$AM13-$AN13-$AO13),IF($P13="",0,IF($Q13="",($Z13-$AE13-$AF13-$AG13-$AI13-$AK13-$AL13-$AM13-$AN13-$AO13),($Z13-$AE13-$AF13-$AG13-$AI13-$AK13-$AL13-$AM13-$AN13-$AO13)*40%/(40%+15%))))) -> 0 | AI13: =IF($Z13="",0,IF($P13="",0,0.5)) -> 0 | AJ13: =IF($Z13="",0,IF(AND($P13="",$Q13=""),0,IF($Q13="",0,IF($P13="",($Z13-$AE13-$AF13-$AG13-$AI13-$AK13-$AL13-$AM13-$AN13-$AO13),($Z13-$AE13-$AF13-$AG13-$AI13-$AK13-$AL13-$AM13-$AN13-$AO13)*15%/(40%+15%))))) -> -3.125 | AK13: =IF($Z13="",0,$Z13*15%) -> 0.575 | AL13: =IF($Z13="",0,IF($R13="",0,$R13)) -> 5 | AM13: =IF(OR($Z13="",$S13=""),0,$Z13*5%) -> 0 | AN13: =IF(OR($Z13="",$T13=""),0,$Z13*10%) -> 0.38333333 | AO13: =IF($Z13="",0,IF($U13="",0,$U13)) -> 1 | AP13: =SUM(AE13:AM13) -> 2.45
A14: 11 | D14: APX - WhatIf Heat Exchanger | F14: Process Team | H14: 1 | K14: 1 | L14: Plan | M14: 0 | Q14: 1 | R14: 3 | T14: 1 | U14: 1 | V14: =SUM(M14:U14) -> 6 | W14: =V14 - (V14 * (SUBSTITUTE(SUBSTITUTE($W$2, "Optimistic (", ""), "%)", "") / 100)) -> 3 | X14: =V14 + (W14 * (SUBSTITUTE(SUBSTITUTE($W$2, "Optimistic (", ""), "%)", "") / 100)) -> 7.5 | Y14: =(W14+(4*V14)+X14)/6 -> 5.75 | Z14: =Y14/2 -> 2.875 | AE14: =IF($Z14="",0,IF($M14="",0,$M14)) -> 0 | AF14: =IF(OR($Z14="",$N14=""),0,$Z14*5%) -> 0 | AG14: =IF(OR($Z14="",$O14=""),0,$Z14*10%) -> 0 | AH14: =IF($Z14="",0,IF(AND($P14="",$Q14=""),($Z14-$AE14-$AF14-$AG14-$AI14-$AK14-$AL14-$AM14-$AN14-$AO14),IF($P14="",0,IF($Q14="",($Z14-$AE14-$AF14-$AG14-$AI14-$AK14-$AL14-$AM14-$AN14-$AO14),($Z14-$AE14-$AF14-$AG14-$AI14-$AK14-$AL14-$AM14-$AN14-$AO14)*40%/(40%+15%))))) -> 0 | AI14: =IF($Z14="",0,IF($P14="",0,0.5)) -> 0 | AJ14: =IF($Z14="",0,IF(AND($P14="",$Q14=""),0,IF($Q14="",0,IF($P14="",($Z14-$AE14-$AF14-$AG14-$AI14-$AK14-$AL14-$AM14-$AN14-$AO14),($Z14-$AE14-$AF14-$AG14-$AI14-$AK14-$AL14-$AM14-$AN14-$AO14)*15%/(40%+15%))))) -> -1.84375 | AK14: =IF($Z14="",0,$Z14*15%) -> 0.43125 | AL14: =IF($Z14="",0,IF($R14="",0,$R14)) -> 3 | AM14: =IF(OR($Z14="",$S14=""),0,$Z14*5%) -> 0 | AN14: =IF(OR($Z14="",$T14=""),0,$Z14*10%) -> 0.2875 | AO14: =IF($Z14="",0,IF($U14="",0,$U14)) -> 1 | AP14: =SUM(AE14:AM14) -> 1.5875
A15: 12 | D15: APX - WhatIf Boiler | F15: Process Team | H15: 1 | K15: 1 | L15: Plan | M15: 0 | Q15: 1 | R15: 0 | T15: 1 | U15: 1 | V15: =SUM(M15:U15) -> 3 | W15: =V15 - (V15 * (SUBSTITUTE(SUBSTITUTE($W$2, "Optimistic (", ""), "%)", "") / 100)) -> 1.5 | X15: =V15 + (W15 * (SUBSTITUTE(SUBSTITUTE($W$2, "Optimistic (", ""), "%)", "") / 100)) -> 3.75 | Y15: =(W15+(4*V15)+X15)/6 -> 2.875 | Z15: =Y15/2 -> 1.4375 | AE15: =IF($Z15="",0,IF($M15="",0,$M15)) -> 0 | AF15: =IF(OR($Z15="",$N15=""),0,$Z15*5%) -> 0 | AG15: =IF(OR($Z15="",$O15=""),0,$Z15*10%) -> 0 | AH15: =IF($Z15="",0,IF(AND($P15="",$Q15=""),($Z15-$AE15-$AF15-$AG15-$AI15-$AK15-$AL15-$AM15-$AN15-$AO15),IF($P15="",0,IF($Q15="",($Z15-$AE15-$AF15-$AG15-$AI15-$AK15-$AL15-$AM15-$AN15-$AO15),($Z15-$AE15-$AF15-$AG15-$AI15-$AK15-$AL15-$AM15-$AN15-$AO15)*40%/(40%+15%))))) -> 0 | AI15: =IF($Z15="",0,IF($P15="",0,0.5)) -> 0 | AJ15: =IF($Z15="",0,IF(AND($P15="",$Q15=""),0,IF($Q15="",0,IF($P15="",($Z15-$AE15-$AF15-$AG15-$AI15-$AK15-$AL15-$AM15-$AN15-$AO15),($Z15-$AE15-$AF15-$AG15-$AI15-$AK15-$AL15-$AM15-$AN15-$AO15)*15%/(40%+15%))))) -> 0.078125 | AK15: =IF($Z15="",0,$Z15*15%) -> 0.215625 | AL15: =IF($Z15="",0,IF($R15="",0,$R15)) -> 0 | AM15: =IF(OR($Z15="",$S15=""),0,$Z15*5%) -> 0 | AN15: =IF(OR($Z15="",$T15=""),0,$Z15*10%) -> 0.14375 | AO15: =IF($Z15="",0,IF($U15="",0,$U15)) -> 1 | AP15: =SUM(AE15:AM15) -> 0.29375
A16: 13 | D16: APX - Health Pump | F16: Process Team | H16: 1 | K16: 1 | L16: Plan | M16: 0 | Q16: 1 | R16: 4 | T16: 1 | U16: 1 | V16: =SUM(M16:U16) -> 7 | W16: =V16 - (V16 * (SUBSTITUTE(SUBSTITUTE($W$2, "Optimistic (", ""), "%)", "") / 100)) -> 3.5 | X16: =V16 + (W16 * (SUBSTITUTE(SUBSTITUTE($W$2, "Optimistic (", ""), "%)", "") / 100)) -> 8.75 | Y16: =(W16+(4*V16)+X16)/6 -> 6.7083333 | Z16: =Y16/2 -> 3.3541667 | AE16: =IF($Z16="",0,IF($M16="",0,$M16)) -> 0 | AF16: =IF(OR($Z16="",$N16=""),0,$Z16*5%) -> 0 | AG16: =IF(OR($Z16="",$O16=""),0,$Z16*10%) -> 0 | AH16: =IF($Z16="",0,IF(AND($P16="",$Q16=""),($Z16-$AE16-$AF16-$AG16-$AI16-$AK16-$AL16-$AM16-$AN16-$AO16),IF($P16="",0,IF($Q16="",($Z16-$AE16-$AF16-$AG16-$AI16-$AK16-$AL16-$AM16-$AN16-$AO16),($Z16-$AE16-$AF16-$AG16-$AI16-$AK16-$AL16-$AM16-$AN16-$AO16)*40%/(40%+15%))))) -> 0 | AI16: =IF($Z16="",0,IF($P16="",0,0.5)) -> 0 | AJ16: =IF($Z16="",0,IF(AND($P16="",$Q16=""),0,IF($Q16="",0,IF($P16="",($Z16-$AE16-$AF16-$AG16-$AI16-$AK16-$AL16-$AM16-$AN16-$AO16),($Z16-$AE16-$AF16-$AG16-$AI16-$AK16-$AL16-$AM16-$AN16-$AO16)*15%/(40%+15%))))) -> -2.484375 | AK16: =IF($Z16="",0,$Z16*15%) -> 0.503125 | AL16: =IF($Z16="",0,IF($R16="",0,$R16)) -> 4 | AM16: =IF(OR($Z16="",$S16=""),0,$Z16*5%) -> 0 | AN16: =IF(OR($Z16="",$T16=""),0,$Z16*10%) -> 0.33541667 | AO16: =IF($Z16="",0,IF($U16="",0,$U16)) -> 1 | AP16: =SUM(AE16:AM16) -> 2.01875
A17: 14 | D17: APX - Health Compressor | F17: Process Team | H17: 1 | K17: 1 | L17: Plan | M17: 0 | Q17: 1 | R17: 3 | T17: 1 | U17: 1 | V17: =SUM(M17:U17) -> 6 | W17: =V17 - (V17 * (SUBSTITUTE(SUBSTITUTE($W$2, "Optimistic (", ""), "%)", "") / 100)) -> 3 | X17: =V17 + (W17 * (SUBSTITUTE(SUBSTITUTE($W$2, "Optimistic (", ""), "%)", "") / 100)) -> 7.5 | Y17: =(W17+(4*V17)+X17)/6 -> 5.75 | Z17: =Y17/2 -> 2.875 | AE17: =IF($Z17="",0,IF($M17="",0,$M17)) -> 0 | AF17: =IF(OR($Z17="",$N17=""),0,$Z17*5%) -> 0 | AG17: =IF(OR($Z17="",$O17=""),0,$Z17*10%) -> 0 | AH17: =IF($Z17="",0,IF(AND($P17="",$Q17=""),($Z17-$AE17-$AF17-$AG17-$AI17-$AK17-$AL17-$AM17-$AN17-$AO17),IF($P17="",0,IF($Q17="",($Z17-$AE17-$AF17-$AG17-$AI17-$AK17-$AL17-$AM17-$AN17-$AO17),($Z17-$AE17-$AF17-$AG17-$AI17-$AK17-$AL17-$AM17-$AN17-$AO17)*40%/(40%+15%))))) -> 0 | AI17: =IF($Z17="",0,IF($P17="",0,0.5)) -> 0 | AJ17: =IF($Z17="",0,IF(AND($P17="",$Q17=""),0,IF($Q17="",0,IF($P17="",($Z17-$AE17-$AF17-$AG17-$AI17-$AK17-$AL17-$AM17-$AN17-$AO17),($Z17-$AE17-$AF17-$AG17-$AI17-$AK17-$AL17-$AM17-$AN17-$AO17)*15%/(40%+15%))))) -> -1.84375 | AK17: =IF($Z17="",0,$Z17*15%) -> 0.43125 | AL17: =IF($Z17="",0,IF($R17="",0,$R17)) -> 3 | AM17: =IF(OR($Z17="",$S17=""),0,$Z17*5%) -> 0 | AN17: =IF(OR($Z17="",$T17=""),0,$Z17*10%) -> 0.2875 | AO17: =IF($Z17="",0,IF($U17="",0,$U17)) -> 1 | AP17: =SUM(AE17:AM17) -> 1.5875
A18: 15 | D18: APX - Health Motor | F18: Process Team | H18: 1 | K18: 1 | L18: Plan | M18: 0 | Q18: 1 | R18: 4 | T18: 1 | U18: 1 | V18: =SUM(M18:U18) -> 7 | W18: =V18 - (V18 * (SUBSTITUTE(SUBSTITUTE($W$2, "Optimistic (", ""), "%)", "") / 100)) -> 3.5 | X18: =V18 + (W18 * (SUBSTITUTE(SUBSTITUTE($W$2, "Optimistic (", ""), "%)", "") / 100)) -> 8.75 | Y18: =(W18+(4*V18)+X18)/6 -> 6.7083333 | Z18: =Y18/2 -> 3.3541667 | AE18: =IF($Z18="",0,IF($M18="",0,$M18)) -> 0 | AF18: =IF(OR($Z18="",$N18=""),0,$Z18*5%) -> 0 | AG18: =IF(OR($Z18="",$O18=""),0,$Z18*10%) -> 0 | AH18: =IF($Z18="",0,IF(AND($P18="",$Q18=""),($Z18-$AE18-$AF18-$AG18-$AI18-$AK18-$AL18-$AM18-$AN18-$AO18),IF($P18="",0,IF($Q18="",($Z18-$AE18-$AF18-$AG18-$AI18-$AK18-$AL18-$AM18-$AN18-$AO18),($Z18-$AE18-$AF18-$AG18-$AI18-$AK18-$AL18-$AM18-$AN18-$AO18)*40%/(40%+15%))))) -> 0 | AI18: =IF($Z18="",0,IF($P18="",0,0.5)) -> 0 | AJ18: =IF($Z18="",0,IF(AND($P18="",$Q18=""),0,IF($Q18="",0,IF($P18="",($Z18-$AE18-$AF18-$AG18-$AI18-$AK18-$AL18-$AM18-$AN18-$AO18),($Z18-$AE18-$AF18-$AG18-$AI18-$AK18-$AL18-$AM18-$AN18-$AO18)*15%/(40%+15%))))) -> -2.484375 | AK18: =IF($Z18="",0,$Z18*15%) -> 0.503125 | AL18: =IF($Z18="",0,IF($R18="",0,$R18)) -> 4 | AM18: =IF(OR($Z18="",$S18=""),0,$Z18*5%) -> 0 | AN18: =IF(OR($Z18="",$T18=""),0,$Z18*10%) -> 0.33541667 | AO18: =IF($Z18="",0,IF($U18="",0,$U18)) -> 1 | AP18: =SUM(AE18:AM18) -> 2.01875
A19: 16 | D19: DEV - WhatIf Visual Screens (Pump, Comp,Cond,Hex, Boiler) II | E19: https://octopusdtlsupport.atlassian.net/browse/O2-1991 | F19: Process Team | H19: 1 | K19: 1 | L19: UnPlan | M19: 1 | O19: 5 | P19: 30 | Q19: 5 | R19: 3 | U19: 3 | V19: =SUM(M19:U19) -> 47 | W19: =V19 - (V19 * (SUBSTITUTE(SUBSTITUTE($W$2, "Optimistic (", ""), "%)", "") / 100)) -> 23.5 | X19: =V19 + (W19 * (SUBSTITUTE(SUBSTITUTE($W$2, "Optimistic (", ""), "%)", "") / 100)) -> 58.75 | Y19: =(W19+(4*V19)+X19)/6 -> 45.041667 | Z19: =Y19/2 -> 22.520833 | AA19: 46118 | AB19: 46135 | AC19: 46136 | AD19: 46141 | AE19: =IF($Z19="",0,IF($M19="",0,$M19)) -> 1 | AF19: =IF(OR($Z19="",$N19=""),0,$Z19*5%) -> 0 | AG19: =IF(OR($Z19="",$O19=""),0,$Z19*10%) -> 2.2520833 | AH19: =IF($Z19="",0,IF(AND($P19="",$Q19=""),($Z19-$AE19-$AF19-$AG19-$AI19-$AK19-$AL19-$AM19-$AN19-$AO19),IF($P19="",0,IF($Q19="",($Z19-$AE19-$AF19-$AG19-$AI19-$AK19-$AL19-$AM19-$AN19-$AO19),($Z19-$AE19-$AF19-$AG19-$AI19-$AK19-$AL19-$AM19-$AN19-$AO19)*40%/(40%+15%))))) -> 6.8295455 | AI19: =IF($Z19="",0,IF($P19="",0,0.5)) -> 0.5 | AJ19: =IF($Z19="",0,IF(AND($P19="",$Q19=""),0,IF($Q19="",0,IF($P19="",($Z19-$AE19-$AF19-$AG19-$AI19-$AK19-$AL19-$AM19-$AN19-$AO19),($Z19-$AE19-$AF19-$AG19-$AI19-$AK19-$AL19-$AM19-$AN19-$AO19)*15%/(40%+15%))))) -> 2.5610795 | AK19: =IF($Z19="",0,$Z19*15%) -> 3.378125 | AL19: =IF($Z19="",0,IF($R19="",0,$R19)) -> 3 | AM19: =IF(OR($Z19="",$S19=""),0,$Z19*5%) -> 0 | AN19: =IF(OR($Z19="",$T19=""),0,$Z19*10%) -> 0 | AO19: =IF($Z19="",0,IF($U19="",0,$U19)) -> 3 | AP19: =SUM(AE19:AM19) -> 19.520833
A20: 17 | D20: DEV - Tempate Tool Enhancement for WhatIf and Health | E20: https://octopusdtlsupport.atlassian.net/browse/O2-2186 | F20: Process Team | H20: 1 | K20: 1 | M20: 4 | P20: 20 | Q20: 10 | R20: 5 | S20: 5 | U20: 3 | V20: =SUM(M20:U20) -> 47 | W20: =V20 - (V20 * (SUBSTITUTE(SUBSTITUTE($W$2, "Optimistic (", ""), "%)", "") / 100)) -> 23.5 | X20: =V20 + (W20 * (SUBSTITUTE(SUBSTITUTE($W$2, "Optimistic (", ""), "%)", "") / 100)) -> 58.75 | Y20: =(W20+(4*V20)+X20)/6 -> 45.041667 | Z20: =Y20/2 -> 22.520833 | AA20: 46118 | AB20: 46128 | AC20: 46129 | AD20: 46139 | AE20: =IF($Z20="",0,IF($M20="",0,$M20)) -> 4 | AF20: =IF(OR($Z20="",$N20=""),0,$Z20*5%) -> 0 | AG20: =IF(OR($Z20="",$O20=""),0,$Z20*10%) -> 0 | AH20: =IF($Z20="",0,IF(AND($P20="",$Q20=""),($Z20-$AE20-$AF20-$AG20-$AI20-$AK20-$AL20-$AM20-$AN20-$AO20),IF($P20="",0,IF($Q20="",($Z20-$AE20-$AF20-$AG20-$AI20-$AK20-$AL20-$AM20-$AN20-$AO20),($Z20-$AE20-$AF20-$AG20-$AI20-$AK20-$AL20-$AM20-$AN20-$AO20)*40%/(40%+15%))))) -> 4.0121212 | AI20: =IF($Z20="",0,IF($P20="",0,0.5)) -> 0.5 | AJ20: =IF($Z20="",0,IF(AND($P20="",$Q20=""),0,IF($Q20="",0,IF($P20="",($Z20-$AE20-$AF20-$AG20-$AI20-$AK20-$AL20-$AM20-$AN20-$AO20),($Z20-$AE20-$AF20-$AG20-$AI20-$AK20-$AL20-$AM20-$AN20-$AO20)*15%/(40%+15%))))) -> 1.5045455 | AK20: =IF($Z20="",0,$Z20*15%) -> 3.378125 | AL20: =IF($Z20="",0,IF($R20="",0,$R20)) -> 5 | AM20: =IF(OR($Z20="",$S20=""),0,$Z20*5%) -> 1.1260417 | AN20: =IF(OR($Z20="",$T20=""),0,$Z20*10%) -> 0 | AO20: =IF($Z20="",0,IF($U20="",0,$U20)) -> 3 | AP20: =SUM(AE20:AM20) -> 19.520833
A21: 18 | D21: DEV - Performance Module Enhancements (Results in OC ) | F21: Process Team | H21: 1 | K21: 1 | L21: UnPlan | M21: 5 | R21: 0 | V21: =SUM(M21:U21) -> 5 | W21: =V21 - (V21 * (SUBSTITUTE(SUBSTITUTE($W$2, "Optimistic (", ""), "%)", "") / 100)) -> 2.5 | X21: =V21 + (W21 * (SUBSTITUTE(SUBSTITUTE($W$2, "Optimistic (", ""), "%)", "") / 100)) -> 6.25 | Y21: =(W21+(4*V21)+X21)/6 -> 4.7916667 | Z21: =Y21/2 -> 2.3958333 | AE21: =IF($Z21="",0,IF($M21="",0,$M21)) -> 5 | AF21: =IF(OR($Z21="",$N21=""),0,$Z21*5%) -> 0 | AG21: =IF(OR($Z21="",$O21=""),0,$Z21*10%) -> 0 | AH21: =IF($Z21="",0,IF(AND($P21="",$Q21=""),($Z21-$AE21-$AF21-$AG21-$AI21-$AK21-$AL21-$AM21-$AN21-$AO21),IF($P21="",0,IF($Q21="",($Z21-$AE21-$AF21-$AG21-$AI21-$AK21-$AL21-$AM21-$AN21-$AO21),($Z21-$AE21-$AF21-$AG21-$AI21-$AK21-$AL21-$AM21-$AN21-$AO21)*40%/(40%+15%))))) -> -2.9635417 | AI21: =IF($Z21="",0,IF($P21="",0,0.5)) -> 0 | AJ21: =IF($Z21="",0,IF(AND($P21="",$Q21=""),0,IF($Q21="",0,IF($P21="",($Z21-$AE21-$AF21-$AG21-$AI21-$AK21-$AL21-$AM21-$AN21-$AO21),($Z21-$AE21-$AF21-$AG21-$AI21-$AK21-$AL21-$AM21-$AN21-$AO21)*15%/(40%+15%))))) -> 0 | AK21: =IF($Z21="",0,$Z21*15%) -> 0.359375 | AL21: =IF($Z21="",0,IF($R21="",0,$R21)) -> 0 | AM21: =IF(OR($Z21="",$S21=""),0,$Z21*5%) -> 0 | AN21: =IF(OR($Z21="",$T21=""),0,$Z21*10%) -> 0 | AO21: =IF($Z21="",0,IF($U21="",0,$U21)) -> 0 | AP21: =SUM(AE21:AM21) -> 2.3958333
A22: 19 | D22: APX - Demos | F22: Process Team | H22: 1 | K22: 1+ | L22: Plan | M22: 8 | R22: 0 | V22: =SUM(M22:U22) -> 8 | W22: =V22 - (V22 * (SUBSTITUTE(SUBSTITUTE($W$2, "Optimistic (", ""), "%)", "") / 100)) -> 4 | X22: =V22 + (W22 * (SUBSTITUTE(SUBSTITUTE($W$2, "Optimistic (", ""), "%)", "") / 100)) -> 10 | Y22: =(W22+(4*V22)+X22)/6 -> 7.6666667 | Z22: =Y22/2 -> 3.8333333 | AE22: =IF($Z22="",0,IF($M22="",0,$M22)) -> 8 | AF22: =IF(OR($Z22="",$N22=""),0,$Z22*5%) -> 0 | AG22: =IF(OR($Z22="",$O22=""),0,$Z22*10%) -> 0 | AH22: =IF($Z22="",0,IF(AND($P22="",$Q22=""),($Z22-$AE22-$AF22-$AG22-$AI22-$AK22-$AL22-$AM22-$AN22-$AO22),IF($P22="",0,IF($Q22="",($Z22-$AE22-$AF22-$AG22-$AI22-$AK22-$AL22-$AM22-$AN22-$AO22),($Z22-$AE22-$AF22-$AG22-$AI22-$AK22-$AL22-$AM22-$AN22-$AO22)*40%/(40%+15%))))) -> -4.7416667 | AI22: =IF($Z22="",0,IF($P22="",0,0.5)) -> 0 | AJ22: =IF($Z22="",0,IF(AND($P22="",$Q22=""),0,IF($Q22="",0,IF($P22="",($Z22-$AE22-$AF22-$AG22-$AI22-$AK22-$AL22-$AM22-$AN22-$AO22),($Z22-$AE22-$AF22-$AG22-$AI22-$AK22-$AL22-$AM22-$AN22-$AO22)*15%/(40%+15%))))) -> 0 | AK22: =IF($Z22="",0,$Z22*15%) -> 0.575 | AL22: =IF($Z22="",0,IF($R22="",0,$R22)) -> 0 | AM22: =IF(OR($Z22="",$S22=""),0,$Z22*5%) -> 0 | AN22: =IF(OR($Z22="",$T22=""),0,$Z22*10%) -> 0 | AO22: =IF($Z22="",0,IF($U22="",0,$U22)) -> 0 | AP22: =SUM(AE22:AM22) -> 3.8333333
A23: 20 | C23: Batch / BPM | D23: IT/OT Conversion Batch/BPM (on hold) | F23: RnD | L23: UnPlan | M23: - | R23: - | V23: =SUM(M23:U23) -> 0 | W23: =V23 - (V23 * (SUBSTITUTE(SUBSTITUTE($W$2, "Optimistic (", ""), "%)", "") / 100)) -> 0 | X23: =V23 + (W23 * (SUBSTITUTE(SUBSTITUTE($W$2, "Optimistic (", ""), "%)", "") / 100)) -> 0 | Y23: =(W23+(4*V23)+X23)/6 -> 0 | Z23: =Y23/2 -> 0 | AE23: =IF($Z23="",0,IF($M23="",0,$M23)) -> - | AF23: =IF(OR($Z23="",$N23=""),0,$Z23*5%) -> 0 | AG23: =IF(OR($Z23="",$O23=""),0,$Z23*10%) -> 0 | AH23: =IF($Z23="",0,IF(AND($P23="",$Q23=""),($Z23-$AE23-$AF23-$AG23-$AI23-$AK23-$AL23-$AM23-$AN23-$AO23),IF($P23="",0,IF($Q23="",($Z23-$AE23-$AF23-$AG23-$AI23-$AK23-$AL23-$AM23-$AN23-$AO23),($Z23-$AE23-$AF23-$AG23-$AI23-$AK23-$AL23-$AM23-$AN23-$AO23)*40%/(40%+15%))))) -> #VALUE! | AI23: =IF($Z23="",0,IF($P23="",0,0.5)) -> 0 | AJ23: =IF($Z23="",0,IF(AND($P23="",$Q23=""),0,IF($Q23="",0,IF($P23="",($Z23-$AE23-$AF23-$AG23-$AI23-$AK23-$AL23-$AM23-$AN23-$AO23),($Z23-$AE23-$AF23-$AG23-$AI23-$AK23-$AL23-$AM23-$AN23-$AO23)*15%/(40%+15%))))) -> 0 | AK23: =IF($Z23="",0,$Z23*15%) -> 0 | AL23: =IF($Z23="",0,IF($R23="",0,$R23)) -> - | AM23: =IF(OR($Z23="",$S23=""),0,$Z23*5%) -> 0 | AN23: =IF(OR($Z23="",$T23=""),0,$Z23*10%) -> 0 | AO23: =IF($Z23="",0,IF($U23="",0,$U23)) -> 0 | AP23: =SUM(AE23:AM23) -> #VALUE!
A24: 21 | D24: Support for SQL Language in Batch/BPM(Features Supported by adx) (Discussion Required) | F24: RnD | K24: 2 | L24: UnPlan | M24: - | R24: - | V24: =SUM(M24:U24) -> 0 | W24: =V24 - (V24 * (SUBSTITUTE(SUBSTITUTE($W$2, "Optimistic (", ""), "%)", "") / 100)) -> 0 | X24: =V24 + (W24 * (SUBSTITUTE(SUBSTITUTE($W$2, "Optimistic (", ""), "%)", "") / 100)) -> 0 | Y24: =(W24+(4*V24)+X24)/6 -> 0 | Z24: =Y24/2 -> 0 | AE24: =IF($Z24="",0,IF($M24="",0,$M24)) -> - | AF24: =IF(OR($Z24="",$N24=""),0,$Z24*5%) -> 0 | AG24: =IF(OR($Z24="",$O24=""),0,$Z24*10%) -> 0 | AH24: =IF($Z24="",0,IF(AND($P24="",$Q24=""),($Z24-$AE24-$AF24-$AG24-$AI24-$AK24-$AL24-$AM24-$AN24-$AO24),IF($P24="",0,IF($Q24="",($Z24-$AE24-$AF24-$AG24-$AI24-$AK24-$AL24-$AM24-$AN24-$AO24),($Z24-$AE24-$AF24-$AG24-$AI24-$AK24-$AL24-$AM24-$AN24-$AO24)*40%/(40%+15%))))) -> #VALUE! | AI24: =IF($Z24="",0,IF($P24="",0,0.5)) -> 0 | AJ24: =IF($Z24="",0,IF(AND($P24="",$Q24=""),0,IF($Q24="",0,IF($P24="",($Z24-$AE24-$AF24-$AG24-$AI24-$AK24-$AL24-$AM24-$AN24-$AO24),($Z24-$AE24-$AF24-$AG24-$AI24-$AK24-$AL24-$AM24-$AN24-$AO24)*15%/(40%+15%))))) -> 0 | AK24: =IF($Z24="",0,$Z24*15%) -> 0 | AL24: =IF($Z24="",0,IF($R24="",0,$R24)) -> - | AM24: =IF(OR($Z24="",$S24=""),0,$Z24*5%) -> 0 | AN24: =IF(OR($Z24="",$T24=""),0,$Z24*10%) -> 0 | AO24: =IF($Z24="",0,IF($U24="",0,$U24)) -> 0 | AP24: =SUM(AE24:AM24) -> #VALUE!
A25: 25 | D25: "Create Asset from Template" Add BPM support (Discussion Required) | F25: RnD | G25: Faster Impl | K25: 2 | L25: UnPlan | V25: =SUM(M25:U25) -> 0 | W25: =V25 - (V25 * (SUBSTITUTE(SUBSTITUTE($W$2, "Optimistic (", ""), "%)", "") / 100)) -> 0 | X25: =V25 + (W25 * (SUBSTITUTE(SUBSTITUTE($W$2, "Optimistic (", ""), "%)", "") / 100)) -> 0 | Y25: =(W25+(4*V25)+X25)/6 -> 0 | Z25: =Y25/2 -> 0 | AE25: =IF($Z25="",0,IF($M25="",0,$M25)) -> 0 | AF25: =IF(OR($Z25="",$N25=""),0,$Z25*5%) -> 0 | AG25: =IF(OR($Z25="",$O25=""),0,$Z25*10%) -> 0 | AH25: =IF($Z25="",0,IF(AND($P25="",$Q25=""),($Z25-$AE25-$AF25-$AG25-$AI25-$AK25-$AL25-$AM25-$AN25-$AO25),IF($P25="",0,IF($Q25="",($Z25-$AE25-$AF25-$AG25-$AI25-$AK25-$AL25-$AM25-$AN25-$AO25),($Z25-$AE25-$AF25-$AG25-$AI25-$AK25-$AL25-$AM25-$AN25-$AO25)*40%/(40%+15%))))) -> 0 | AI25: =IF($Z25="",0,IF($P25="",0,0.5)) -> 0 | AJ25: =IF($Z25="",0,IF(AND($P25="",$Q25=""),0,IF($Q25="",0,IF($P25="",($Z25-$AE25-$AF25-$AG25-$AI25-$AK25-$AL25-$AM25-$AN25-$AO25),($Z25-$AE25-$AF25-$AG25-$AI25-$AK25-$AL25-$AM25-$AN25-$AO25)*15%/(40%+15%))))) -> 0 | AK25: =IF($Z25="",0,$Z25*15%) -> 0 | AL25: =IF($Z25="",0,IF($R25="",0,$R25)) -> 0 | AM25: =IF(OR($Z25="",$S25=""),0,$Z25*5%) -> 0 | AN25: =IF(OR($Z25="",$T25=""),0,$Z25*10%) -> 0 | AO25: =IF($Z25="",0,IF($U25="",0,$U25)) -> 0 | AP25: =SUM(AE25:AM25) -> 0
A26: 26 | C26: Enterprise connectors | D26: Enterprise Connectors Pipeline OnDemand Trigger | F26: Imp Team | G26: Faster Impl | H26: 3 | K26: 3 | L26: UnPlan | V26: =SUM(M26:U26) -> 0 | W26: =V26 - (V26 * (SUBSTITUTE(SUBSTITUTE($W$2, "Optimistic (", ""), "%)", "") / 100)) -> 0 | X26: =V26 + (W26 * (SUBSTITUTE(SUBSTITUTE($W$2, "Optimistic (", ""), "%)", "") / 100)) -> 0 | Y26: =(W26+(4*V26)+X26)/6 -> 0 | Z26: =Y26/2 -> 0 | AE26: =IF($Z26="",0,IF($M26="",0,$M26)) -> 0 | AF26: =IF(OR($Z26="",$N26=""),0,$Z26*5%) -> 0 | AG26: =IF(OR($Z26="",$O26=""),0,$Z26*10%) -> 0 | AH26: =IF($Z26="",0,IF(AND($P26="",$Q26=""),($Z26-$AE26-$AF26-$AG26-$AI26-$AK26-$AL26-$AM26-$AN26-$AO26),IF($P26="",0,IF($Q26="",($Z26-$AE26-$AF26-$AG26-$AI26-$AK26-$AL26-$AM26-$AN26-$AO26),($Z26-$AE26-$AF26-$AG26-$AI26-$AK26-$AL26-$AM26-$AN26-$AO26)*40%/(40%+15%))))) -> 0 | AI26: =IF($Z26="",0,IF($P26="",0,0.5)) -> 0 | AJ26: =IF($Z26="",0,IF(AND($P26="",$Q26=""),0,IF($Q26="",0,IF($P26="",($Z26-$AE26-$AF26-$AG26-$AI26-$AK26-$AL26-$AM26-$AN26-$AO26),($Z26-$AE26-$AF26-$AG26-$AI26-$AK26-$AL26-$AM26-$AN26-$AO26)*15%/(40%+15%))))) -> 0 | AK26: =IF($Z26="",0,$Z26*15%) -> 0 | AL26: =IF($Z26="",0,IF($R26="",0,$R26)) -> 0 | AM26: =IF(OR($Z26="",$S26=""),0,$Z26*5%) -> 0 | AN26: =IF(OR($Z26="",$T26=""),0,$Z26*10%) -> 0 | AO26: =IF($Z26="",0,IF($U26="",0,$U26)) -> 0 | AP26: =SUM(AE26:AM26) -> 0 | AQ26: In the meantime we should document the process of achieving that as project implementation
A27: 27 | D27: IT/OT Conversion for Enterprise Connectors (on hold) | F27: RnD | H27: 3 | K27: 1 | L27: UnPlan | V27: =SUM(M27:U27) -> 0 | W27: =V27 - (V27 * (SUBSTITUTE(SUBSTITUTE($W$2, "Optimistic (", ""), "%)", "") / 100)) -> 0 | X27: =V27 + (W27 * (SUBSTITUTE(SUBSTITUTE($W$2, "Optimistic (", ""), "%)", "") / 100)) -> 0 | Y27: =(W27+(4*V27)+X27)/6 -> 0 | Z27: =Y27/2 -> 0 | AE27: =IF($Z27="",0,IF($M27="",0,$M27)) -> 0 | AF27: =IF(OR($Z27="",$N27=""),0,$Z27*5%) -> 0 | AG27: =IF(OR($Z27="",$O27=""),0,$Z27*10%) -> 0 | AH27: =IF($Z27="",0,IF(AND($P27="",$Q27=""),($Z27-$AE27-$AF27-$AG27-$AI27-$AK27-$AL27-$AM27-$AN27-$AO27),IF($P27="",0,IF($Q27="",($Z27-$AE27-$AF27-$AG27-$AI27-$AK27-$AL27-$AM27-$AN27-$AO27),($Z27-$AE27-$AF27-$AG27-$AI27-$AK27-$AL27-$AM27-$AN27-$AO27)*40%/(40%+15%))))) -> 0 | AI27: =IF($Z27="",0,IF($P27="",0,0.5)) -> 0 | AJ27: =IF($Z27="",0,IF(AND($P27="",$Q27=""),0,IF($Q27="",0,IF($P27="",($Z27-$AE27-$AF27-$AG27-$AI27-$AK27-$AL27-$AM27-$AN27-$AO27),($Z27-$AE27-$AF27-$AG27-$AI27-$AK27-$AL27-$AM27-$AN27-$AO27)*15%/(40%+15%))))) -> 0 | AK27: =IF($Z27="",0,$Z27*15%) -> 0 | AL27: =IF($Z27="",0,IF($R27="",0,$R27)) -> 0 | AM27: =IF(OR($Z27="",$S27=""),0,$Z27*5%) -> 0 | AN27: =IF(OR($Z27="",$T27=""),0,$Z27*10%) -> 0 | AO27: =IF($Z27="",0,IF($U27="",0,$U27)) -> 0 | AP27: =SUM(AE27:AM27) -> 0
A28: 28 | C28: Calculated Tags Enhancement | D28: Nesting of Counter, Timer, Totalizer | E28: https://octopusdtlsupport.atlassian.net/browse/O2-697 | F28: RnD | H28: 1 | K28: 2 | L28: Plan | O28: 2 | P28: 20 | Q28: 15 | S28: 4 | T28: 25 | U28: =7+10+2 -> 19 | V28: =SUM(M28:U28) -> 85 | W28: =V28 - (V28 * (SUBSTITUTE(SUBSTITUTE($W$2, "Optimistic (", ""), "%)", "") / 100)) -> 42.5 | X28: =V28 + (W28 * (SUBSTITUTE(SUBSTITUTE($W$2, "Optimistic (", ""), "%)", "") / 100)) -> 106.25 | Y28: =(W28+(4*V28)+X28)/6 -> 81.458333 | Z28: =Y28/2 -> 40.729167 | AA28: 46146 | AB28: 46163 | AC28: 46164 | AD28: 46171 | AE28: =IF($Z28="",0,IF($M28="",0,$M28)) -> 0 | AF28: =IF(OR($Z28="",$N28=""),0,$Z28*5%) -> 0 | AG28: =IF(OR($Z28="",$O28=""),0,$Z28*10%) -> 4.0729167 | AH28: =IF($Z28="",0,IF(AND($P28="",$Q28=""),($Z28-$AE28-$AF28-$AG28-$AI28-$AK28-$AL28-$AM28-$AN28-$AO28),IF($P28="",0,IF($Q28="",($Z28-$AE28-$AF28-$AG28-$AI28-$AK28-$AL28-$AM28-$AN28-$AO28),($Z28-$AE28-$AF28-$AG28-$AI28-$AK28-$AL28-$AM28-$AN28-$AO28)*40%/(40%+15%))))) -> 3.5909091 | AI28: =IF($Z28="",0,IF($P28="",0,0.5)) -> 0.5 | AJ28: =IF($Z28="",0,IF(AND($P28="",$Q28=""),0,IF($Q28="",0,IF($P28="",($Z28-$AE28-$AF28-$AG28-$AI28-$AK28-$AL28-$AM28-$AN28-$AO28),($Z28-$AE28-$AF28-$AG28-$AI28-$AK28-$AL28-$AM28-$AN28-$AO28)*15%/(40%+15%))))) -> 1.3465909 | AK28: =IF($Z28="",0,$Z28*15%) -> 6.109375 | AL28: =IF($Z28="",0,IF($R28="",0,$R28)) -> 0 | AM28: =IF(OR($Z28="",$S28=""),0,$Z28*5%) -> 2.0364583 | AN28: =IF(OR($Z28="",$T28=""),0,$Z28*10%) -> 4.0729167 | AO28: =IF($Z28="",0,IF($U28="",0,$U28)) -> 19 | AP28: =SUM(AE28:AM28) -> 17.65625 | AQ28: Thought it was already done
A29: 29 | C29: Anomaly Detection Engine (ADE) | D29: ADE for Batch/BPM IT Data (Discussion Requried) | F29: RnD | H29: 2 | K29: 1+ | L29: UnPlan | W29: =V29 - (V29 * (SUBSTITUTE(SUBSTITUTE($W$2, "Optimistic (", ""), "%)", "") / 100)) -> 0 | X29: =V29 + (W29 * (SUBSTITUTE(SUBSTITUTE($W$2, "Optimistic (", ""), "%)", "") / 100)) -> 0 | Y29: =(W29+(4*V29)+X29)/6 -> 0 | Z29: =Y29/2 -> 0 | AE29: =IF($Z29="",0,IF($M29="",0,$M29)) -> 0 | AF29: =IF(OR($Z29="",$N29=""),0,$Z29*5%) -> 0 | AG29: =IF(OR($Z29="",$O29=""),0,$Z29*10%) -> 0 | AH29: =IF($Z29="",0,IF(AND($P29="",$Q29=""),($Z29-$AE29-$AF29-$AG29-$AI29-$AK29-$AL29-$AM29-$AN29-$AO29),IF($P29="",0,IF($Q29="",($Z29-$AE29-$AF29-$AG29-$AI29-$AK29-$AL29-$AM29-$AN29-$AO29),($Z29-$AE29-$AF29-$AG29-$AI29-$AK29-$AL29-$AM29-$AN29-$AO29)*40%/(40%+15%))))) -> 0 | AI29: =IF($Z29="",0,IF($P29="",0,0.5)) -> 0 | AJ29: =IF($Z29="",0,IF(AND($P29="",$Q29=""),0,IF($Q29="",0,IF($P29="",($Z29-$AE29-$AF29-$AG29-$AI29-$AK29-$AL29-$AM29-$AN29-$AO29),($Z29-$AE29-$AF29-$AG29-$AI29-$AK29-$AL29-$AM29-$AN29-$AO29)*15%/(40%+15%))))) -> 0 | AK29: =IF($Z29="",0,$Z29*15%) -> 0 | AL29: =IF($Z29="",0,IF($R29="",0,$R29)) -> 0 | AM29: =IF(OR($Z29="",$S29=""),0,$Z29*5%) -> 0 | AN29: =IF(OR($Z29="",$T29=""),0,$Z29*10%) -> 0 | AO29: =IF($Z29="",0,IF($U29="",0,$U29)) -> 0 | AP29: =SUM(AE29:AM29) -> 0
A30: 30 | D30: ADE for Enterprise Connectors IT Data (Discussion Required) | F30: RnD | L30: UnPlan | V30: =SUM(M30:U30) -> 0 | W30: =V30 - (V30 * (SUBSTITUTE(SUBSTITUTE($W$2, "Optimistic (", ""), "%)", "") / 100)) -> 0 | X30: =V30 + (W30 * (SUBSTITUTE(SUBSTITUTE($W$2, "Optimistic (", ""), "%)", "") / 100)) -> 0 | Y30: =(W30+(4*V30)+X30)/6 -> 0 | Z30: =Y30/2 -> 0 | AE30: =IF($Z30="",0,IF($M30="",0,$M30)) -> 0 | AF30: =IF(OR($Z30="",$N30=""),0,$Z30*5%) -> 0 | AG30: =IF(OR($Z30="",$O30=""),0,$Z30*10%) -> 0 | AH30: =IF($Z30="",0,IF(AND($P30="",$Q30=""),($Z30-$AE30-$AF30-$AG30-$AI30-$AK30-$AL30-$AM30-$AN30-$AO30),IF($P30="",0,IF($Q30="",($Z30-$AE30-$AF30-$AG30-$AI30-$AK30-$AL30-$AM30-$AN30-$AO30),($Z30-$AE30-$AF30-$AG30-$AI30-$AK30-$AL30-$AM30-$AN30-$AO30)*40%/(40%+15%))))) -> 0 | AI30: =IF($Z30="",0,IF($P30="",0,0.5)) -> 0 | AJ30: =IF($Z30="",0,IF(AND($P30="",$Q30=""),0,IF($Q30="",0,IF($P30="",($Z30-$AE30-$AF30-$AG30-$AI30-$AK30-$AL30-$AM30-$AN30-$AO30),($Z30-$AE30-$AF30-$AG30-$AI30-$AK30-$AL30-$AM30-$AN30-$AO30)*15%/(40%+15%))))) -> 0 | AK30: =IF($Z30="",0,$Z30*15%) -> 0 | AL30: =IF($Z30="",0,IF($R30="",0,$R30)) -> 0 | AM30: =IF(OR($Z30="",$S30=""),0,$Z30*5%) -> 0 | AN30: =IF(OR($Z30="",$T30=""),0,$Z30*10%) -> 0 | AO30: =IF($Z30="",0,IF($U30="",0,$U30)) -> 0 | AP30: =SUM(AE30:AM30) -> 0
A31: 31 | C31: Alarm | D31: Alarms for Batch IT Data | E31: https://octopusdtlsupport.atlassian.net/browse/O2-2277 | F31: RnD | H31: 1 | K31: 3 | L31: UnPlan | O31: 3 | P31: =(21+3) -> 24 | Q31: 5 | S31: 1 | T31: 5 | V31: =SUM(M31:U31) -> 38 | W31: =V31 - (V31 * (SUBSTITUTE(SUBSTITUTE($W$2, "Optimistic (", ""), "%)", "") / 100)) -> 19 | X31: =V31 + (W31 * (SUBSTITUTE(SUBSTITUTE($W$2, "Optimistic (", ""), "%)", "") / 100)) -> 47.5 | Y31: =(W31+(4*V31)+X31)/6 -> 36.416667 | Z31: =Y31/2 -> 18.208333 | AA31: 46121 | AB31: 46134 | AC31: 46135 | AD31: 46142 | AE31: =IF($Z31="",0,IF($M31="",0,$M31)) -> 0 | AF31: =IF(OR($Z31="",$N31=""),0,$Z31*5%) -> 0 | AG31: =IF(OR($Z31="",$O31=""),0,$Z31*10%) -> 1.8208333 | AH31: =IF($Z31="",0,IF(AND($P31="",$Q31=""),($Z31-$AE31-$AF31-$AG31-$AI31-$AK31-$AL31-$AM31-$AN31-$AO31),IF($P31="",0,IF($Q31="",($Z31-$AE31-$AF31-$AG31-$AI31-$AK31-$AL31-$AM31-$AN31-$AO31),($Z31-$AE31-$AF31-$AG31-$AI31-$AK31-$AL31-$AM31-$AN31-$AO31)*40%/(40%+15%))))) -> 7.5818182 | AI31: =IF($Z31="",0,IF($P31="",0,0.5)) -> 0.5 | AJ31: =IF($Z31="",0,IF(AND($P31="",$Q31=""),0,IF($Q31="",0,IF($P31="",($Z31-$AE31-$AF31-$AG31-$AI31-$AK31-$AL31-$AM31-$AN31-$AO31),($Z31-$AE31-$AF31-$AG31-$AI31-$AK31-$AL31-$AM31-$AN31-$AO31)*15%/(40%+15%))))) -> 2.8431818 | AK31: =IF($Z31="",0,$Z31*15%) -> 2.73125 | AL31: =IF($Z31="",0,IF($R31="",0,$R31)) -> 0 | AM31: =IF(OR($Z31="",$S31=""),0,$Z31*5%) -> 0.91041667 | AN31: =IF(OR($Z31="",$T31=""),0,$Z31*10%) -> 1.8208333 | AO31: =IF($Z31="",0,IF($U31="",0,$U31)) -> 0 | AP31: =SUM(AE31:AM31) -> 16.3875
D32: Alarms for BPM IT Data | E32: https://octopusdtlsupport.atlassian.net/browse/O2-2278 | F32: RnD | H32: 1 | K32: 3 | L32: UnPlan | O32: 6 | P32: =(21+6) -> 27 | Q32: 5 | S32: 1 | T32: 5 | V32: =SUM(M32:U32) -> 44 | W32: =V32 - (V32 * (SUBSTITUTE(SUBSTITUTE($W$2, "Optimistic (", ""), "%)", "") / 100)) -> 22 | X32: =V32 + (W32 * (SUBSTITUTE(SUBSTITUTE($W$2, "Optimistic (", ""), "%)", "") / 100)) -> 55 | Y32: =(W32+(4*V32)+X32)/6 -> 42.166667 | Z32: =Y32/2 -> 21.083333 | AA32: 46146 | AB32: 46167 | AC32: 46168 | AD32: 46175 | AE32: =IF($Z32="",0,IF($M32="",0,$M32)) -> 0 | AF32: =IF(OR($Z32="",$N32=""),0,$Z32*5%) -> 0 | AG32: =IF(OR($Z32="",$O32=""),0,$Z32*10%) -> 2.1083333 | AH32: =IF($Z32="",0,IF(AND($P32="",$Q32=""),($Z32-$AE32-$AF32-$AG32-$AI32-$AK32-$AL32-$AM32-$AN32-$AO32),IF($P32="",0,IF($Q32="",($Z32-$AE32-$AF32-$AG32-$AI32-$AK32-$AL32-$AM32-$AN32-$AO32),($Z32-$AE32-$AF32-$AG32-$AI32-$AK32-$AL32-$AM32-$AN32-$AO32)*40%/(40%+15%))))) -> 8.8363636 | AI32: =IF($Z32="",0,IF($P32="",0,0.5)) -> 0.5 | AJ32: =IF($Z32="",0,IF(AND($P32="",$Q32=""),0,IF($Q32="",0,IF($P32="",($Z32-$AE32-$AF32-$AG32-$AI32-$AK32-$AL32-$AM32-$AN32-$AO32),($Z32-$AE32-$AF32-$AG32-$AI32-$AK32-$AL32-$AM32-$AN32-$AO32)*15%/(40%+15%))))) -> 3.3136364 | AK32: =IF($Z32="",0,$Z32*15%) -> 3.1625 | AL32: =IF($Z32="",0,IF($R32="",0,$R32)) -> 0 | AM32: =IF(OR($Z32="",$S32=""),0,$Z32*5%) -> 1.0541667 | AN32: =IF(OR($Z32="",$T32=""),0,$Z32*10%) -> 2.1083333 | AO32: =IF($Z32="",0,IF($U32="",0,$U32)) -> 0 | AP32: =SUM(AE32:AM32) -> 18.975
A33: 32 | D33: Alarms for Enterprise Connectors IT Data SQL | E33: https://octopusdtlsupport.atlassian.net/browse/O2-2279 | F33: RnD | L33: UnPlan | O33: 3 | P33: =(12+3) -> 15 | Q33: 5 | T33: 5 | V33: =SUM(M33:U33) -> 28 | W33: =V33 - (V33 * (SUBSTITUTE(SUBSTITUTE($W$2, "Optimistic (", ""), "%)", "") / 100)) -> 14 | X33: =V33 + (W33 * (SUBSTITUTE(SUBSTITUTE($W$2, "Optimistic (", ""), "%)", "") / 100)) -> 35 | Y33: =(W33+(4*V33)+X33)/6 -> 26.833333 | Z33: =Y33/2 -> 13.416667 | AA33: 46169 | AB33: 46178 | AC33: 46181 | AD33: 46188 | AE33: =IF($Z33="",0,IF($M33="",0,$M33)) -> 0 | AF33: =IF(OR($Z33="",$N33=""),0,$Z33*5%) -> 0 | AG33: =IF(OR($Z33="",$O33=""),0,$Z33*10%) -> 1.3416667 | AH33: =IF($Z33="",0,IF(AND($P33="",$Q33=""),($Z33-$AE33-$AF33-$AG33-$AI33-$AK33-$AL33-$AM33-$AN33-$AO33),IF($P33="",0,IF($Q33="",($Z33-$AE33-$AF33-$AG33-$AI33-$AK33-$AL33-$AM33-$AN33-$AO33),($Z33-$AE33-$AF33-$AG33-$AI33-$AK33-$AL33-$AM33-$AN33-$AO33)*40%/(40%+15%))))) -> 5.9787879 | AI33: =IF($Z33="",0,IF($P33="",0,0.5)) -> 0.5 | AJ33: =IF($Z33="",0,IF(AND($P33="",$Q33=""),0,IF($Q33="",0,IF($P33="",($Z33-$AE33-$AF33-$AG33-$AI33-$AK33-$AL33-$AM33-$AN33-$AO33),($Z33-$AE33-$AF33-$AG33-$AI33-$AK33-$AL33-$AM33-$AN33-$AO33)*15%/(40%+15%))))) -> 2.2420455 | AK33: =IF($Z33="",0,$Z33*15%) -> 2.0125 | AL33: =IF($Z33="",0,IF($R33="",0,$R33)) -> 0 | AM33: =IF(OR($Z33="",$S33=""),0,$Z33*5%) -> 0 | AN33: =IF(OR($Z33="",$T33=""),0,$Z33*10%) -> 1.3416667 | AO33: =IF($Z33="",0,IF($U33="",0,$U33)) -> 0 | AP33: =SUM(AE33:AM33) -> 12.075
A34: 33 | D34: Alarms for Enterprise Connectors IT Data Rest API | E34: https://octopusdtlsupport.atlassian.net/browse/O2-2280 | F34: RnD | O34: 3 | P34: =(12+3) -> 15 | Q34: 5 | T34: 5 | V34: =SUM(M34:U34) -> 28 | W34: =V34 - (V34 * (SUBSTITUTE(SUBSTITUTE($W$2, "Optimistic (", ""), "%)", "") / 100)) -> 14 | X34: =V34 + (W34 * (SUBSTITUTE(SUBSTITUTE($W$2, "Optimistic (", ""), "%)", "") / 100)) -> 35 | Y34: =(W34+(4*V34)+X34)/6 -> 26.833333 | Z34: =Y34/2 -> 13.416667 | AA34: 46182 | AB34: 46191 | AC34: 46192 | AD34: 46199 | AE34: =IF($Z34="",0,IF($M34="",0,$M34)) -> 0 | AF34: =IF(OR($Z34="",$N34=""),0,$Z34*5%) -> 0 | AG34: =IF(OR($Z34="",$O34=""),0,$Z34*10%) -> 1.3416667 | AH34: =IF($Z34="",0,IF(AND($P34="",$Q34=""),($Z34-$AE34-$AF34-$AG34-$AI34-$AK34-$AL34-$AM34-$AN34-$AO34),IF($P34="",0,IF($Q34="",($Z34-$AE34-$AF34-$AG34-$AI34-$AK34-$AL34-$AM34-$AN34-$AO34),($Z34-$AE34-$AF34-$AG34-$AI34-$AK34-$AL34-$AM34-$AN34-$AO34)*40%/(40%+15%))))) -> 5.9787879 | AI34: =IF($Z34="",0,IF($P34="",0,0.5)) -> 0.5 | AJ34: =IF($Z34="",0,IF(AND($P34="",$Q34=""),0,IF($Q34="",0,IF($P34="",($Z34-$AE34-$AF34-$AG34-$AI34-$AK34-$AL34-$AM34-$AN34-$AO34),($Z34-$AE34-$AF34-$AG34-$AI34-$AK34-$AL34-$AM34-$AN34-$AO34)*15%/(40%+15%))))) -> 2.2420455 | AK34: =IF($Z34="",0,$Z34*15%) -> 2.0125 | AL34: =IF($Z34="",0,IF($R34="",0,$R34)) -> 0 | AM34: =IF(OR($Z34="",$S34=""),0,$Z34*5%) -> 0 | AN34: =IF(OR($Z34="",$T34=""),0,$Z34*10%) -> 1.3416667 | AO34: =IF($Z34="",0,IF($U34="",0,$U34)) -> 0 | AP34: =SUM(AE34:AM34) -> 12.075
A35: 34 | D35: Alarms for Enterprise Connectors IT Data SFTP | E35: https://octopusdtlsupport.atlassian.net/browse/O2-2296 | F35: RnD | O35: 3 | P35: =(12+3) -> 15 | Q35: 5 | T35: 5 | V35: =SUM(M35:U35) -> 28 | W35: =V35 - (V35 * (SUBSTITUTE(SUBSTITUTE($W$2, "Optimistic (", ""), "%)", "") / 100)) -> 14 | X35: =V35 + (W35 * (SUBSTITUTE(SUBSTITUTE($W$2, "Optimistic (", ""), "%)", "") / 100)) -> 35 | Y35: =(W35+(4*V35)+X35)/6 -> 26.833333 | Z35: =Y35/2 -> 13.416667 | AA35: 46195 | AB35: 46204 | AC35: 46205 | AD35: 46212 | AE35: =IF($Z35="",0,IF($M35="",0,$M35)) -> 0 | AF35: =IF(OR($Z35="",$N35=""),0,$Z35*5%) -> 0 | AG35: =IF(OR($Z35="",$O35=""),0,$Z35*10%) -> 1.3416667 | AH35: =IF($Z35="",0,IF(AND($P35="",$Q35=""),($Z35-$AE35-$AF35-$AG35-$AI35-$AK35-$AL35-$AM35-$AN35-$AO35),IF($P35="",0,IF($Q35="",($Z35-$AE35-$AF35-$AG35-$AI35-$AK35-$AL35-$AM35-$AN35-$AO35),($Z35-$AE35-$AF35-$AG35-$AI35-$AK35-$AL35-$AM35-$AN35-$AO35)*40%/(40%+15%))))) -> 5.9787879 | AI35: =IF($Z35="",0,IF($P35="",0,0.5)) -> 0.5 | AJ35: =IF($Z35="",0,IF(AND($P35="",$Q35=""),0,IF($Q35="",0,IF($P35="",($Z35-$AE35-$AF35-$AG35-$AI35-$AK35-$AL35-$AM35-$AN35-$AO35),($Z35-$AE35-$AF35-$AG35-$AI35-$AK35-$AL35-$AM35-$AN35-$AO35)*15%/(40%+15%))))) -> 2.2420455 | AK35: =IF($Z35="",0,$Z35*15%) -> 2.0125 | AL35: =IF($Z35="",0,IF($R35="",0,$R35)) -> 0 | AM35: =IF(OR($Z35="",$S35=""),0,$Z35*5%) -> 0 | AN35: =IF(OR($Z35="",$T35=""),0,$Z35*10%) -> 1.3416667 | AO35: =IF($Z35="",0,IF($U35="",0,$U35)) -> 0 | AP35: =SUM(AE35:AM35) -> 12.075
A36: 35 | D36: Alarms for Enterprise Connectors IT Data SAP | E36: https://octopusdtlsupport.atlassian.net/browse/O2-2321 | F36: RnD | O36: 3 | P36: =(12+3) -> 15 | Q36: 5 | T36: 5 | V36: =SUM(M36:U36) -> 28 | W36: =V36 - (V36 * (SUBSTITUTE(SUBSTITUTE($W$2, "Optimistic (", ""), "%)", "") / 100)) -> 14 | X36: =V36 + (W36 * (SUBSTITUTE(SUBSTITUTE($W$2, "Optimistic (", ""), "%)", "") / 100)) -> 35 | Y36: =(W36+(4*V36)+X36)/6 -> 26.833333 | Z36: =Y36/2 -> 13.416667 | AA36: 46206 | AB36: 46217 | AC36: 46218 | AD36: 46225 | AE36: =IF($Z36="",0,IF($M36="",0,$M36)) -> 0 | AF36: =IF(OR($Z36="",$N36=""),0,$Z36*5%) -> 0 | AG36: =IF(OR($Z36="",$O36=""),0,$Z36*10%) -> 1.3416667 | AH36: =IF($Z36="",0,IF(AND($P36="",$Q36=""),($Z36-$AE36-$AF36-$AG36-$AI36-$AK36-$AL36-$AM36-$AN36-$AO36),IF($P36="",0,IF($Q36="",($Z36-$AE36-$AF36-$AG36-$AI36-$AK36-$AL36-$AM36-$AN36-$AO36),($Z36-$AE36-$AF36-$AG36-$AI36-$AK36-$AL36-$AM36-$AN36-$AO36)*40%/(40%+15%))))) -> 5.9787879 | AI36: =IF($Z36="",0,IF($P36="",0,0.5)) -> 0.5 | AJ36: =IF($Z36="",0,IF(AND($P36="",$Q36=""),0,IF($Q36="",0,IF($P36="",($Z36-$AE36-$AF36-$AG36-$AI36-$AK36-$AL36-$AM36-$AN36-$AO36),($Z36-$AE36-$AF36-$AG36-$AI36-$AK36-$AL36-$AM36-$AN36-$AO36)*15%/(40%+15%))))) -> 2.2420455 | AK36: =IF($Z36="",0,$Z36*15%) -> 2.0125 | AL36: =IF($Z36="",0,IF($R36="",0,$R36)) -> 0 | AM36: =IF(OR($Z36="",$S36=""),0,$Z36*5%) -> 0 | AN36: =IF(OR($Z36="",$T36=""),0,$Z36*10%) -> 1.3416667 | AO36: =IF($Z36="",0,IF($U36="",0,$U36)) -> 0 | AP36: =SUM(AE36:AM36) -> 12.075
A37: 36 | C37: Diagnostics | D37: ML based Tier 4 Diagnostics (Landing Pattern based alerts) | F37: RnD | H37: 1 | L37: UnPlan | P37: 4 | Q37: 3 | S37: 1 | V37: =SUM(M37:U37) -> 8 | W37: =V37 - (V37 * (SUBSTITUTE(SUBSTITUTE($W$2, "Optimistic (", ""), "%)", "") / 100)) -> 4 | X37: =V37 + (W37 * (SUBSTITUTE(SUBSTITUTE($W$2, "Optimistic (", ""), "%)", "") / 100)) -> 10 | Y37: =(W37+(4*V37)+X37)/6 -> 7.6666667 | Z37: =Y37/2 -> 3.8333333 | AE37: =IF($Z37="",0,IF($M37="",0,$M37)) -> 0 | AF37: =IF(OR($Z37="",$N37=""),0,$Z37*5%) -> 0 | AG37: =IF(OR($Z37="",$O37=""),0,$Z37*10%) -> 0 | AH37: =IF($Z37="",0,IF(AND($P37="",$Q37=""),($Z37-$AE37-$AF37-$AG37-$AI37-$AK37-$AL37-$AM37-$AN37-$AO37),IF($P37="",0,IF($Q37="",($Z37-$AE37-$AF37-$AG37-$AI37-$AK37-$AL37-$AM37-$AN37-$AO37),($Z37-$AE37-$AF37-$AG37-$AI37-$AK37-$AL37-$AM37-$AN37-$AO37)*40%/(40%+15%))))) -> 1.8666667 | AI37: =IF($Z37="",0,IF($P37="",0,0.5)) -> 0.5 | AJ37: =IF($Z37="",0,IF(AND($P37="",$Q37=""),0,IF($Q37="",0,IF($P37="",($Z37-$AE37-$AF37-$AG37-$AI37-$AK37-$AL37-$AM37-$AN37-$AO37),($Z37-$AE37-$AF37-$AG37-$AI37-$AK37-$AL37-$AM37-$AN37-$AO37)*15%/(40%+15%))))) -> 0.7 | AK37: =IF($Z37="",0,$Z37*15%) -> 0.575 | AL37: =IF($Z37="",0,IF($R37="",0,$R37)) -> 0 | AM37: =IF(OR($Z37="",$S37=""),0,$Z37*5%) -> 0.19166667 | AN37: =IF(OR($Z37="",$T37=""),0,$Z37*10%) -> 0 | AO37: =IF($Z37="",0,IF($U37="",0,$U37)) -> 0 | AP37: =SUM(AE37:AM37) -> 3.8333333
A38: 37 | C38: OmniOEE | D38: OmniOEE Phase 1 - Batch/BPM Std Compute Module (Curated, Library-stored) | F38: Management | H38: 3 | K38: 1 | L38: UnPlan | V38: =SUM(M38:U38) -> 0 | W38: =V38 - (V38 * (SUBSTITUTE(SUBSTITUTE($W$2, "Optimistic (", ""), "%)", "") / 100)) -> 0 | X38: =V38 + (W38 * (SUBSTITUTE(SUBSTITUTE($W$2, "Optimistic (", ""), "%)", "") / 100)) -> 0 | Y38: =(W38+(4*V38)+X38)/6 -> 0 | Z38: =Y38/2 -> 0 | AE38: =IF($Z38="",0,IF($M38="",0,$M38)) -> 0 | AF38: =IF(OR($Z38="",$N38=""),0,$Z38*5%) -> 0 | AG38: =IF(OR($Z38="",$O38=""),0,$Z38*10%) -> 0 | AH38: =IF($Z38="",0,IF(AND($P38="",$Q38=""),($Z38-$AE38-$AF38-$AG38-$AI38-$AK38-$AL38-$AM38-$AN38-$AO38),IF($P38="",0,IF($Q38="",($Z38-$AE38-$AF38-$AG38-$AI38-$AK38-$AL38-$AM38-$AN38-$AO38),($Z38-$AE38-$AF38-$AG38-$AI38-$AK38-$AL38-$AM38-$AN38-$AO38)*40%/(40%+15%))))) -> 0 | AI38: =IF($Z38="",0,IF($P38="",0,0.5)) -> 0 | AJ38: =IF($Z38="",0,IF(AND($P38="",$Q38=""),0,IF($Q38="",0,IF($P38="",($Z38-$AE38-$AF38-$AG38-$AI38-$AK38-$AL38-$AM38-$AN38-$AO38),($Z38-$AE38-$AF38-$AG38-$AI38-$AK38-$AL38-$AM38-$AN38-$AO38)*15%/(40%+15%))))) -> 0 | AK38: =IF($Z38="",0,$Z38*15%) -> 0 | AL38: =IF($Z38="",0,IF($R38="",0,$R38)) -> 0 | AM38: =IF(OR($Z38="",$S38=""),0,$Z38*5%) -> 0 | AN38: =IF(OR($Z38="",$T38=""),0,$Z38*10%) -> 0 | AO38: =IF($Z38="",0,IF($U38="",0,$U38)) -> 0 | AP38: =SUM(AE38:AM38) -> 0 | AQ38: Need to understand it. Also we should be able to document this and do it as project
A39: 38 | D39: OmniOEE Phase 2 – Full OEE System (Production Planning, Configuration, Data, Visualizations) | F39: Management | H39: 3 | K39: 2 | L39: UnPlan | W39: =V39 - (V39 * (SUBSTITUTE(SUBSTITUTE($W$2, "Optimistic (", ""), "%)", "") / 100)) -> 0 | X39: =V39 + (W39 * (SUBSTITUTE(SUBSTITUTE($W$2, "Optimistic (", ""), "%)", "") / 100)) -> 0 | Y39: =(W39+(4*V39)+X39)/6 -> 0 | Z39: =Y39/2 -> 0 | AE39: =IF($Z39="",0,IF($M39="",0,$M39)) -> 0 | AF39: =IF(OR($Z39="",$N39=""),0,$Z39*5%) -> 0 | AG39: =IF(OR($Z39="",$O39=""),0,$Z39*10%) -> 0 | AH39: =IF($Z39="",0,IF(AND($P39="",$Q39=""),($Z39-$AE39-$AF39-$AG39-$AI39-$AK39-$AL39-$AM39-$AN39-$AO39),IF($P39="",0,IF($Q39="",($Z39-$AE39-$AF39-$AG39-$AI39-$AK39-$AL39-$AM39-$AN39-$AO39),($Z39-$AE39-$AF39-$AG39-$AI39-$AK39-$AL39-$AM39-$AN39-$AO39)*40%/(40%+15%))))) -> 0 | AI39: =IF($Z39="",0,IF($P39="",0,0.5)) -> 0 | AJ39: =IF($Z39="",0,IF(AND($P39="",$Q39=""),0,IF($Q39="",0,IF($P39="",($Z39-$AE39-$AF39-$AG39-$AI39-$AK39-$AL39-$AM39-$AN39-$AO39),($Z39-$AE39-$AF39-$AG39-$AI39-$AK39-$AL39-$AM39-$AN39-$AO39)*15%/(40%+15%))))) -> 0 | AK39: =IF($Z39="",0,$Z39*15%) -> 0 | AL39: =IF($Z39="",0,IF($R39="",0,$R39)) -> 0 | AM39: =IF(OR($Z39="",$S39=""),0,$Z39*5%) -> 0 | AN39: =IF(OR($Z39="",$T39=""),0,$Z39*10%) -> 0 | AO39: =IF($Z39="",0,IF($U39="",0,$U39)) -> 0 | AP39: =SUM(AE39:AM39) -> 0
A40: 39 | C40: OmniALA | D40: Aux Load Advisor | F40: Management | H40: 3 | K40: 1 | L40: UnPlan | O40: 10 | V40: =SUM(M40:U40) -> 10 | W40: =V40 - (V40 * (SUBSTITUTE(SUBSTITUTE($W$2, "Optimistic (", ""), "%)", "") / 100)) -> 5 | X40: =V40 + (W40 * (SUBSTITUTE(SUBSTITUTE($W$2, "Optimistic (", ""), "%)", "") / 100)) -> 12.5 | Y40: =(W40+(4*V40)+X40)/6 -> 9.5833333 | Z40: =Y40/2 -> 4.7916667 | AE40: =IF($Z40="",0,IF($M40="",0,$M40)) -> 0 | AF40: =IF(OR($Z40="",$N40=""),0,$Z40*5%) -> 0 | AG40: =IF(OR($Z40="",$O40=""),0,$Z40*10%) -> 0.47916667 | AH40: =IF($Z40="",0,IF(AND($P40="",$Q40=""),($Z40-$AE40-$AF40-$AG40-$AI40-$AK40-$AL40-$AM40-$AN40-$AO40),IF($P40="",0,IF($Q40="",($Z40-$AE40-$AF40-$AG40-$AI40-$AK40-$AL40-$AM40-$AN40-$AO40),($Z40-$AE40-$AF40-$AG40-$AI40-$AK40-$AL40-$AM40-$AN40-$AO40)*40%/(40%+15%))))) -> 3.59375 | AI40: =IF($Z40="",0,IF($P40="",0,0.5)) -> 0 | AJ40: =IF($Z40="",0,IF(AND($P40="",$Q40=""),0,IF($Q40="",0,IF($P40="",($Z40-$AE40-$AF40-$AG40-$AI40-$AK40-$AL40-$AM40-$AN40-$AO40),($Z40-$AE40-$AF40-$AG40-$AI40-$AK40-$AL40-$AM40-$AN40-$AO40)*15%/(40%+15%))))) -> 0 | AK40: =IF($Z40="",0,$Z40*15%) -> 0.71875 | AL40: =IF($Z40="",0,IF($R40="",0,$R40)) -> 0 | AM40: =IF(OR($Z40="",$S40=""),0,$Z40*5%) -> 0 | AN40: =IF(OR($Z40="",$T40=""),0,$Z40*10%) -> 0 | AO40: =IF($Z40="",0,IF($U40="",0,$U40)) -> 0 | AP40: =SUM(AE40:AM40) -> 4.7916667 | AQ40: Document and make it sound as a product till we get an order
A41: 40 | C41: ML | D41: Pattern Recognition | F41: RnD | H41: 2 | K41: 1 | L41: UnPlan | O41: 2 | P41: 8 | Q41: 5 | S41: 5 | V41: =SUM(M41:U41) -> 20 | W41: =V41 - (V41 * (SUBSTITUTE(SUBSTITUTE($W$2, "Optimistic (", ""), "%)", "") / 100)) -> 10 | X41: =V41 + (W41 * (SUBSTITUTE(SUBSTITUTE($W$2, "Optimistic (", ""), "%)", "") / 100)) -> 25 | Y41: =(W41+(4*V41)+X41)/6 -> 19.166667 | Z41: =Y41/2 -> 9.5833333 | AE41: =IF($Z41="",0,IF($M41="",0,$M41)) -> 0 | AF41: =IF(OR($Z41="",$N41=""),0,$Z41*5%) -> 0 | AG41: =IF(OR($Z41="",$O41=""),0,$Z41*10%) -> 0.95833333 | AH41: =IF($Z41="",0,IF(AND($P41="",$Q41=""),($Z41-$AE41-$AF41-$AG41-$AI41-$AK41-$AL41-$AM41-$AN41-$AO41),IF($P41="",0,IF($Q41="",($Z41-$AE41-$AF41-$AG41-$AI41-$AK41-$AL41-$AM41-$AN41-$AO41),($Z41-$AE41-$AF41-$AG41-$AI41-$AK41-$AL41-$AM41-$AN41-$AO41)*40%/(40%+15%))))) -> 4.5151515 | AI41: =IF($Z41="",0,IF($P41="",0,0.5)) -> 0.5 | AJ41: =IF($Z41="",0,IF(AND($P41="",$Q41=""),0,IF($Q41="",0,IF($P41="",($Z41-$AE41-$AF41-$AG41-$AI41-$AK41-$AL41-$AM41-$AN41-$AO41),($Z41-$AE41-$AF41-$AG41-$AI41-$AK41-$AL41-$AM41-$AN41-$AO41)*15%/(40%+15%))))) -> 1.6931818 | AK41: =IF($Z41="",0,$Z41*15%) -> 1.4375 | AL41: =IF($Z41="",0,IF($R41="",0,$R41)) -> 0 | AM41: =IF(OR($Z41="",$S41=""),0,$Z41*5%) -> 0.47916667 | AN41: =IF(OR($Z41="",$T41=""),0,$Z41*10%) -> 0 | AO41: =IF($Z41="",0,IF($U41="",0,$U41)) -> 0 | AP41: =SUM(AE41:AM41) -> 9.5833333 | AQ41: This should be very easy to implement using AI coding assistance
A42: 41 | D42: Forcasting | F42: RnD | H42: 2 | K42: 1 | L42: UnPlan | V42: =SUM(M42:U42) -> 0 | W42: =V42 - (V42 * (SUBSTITUTE(SUBSTITUTE($W$2, "Optimistic (", ""), "%)", "") / 100)) -> 0 | X42: =V42 + (W42 * (SUBSTITUTE(SUBSTITUTE($W$2, "Optimistic (", ""), "%)", "") / 100)) -> 0 | Y42: =(W42+(4*V42)+X42)/6 -> 0 | Z42: =Y42/2 -> 0 | AE42: =IF($Z42="",0,IF($M42="",0,$M42)) -> 0 | AF42: =IF(OR($Z42="",$N42=""),0,$Z42*5%) -> 0 | AG42: =IF(OR($Z42="",$O42=""),0,$Z42*10%) -> 0 | AH42: =IF($Z42="",0,IF(AND($P42="",$Q42=""),($Z42-$AE42-$AF42-$AG42-$AI42-$AK42-$AL42-$AM42-$AN42-$AO42),IF($P42="",0,IF($Q42="",($Z42-$AE42-$AF42-$AG42-$AI42-$AK42-$AL42-$AM42-$AN42-$AO42),($Z42-$AE42-$AF42-$AG42-$AI42-$AK42-$AL42-$AM42-$AN42-$AO42)*40%/(40%+15%))))) -> 0 | AI42: =IF($Z42="",0,IF($P42="",0,0.5)) -> 0 | AJ42: =IF($Z42="",0,IF(AND($P42="",$Q42=""),0,IF($Q42="",0,IF($P42="",($Z42-$AE42-$AF42-$AG42-$AI42-$AK42-$AL42-$AM42-$AN42-$AO42),($Z42-$AE42-$AF42-$AG42-$AI42-$AK42-$AL42-$AM42-$AN42-$AO42)*15%/(40%+15%))))) -> 0 | AK42: =IF($Z42="",0,$Z42*15%) -> 0 | AL42: =IF($Z42="",0,IF($R42="",0,$R42)) -> 0 | AM42: =IF(OR($Z42="",$S42=""),0,$Z42*5%) -> 0 | AN42: =IF(OR($Z42="",$T42=""),0,$Z42*10%) -> 0 | AO42: =IF($Z42="",0,IF($U42="",0,$U42)) -> 0 | AP42: =SUM(AE42:AM42) -> 0 | AQ42: This should be very easy to implement using AI coding assistance
A43: 42 | B43: Output | C43: OmniAgent | D43: Multi Agent Support | F43: RnD | K43: 1 | L43: UnPlan | O43: 1 | P43: 2 | Q43: 2 | S43: 1 | V43: =SUM(M43:U43) -> 6 | W43: =V43 - (V43 * (SUBSTITUTE(SUBSTITUTE($W$2, "Optimistic (", ""), "%)", "") / 100)) -> 3 | X43: =V43 + (W43 * (SUBSTITUTE(SUBSTITUTE($W$2, "Optimistic (", ""), "%)", "") / 100)) -> 7.5 | Y43: =(W43+(4*V43)+X43)/6 -> 5.75 | Z43: =Y43/2 -> 2.875 | AE43: =IF($Z43="",0,IF($M43="",0,$M43)) -> 0 | AF43: =IF(OR($Z43="",$N43=""),0,$Z43*5%) -> 0 | AG43: =IF(OR($Z43="",$O43=""),0,$Z43*10%) -> 0.2875 | AH43: =IF($Z43="",0,IF(AND($P43="",$Q43=""),($Z43-$AE43-$AF43-$AG43-$AI43-$AK43-$AL43-$AM43-$AN43-$AO43),IF($P43="",0,IF($Q43="",($Z43-$AE43-$AF43-$AG43-$AI43-$AK43-$AL43-$AM43-$AN43-$AO43),($Z43-$AE43-$AF43-$AG43-$AI43-$AK43-$AL43-$AM43-$AN43-$AO43)*40%/(40%+15%))))) -> 1.1 | AI43: =IF($Z43="",0,IF($P43="",0,0.5)) -> 0.5 | AJ43: =IF($Z43="",0,IF(AND($P43="",$Q43=""),0,IF($Q43="",0,IF($P43="",($Z43-$AE43-$AF43-$AG43-$AI43-$AK43-$AL43-$AM43-$AN43-$AO43),($Z43-$AE43-$AF43-$AG43-$AI43-$AK43-$AL43-$AM43-$AN43-$AO43)*15%/(40%+15%))))) -> 0.4125 | AK43: =IF($Z43="",0,$Z43*15%) -> 0.43125 | AL43: =IF($Z43="",0,IF($R43="",0,$R43)) -> 0 | AM43: =IF(OR($Z43="",$S43=""),0,$Z43*5%) -> 0.14375 | AN43: =IF(OR($Z43="",$T43=""),0,$Z43*10%) -> 0 | AO43: =IF($Z43="",0,IF($U43="",0,$U43)) -> 0 | AP43: =SUM(AE43:AM43) -> 2.875 | AQ43: What is this?
A44: 43 | D44: ADE to AutoPrompt to OmniAgent to RCA/Advice | F44: Management | H44: 1 | K44: 1+ | L44: UnPlan | V44: =SUM(M44:U44) -> 0 | W44: =V44 - (V44 * (SUBSTITUTE(SUBSTITUTE($W$2, "Optimistic (", ""), "%)", "") / 100)) -> 0 | X44: =V44 + (W44 * (SUBSTITUTE(SUBSTITUTE($W$2, "Optimistic (", ""), "%)", "") / 100)) -> 0 | Y44: =(W44+(4*V44)+X44)/6 -> 0 | Z44: =Y44/2 -> 0 | AE44: =IF($Z44="",0,IF($M44="",0,$M44)) -> 0 | AF44: =IF(OR($Z44="",$N44=""),0,$Z44*5%) -> 0 | AG44: =IF(OR($Z44="",$O44=""),0,$Z44*10%) -> 0 | AH44: =IF($Z44="",0,IF(AND($P44="",$Q44=""),($Z44-$AE44-$AF44-$AG44-$AI44-$AK44-$AL44-$AM44-$AN44-$AO44),IF($P44="",0,IF($Q44="",($Z44-$AE44-$AF44-$AG44-$AI44-$AK44-$AL44-$AM44-$AN44-$AO44),($Z44-$AE44-$AF44-$AG44-$AI44-$AK44-$AL44-$AM44-$AN44-$AO44)*40%/(40%+15%))))) -> 0 | AI44: =IF($Z44="",0,IF($P44="",0,0.5)) -> 0 | AJ44: =IF($Z44="",0,IF(AND($P44="",$Q44=""),0,IF($Q44="",0,IF($P44="",($Z44-$AE44-$AF44-$AG44-$AI44-$AK44-$AL44-$AM44-$AN44-$AO44),($Z44-$AE44-$AF44-$AG44-$AI44-$AK44-$AL44-$AM44-$AN44-$AO44)*15%/(40%+15%))))) -> 0 | AK44: =IF($Z44="",0,$Z44*15%) -> 0 | AL44: =IF($Z44="",0,IF($R44="",0,$R44)) -> 0 | AM44: =IF(OR($Z44="",$S44=""),0,$Z44*5%) -> 0 | AN44: =IF(OR($Z44="",$T44=""),0,$Z44*10%) -> 0 | AO44: =IF($Z44="",0,IF($U44="",0,$U44)) -> 0 | AP44: =SUM(AE44:AM44) -> 0
A45: 44 | C45: Trending | D45: OC Trending V2 | E45: https://octopusdtlsupport.atlassian.net/browse/O2-456 | F45: Imp Team, Process Team | H45: 3 | K45: 1 | L45: UnPlan | O45: 10 | P45: 30 | Q45: 10 | T45: 5 | U45: =10+2 -> 12 | V45: =SUM(M45:U45) -> 67 | W45: =V45 - (V45 * (SUBSTITUTE(SUBSTITUTE($W$2, "Optimistic (", ""), "%)", "") / 100)) -> 33.5 | X45: =V45 + (W45 * (SUBSTITUTE(SUBSTITUTE($W$2, "Optimistic (", ""), "%)", "") / 100)) -> 83.75 | Y45: =(W45+(4*V45)+X45)/6 -> 64.208333 | Z45: =Y45/2 -> 32.104167 | AA45: 46146 | AB45: 46171 | AC45: 46174 | AD45: 46183 | AE45: =IF($Z45="",0,IF($M45="",0,$M45)) -> 0 | AF45: =IF(OR($Z45="",$N45=""),0,$Z45*5%) -> 0 | AG45: =IF(OR($Z45="",$O45=""),0,$Z45*10%) -> 3.2104167 | AH45: =IF($Z45="",0,IF(AND($P45="",$Q45=""),($Z45-$AE45-$AF45-$AG45-$AI45-$AK45-$AL45-$AM45-$AN45-$AO45),IF($P45="",0,IF($Q45="",($Z45-$AE45-$AF45-$AG45-$AI45-$AK45-$AL45-$AM45-$AN45-$AO45),($Z45-$AE45-$AF45-$AG45-$AI45-$AK45-$AL45-$AM45-$AN45-$AO45)*40%/(40%+15%))))) -> 6.0856061 | AI45: =IF($Z45="",0,IF($P45="",0,0.5)) -> 0.5 | AJ45: =IF($Z45="",0,IF(AND($P45="",$Q45=""),0,IF($Q45="",0,IF($P45="",($Z45-$AE45-$AF45-$AG45-$AI45-$AK45-$AL45-$AM45-$AN45-$AO45),($Z45-$AE45-$AF45-$AG45-$AI45-$AK45-$AL45-$AM45-$AN45-$AO45)*15%/(40%+15%))))) -> 2.2821023 | AK45: =IF($Z45="",0,$Z45*15%) -> 4.815625 | AL45: =IF($Z45="",0,IF($R45="",0,$R45)) -> 0 | AM45: =IF(OR($Z45="",$S45=""),0,$Z45*5%) -> 0 | AN45: =IF(OR($Z45="",$T45=""),0,$Z45*10%) -> 3.2104167 | AO45: =IF($Z45="",0,IF($U45="",0,$U45)) -> 12 | AP45: =SUM(AE45:AM45) -> 16.89375
A46: 45 | C46: Audit Trail | D46: Audit Trail | F46: Competitive | H46: 2 | K46: 1 | L46: UnPlan | V46: =SUM(M46:U46) -> 0 | W46: =V46 - (V46 * (SUBSTITUTE(SUBSTITUTE($W$2, "Optimistic (", ""), "%)", "") / 100)) -> 0 | X46: =V46 + (W46 * (SUBSTITUTE(SUBSTITUTE($W$2, "Optimistic (", ""), "%)", "") / 100)) -> 0 | Y46: =(W46+(4*V46)+X46)/6 -> 0 | Z46: =Y46/2 -> 0 | AE46: =IF($Z46="",0,IF($M46="",0,$M46)) -> 0 | AF46: =IF(OR($Z46="",$N46=""),0,$Z46*5%) -> 0 | AG46: =IF(OR($Z46="",$O46=""),0,$Z46*10%) -> 0 | AH46: =IF($Z46="",0,IF(AND($P46="",$Q46=""),($Z46-$AE46-$AF46-$AG46-$AI46-$AK46-$AL46-$AM46-$AN46-$AO46),IF($P46="",0,IF($Q46="",($Z46-$AE46-$AF46-$AG46-$AI46-$AK46-$AL46-$AM46-$AN46-$AO46),($Z46-$AE46-$AF46-$AG46-$AI46-$AK46-$AL46-$AM46-$AN46-$AO46)*40%/(40%+15%))))) -> 0 | AI46: =IF($Z46="",0,IF($P46="",0,0.5)) -> 0 | AJ46: =IF($Z46="",0,IF(AND($P46="",$Q46=""),0,IF($Q46="",0,IF($P46="",($Z46-$AE46-$AF46-$AG46-$AI46-$AK46-$AL46-$AM46-$AN46-$AO46),($Z46-$AE46-$AF46-$AG46-$AI46-$AK46-$AL46-$AM46-$AN46-$AO46)*15%/(40%+15%))))) -> 0 | AK46: =IF($Z46="",0,$Z46*15%) -> 0 | AL46: =IF($Z46="",0,IF($R46="",0,$R46)) -> 0 | AM46: =IF(OR($Z46="",$S46=""),0,$Z46*5%) -> 0 | AN46: =IF(OR($Z46="",$T46=""),0,$Z46*10%) -> 0 | AO46: =IF($Z46="",0,IF($U46="",0,$U46)) -> 0 | AP46: =SUM(AE46:AM46) -> 0
A47: 46 | C47: UI UX | D47: Revamped UI | F47: Management | H47: 1 | K47: 1+ | V47: =SUM(M47:U47) -> 0 | W47: =V47 - (V47 * (SUBSTITUTE(SUBSTITUTE($W$2, "Optimistic (", ""), "%)", "") / 100)) -> 0 | X47: =V47 + (W47 * (SUBSTITUTE(SUBSTITUTE($W$2, "Optimistic (", ""), "%)", "") / 100)) -> 0 | Y47: =(W47+(4*V47)+X47)/6 -> 0 | Z47: =Y47/2 -> 0 | AE47: =IF($Z47="",0,IF($M47="",0,$M47)) -> 0 | AF47: =IF(OR($Z47="",$N47=""),0,$Z47*5%) -> 0 | AG47: =IF(OR($Z47="",$O47=""),0,$Z47*10%) -> 0 | AH47: =IF($Z47="",0,IF(AND($P47="",$Q47=""),($Z47-$AE47-$AF47-$AG47-$AI47-$AK47-$AL47-$AM47-$AN47-$AO47),IF($P47="",0,IF($Q47="",($Z47-$AE47-$AF47-$AG47-$AI47-$AK47-$AL47-$AM47-$AN47-$AO47),($Z47-$AE47-$AF47-$AG47-$AI47-$AK47-$AL47-$AM47-$AN47-$AO47)*40%/(40%+15%))))) -> 0 | AI47: =IF($Z47="",0,IF($P47="",0,0.5)) -> 0 | AJ47: =IF($Z47="",0,IF(AND($P47="",$Q47=""),0,IF($Q47="",0,IF($P47="",($Z47-$AE47-$AF47-$AG47-$AI47-$AK47-$AL47-$AM47-$AN47-$AO47),($Z47-$AE47-$AF47-$AG47-$AI47-$AK47-$AL47-$AM47-$AN47-$AO47)*15%/(40%+15%))))) -> 0 | AK47: =IF($Z47="",0,$Z47*15%) -> 0 | AL47: =IF($Z47="",0,IF($R47="",0,$R47)) -> 0 | AM47: =IF(OR($Z47="",$S47=""),0,$Z47*5%) -> 0 | AN47: =IF(OR($Z47="",$T47=""),0,$Z47*10%) -> 0 | AO47: =IF($Z47="",0,IF($U47="",0,$U47)) -> 0 | AP47: =SUM(AE47:AM47) -> 0
A48: 47 | C48: Unified Notification Engine | D48: Unified Notification Engine | E48: https://octopusdtlsupport.atlassian.net/browse/O2-36 | F48: RnD | H48: 2 | K48: 1 | L48: UnPlan | N48: 5 | O48: 5 | P48: 12 | Q48: 5 | U48: 12 | V48: =SUM(M48:U48) -> 39 | W48: =V48 - (V48 * (SUBSTITUTE(SUBSTITUTE($W$2, "Optimistic (", ""), "%)", "") / 100)) -> 19.5 | X48: =V48 + (W48 * (SUBSTITUTE(SUBSTITUTE($W$2, "Optimistic (", ""), "%)", "") / 100)) -> 48.75 | Y48: =(W48+(4*V48)+X48)/6 -> 37.375 | Z48: =Y48/2 -> 18.6875 | AA48: 46125 | AB48: 46142 | AC48: 46146 | AD48: 46149 | AE48: =IF($Z48="",0,IF($M48="",0,$M48)) -> 0 | AF48: =IF(OR($Z48="",$N48=""),0,$Z48*5%) -> 0.934375 | AG48: =IF(OR($Z48="",$O48=""),0,$Z48*10%) -> 1.86875 | AH48: =IF($Z48="",0,IF(AND($P48="",$Q48=""),($Z48-$AE48-$AF48-$AG48-$AI48-$AK48-$AL48-$AM48-$AN48-$AO48),IF($P48="",0,IF($Q48="",($Z48-$AE48-$AF48-$AG48-$AI48-$AK48-$AL48-$AM48-$AN48-$AO48),($Z48-$AE48-$AF48-$AG48-$AI48-$AK48-$AL48-$AM48-$AN48-$AO48)*40%/(40%+15%))))) -> 0.42272727 | AI48: =IF($Z48="",0,IF($P48="",0,0.5)) -> 0.5 | AJ48: =IF($Z48="",0,IF(AND($P48="",$Q48=""),0,IF($Q48="",0,IF($P48="",($Z48-$AE48-$AF48-$AG48-$AI48-$AK48-$AL48-$AM48-$AN48-$AO48),($Z48-$AE48-$AF48-$AG48-$AI48-$AK48-$AL48-$AM48-$AN48-$AO48)*15%/(40%+15%))))) -> 0.15852273 | AK48: =IF($Z48="",0,$Z48*15%) -> 2.803125 | AL48: =IF($Z48="",0,IF($R48="",0,$R48)) -> 0 | AM48: =IF(OR($Z48="",$S48=""),0,$Z48*5%) -> 0 | AN48: =IF(OR($Z48="",$T48=""),0,$Z48*10%) -> 0 | AO48: =IF($Z48="",0,IF($U48="",0,$U48)) -> 12 | AP48: =SUM(AE48:AM48) -> 6.6875
C49: Export to SQL | D49: Export to SQL Enhancement | E49: https://octopusdtlsupport.atlassian.net/browse/O2-1976 | F49: Imp Team | N49: 0 | O49: 5 | P49: 10 | Q49: 5 | S49: 3 | T49: 5 | U49: 10 | V49: =SUM(M49:U49) -> 38 | W49: =V49 - (V49 * (SUBSTITUTE(SUBSTITUTE($W$2, "Optimistic (", ""), "%)", "") / 100)) -> 19 | X49: =V49 + (W49 * (SUBSTITUTE(SUBSTITUTE($W$2, "Optimistic (", ""), "%)", "") / 100)) -> 47.5 | Y49: =(W49+(4*V49)+X49)/6 -> 36.416667 | Z49: =Y49/2 -> 18.208333 | AA49: 46098 | AB49: 46115 | AC49: 46121 | AD49: 46128 | AE49: =IF($Z49="",0,IF($M49="",0,$M49)) -> 0 | AF49: =IF(OR($Z49="",$N49=""),0,$Z49*5%) -> 0.91041667 | AG49: =IF(OR($Z49="",$O49=""),0,$Z49*10%) -> 1.8208333 | AH49: =IF($Z49="",0,IF(AND($P49="",$Q49=""),($Z49-$AE49-$AF49-$AG49-$AI49-$AK49-$AL49-$AM49-$AN49-$AO49),IF($P49="",0,IF($Q49="",($Z49-$AE49-$AF49-$AG49-$AI49-$AK49-$AL49-$AM49-$AN49-$AO49),($Z49-$AE49-$AF49-$AG49-$AI49-$AK49-$AL49-$AM49-$AN49-$AO49)*40%/(40%+15%))))) -> -0.3530303 | AI49: =IF($Z49="",0,IF($P49="",0,0.5)) -> 0.5 | AJ49: =IF($Z49="",0,IF(AND($P49="",$Q49=""),0,IF($Q49="",0,IF($P49="",($Z49-$AE49-$AF49-$AG49-$AI49-$AK49-$AL49-$AM49-$AN49-$AO49),($Z49-$AE49-$AF49-$AG49-$AI49-$AK49-$AL49-$AM49-$AN49-$AO49)*15%/(40%+15%))))) -> -0.13238636 | AK49: =IF($Z49="",0,$Z49*15%) -> 2.73125 | AL49: =IF($Z49="",0,IF($R49="",0,$R49)) -> 0 | AM49: =IF(OR($Z49="",$S49=""),0,$Z49*5%) -> 0.91041667 | AN49: =IF(OR($Z49="",$T49=""),0,$Z49*10%) -> 1.8208333 | AO49: =IF($Z49="",0,IF($U49="",0,$U49)) -> 10 | AP49: =SUM(AE49:AM49) -> 6.3875
A50: 48 | B50: Administration | C50: Subscription Management | D50: Pricing Module | F50: Management | H50: 1 | K50: 1 | L50: Plan | V50: =SUM(M50:U50) -> 0 | W50: =V50 - (V50 * (SUBSTITUTE(SUBSTITUTE($W$2, "Optimistic (", ""), "%)", "") / 100)) -> 0 | X50: =V50 + (W50 * (SUBSTITUTE(SUBSTITUTE($W$2, "Optimistic (", ""), "%)", "") / 100)) -> 0 | Y50: =(W50+(4*V50)+X50)/6 -> 0 | Z50: =Y50/2 -> 0 | AE50: =IF($Z50="",0,IF($M50="",0,$M50)) -> 0 | AF50: =IF(OR($Z50="",$N50=""),0,$Z50*5%) -> 0 | AG50: =IF(OR($Z50="",$O50=""),0,$Z50*10%) -> 0 | AH50: =IF($Z50="",0,IF(AND($P50="",$Q50=""),($Z50-$AE50-$AF50-$AG50-$AI50-$AK50-$AL50-$AM50-$AN50-$AO50),IF($P50="",0,IF($Q50="",($Z50-$AE50-$AF50-$AG50-$AI50-$AK50-$AL50-$AM50-$AN50-$AO50),($Z50-$AE50-$AF50-$AG50-$AI50-$AK50-$AL50-$AM50-$AN50-$AO50)*40%/(40%+15%))))) -> 0 | AI50: =IF($Z50="",0,IF($P50="",0,0.5)) -> 0 | AJ50: =IF($Z50="",0,IF(AND($P50="",$Q50=""),0,IF($Q50="",0,IF($P50="",($Z50-$AE50-$AF50-$AG50-$AI50-$AK50-$AL50-$AM50-$AN50-$AO50),($Z50-$AE50-$AF50-$AG50-$AI50-$AK50-$AL50-$AM50-$AN50-$AO50)*15%/(40%+15%))))) -> 0 | AK50: =IF($Z50="",0,$Z50*15%) -> 0 | AL50: =IF($Z50="",0,IF($R50="",0,$R50)) -> 0 | AM50: =IF(OR($Z50="",$S50=""),0,$Z50*5%) -> 0 | AN50: =IF(OR($Z50="",$T50=""),0,$Z50*10%) -> 0 | AO50: =IF($Z50="",0,IF($U50="",0,$U50)) -> 0 | AP50: =SUM(AE50:AM50) -> 0
A51: 49 | D51: Subscription Management | F51: Management | H51: 1 | K51: 2 | L51: UnPlan | V51: =SUM(M51:U51) -> 0 | W51: =V51 - (V51 * (SUBSTITUTE(SUBSTITUTE($W$2, "Optimistic (", ""), "%)", "") / 100)) -> 0 | X51: =V51 + (W51 * (SUBSTITUTE(SUBSTITUTE($W$2, "Optimistic (", ""), "%)", "") / 100)) -> 0 | Y51: =(W51+(4*V51)+X51)/6 -> 0 | Z51: =Y51/2 -> 0 | AE51: =IF($Z51="",0,IF($M51="",0,$M51)) -> 0 | AF51: =IF(OR($Z51="",$N51=""),0,$Z51*5%) -> 0 | AG51: =IF(OR($Z51="",$O51=""),0,$Z51*10%) -> 0 | AH51: =IF($Z51="",0,IF(AND($P51="",$Q51=""),($Z51-$AE51-$AF51-$AG51-$AI51-$AK51-$AL51-$AM51-$AN51-$AO51),IF($P51="",0,IF($Q51="",($Z51-$AE51-$AF51-$AG51-$AI51-$AK51-$AL51-$AM51-$AN51-$AO51),($Z51-$AE51-$AF51-$AG51-$AI51-$AK51-$AL51-$AM51-$AN51-$AO51)*40%/(40%+15%))))) -> 0 | AI51: =IF($Z51="",0,IF($P51="",0,0.5)) -> 0 | AJ51: =IF($Z51="",0,IF(AND($P51="",$Q51=""),0,IF($Q51="",0,IF($P51="",($Z51-$AE51-$AF51-$AG51-$AI51-$AK51-$AL51-$AM51-$AN51-$AO51),($Z51-$AE51-$AF51-$AG51-$AI51-$AK51-$AL51-$AM51-$AN51-$AO51)*15%/(40%+15%))))) -> 0 | AK51: =IF($Z51="",0,$Z51*15%) -> 0 | AL51: =IF($Z51="",0,IF($R51="",0,$R51)) -> 0 | AM51: =IF(OR($Z51="",$S51=""),0,$Z51*5%) -> 0 | AN51: =IF(OR($Z51="",$T51=""),0,$Z51*10%) -> 0 | AO51: =IF($Z51="",0,IF($U51="",0,$U51)) -> 0 | AP51: =SUM(AE51:AM51) -> 0
A52: 50 | C52: DRP | D52: Redundancy in Blob Storage | F52: RnD | H52: 3 | K52: 3 | L52: UnPlan | V52: =SUM(M52:U52) -> 0 | W52: =V52 - (V52 * (SUBSTITUTE(SUBSTITUTE($W$2, "Optimistic (", ""), "%)", "") / 100)) -> 0 | X52: =V52 + (W52 * (SUBSTITUTE(SUBSTITUTE($W$2, "Optimistic (", ""), "%)", "") / 100)) -> 0 | Y52: =(W52+(4*V52)+X52)/6 -> 0 | Z52: =Y52/2 -> 0 | AE52: =IF($Z52="",0,IF($M52="",0,$M52)) -> 0 | AF52: =IF(OR($Z52="",$N52=""),0,$Z52*5%) -> 0 | AG52: =IF(OR($Z52="",$O52=""),0,$Z52*10%) -> 0 | AH52: =IF($Z52="",0,IF(AND($P52="",$Q52=""),($Z52-$AE52-$AF52-$AG52-$AI52-$AK52-$AL52-$AM52-$AN52-$AO52),IF($P52="",0,IF($Q52="",($Z52-$AE52-$AF52-$AG52-$AI52-$AK52-$AL52-$AM52-$AN52-$AO52),($Z52-$AE52-$AF52-$AG52-$AI52-$AK52-$AL52-$AM52-$AN52-$AO52)*40%/(40%+15%))))) -> 0 | AI52: =IF($Z52="",0,IF($P52="",0,0.5)) -> 0 | AJ52: =IF($Z52="",0,IF(AND($P52="",$Q52=""),0,IF($Q52="",0,IF($P52="",($Z52-$AE52-$AF52-$AG52-$AI52-$AK52-$AL52-$AM52-$AN52-$AO52),($Z52-$AE52-$AF52-$AG52-$AI52-$AK52-$AL52-$AM52-$AN52-$AO52)*15%/(40%+15%))))) -> 0 | AK52: =IF($Z52="",0,$Z52*15%) -> 0 | AL52: =IF($Z52="",0,IF($R52="",0,$R52)) -> 0 | AM52: =IF(OR($Z52="",$S52=""),0,$Z52*5%) -> 0 | AN52: =IF(OR($Z52="",$T52=""),0,$Z52*10%) -> 0 | AO52: =IF($Z52="",0,IF($U52="",0,$U52)) -> 0 | AP52: =SUM(AE52:AM52) -> 0 | AQ52: Why is this needed?
V53: =SUM(V3:V52)*Settings!I2 -> 0 | W53: =SUM(W3:W52)*Settings!I2 -> 0 | X53: =SUM(X3:X52)*Settings!I2 -> 0 | Y53: =SUM(Y3:Y52)*Settings!I2 -> 0 | Z53: =SUM(Z3:Z52)*Settings!I2 -> 0 | AE53: =SUM(AE3:AE52) -> 20 | AF53: =SUM(AF3:AF52) -> 4.2645833 | AG53: =IF(OR($Z53="",$O53=""),0,$Z53*10%) -> 0 | AH53: =IF($Z53="",0,IF(AND($P53="",$Q53=""),($Z53-$AE53-$AF53-$AG53-$AI53-$AK53-$AL53-$AM53-$AN53-$AO53),IF($P53="",0,IF($Q53="",($Z53-$AE53-$AF53-$AG53-$AI53-$AK53-$AL53-$AM53-$AN53-$AO53),($Z53-$AE53-$AF53-$AG53-$AI53-$AK53-$AL53-$AM53-$AN53-$AO53)*40%/(40%+15%))))) -> -24.264583 | AI53: =IF($Z53="",0,IF($P53="",0,0.5)) -> 0 | AJ53: =IF($Z53="",0,IF(AND($P53="",$Q53=""),0,IF($Q53="",0,IF($P53="",($Z53-$AE53-$AF53-$AG53-$AI53-$AK53-$AL53-$AM53-$AN53-$AO53),($Z53-$AE53-$AF53-$AG53-$AI53-$AK53-$AL53-$AM53-$AN53-$AO53)*15%/(40%+15%))))) -> 0 | AK53: =IF($Z53="",0,$Z53*15%) -> 0 | AL53: =IF($Z53="",0,IF($R53="",0,$R53)) -> 0 | AM53: =IF(OR($Z53="",$S53=""),0,$Z53*5%) -> 0 | AN53: =IF(OR($Z53="",$T53=""),0,$Z53*10%) -> 0 | AO53: =IF($Z53="",0,IF($U53="",0,$U53)) -> 0

Sheet Sheet6
C1: Man days
B2: Most likely | C2: 20 | D2: =C2*3 -> 60
B3: 0.3 | C3: =C2*1.3 -> 26 | D3: =C3 -> 26
C4: =C2/1.5 -> 13.333333 | D4: =C4 -> 13.333333
D5: =SUM(D2:D4) -> 99.333333
D6: =D5/6 -> 16.555556

Sheet Fintech Fuel RMI
A1: Fintech Fuel Roadmap Items | H1: BHW | I1: TK | J1: AA | K1: TS | M1: RnD Most likely | W1: TK Budgeted
A2: Sr # | B2: Category | C2: Components | D2: Road Map Items | E2: JIRA ID | F2: Originator | G2: Value | H2: Priority | I2: Priority | J2: Priority | K2: Priority | L2: Plan Status | M2: Prc Design | N2: R/URS | O2: R/DDS | P2: Dev | Q2: SQA | R2: Prc Test | S2: Doc | T2: Reg SQA | U2: Release | V2: Man Days | W2: ="Optimistic ("&Summary!E7&")" -> Optimistic (50%) | X2: Pessimistic (10%) | Y2: Est Formula | Z2: TK's TARGET | AA2: Start Date | AB2: Dev End | AC2: SQA HO | AD2: Prod Date | AE2: Prc Design | AF2: R/URS (5%) | AG2: R/DDS (10%) | AH2: Dev (40%) | AI2: Handover | AJ2: SQA (15%) | AK2: Bug Fixing (15%) | AL2: Prc Test | AM2: Doc (5%) | AN2: Reg SQA (10%) | AO2: Release
A3: 1 | B3: Input | C3: Alsons | D3: Alsons Connectivity for Reading (done) (6h) | F3: PGL | N3: 2 | O3: 1 | P3: 5 | Q3: 0 | S3: 0 | U3: 2 | V3: =SUM(M3:U3) -> 10 | W3: =V3 - (V3 * (SUBSTITUTE(SUBSTITUTE($W$2, "Optimistic (", ""), "%)", "") / 100)) -> 5 | X3: =V3 + (V3 * (SUBSTITUTE(SUBSTITUTE($X$2, "Pessimistic (", ""), "%)", "") / 100)) -> 11 | Y3: =(W3+(4*V3)+X3)/6 -> 9.3333333 | Z3: =Y3/2 -> 4.6666667 | AE3: =IF($Z3="",0,IF($M3="",0,$M3)) -> 0 | AF3: =IF(OR($Z3="",$N3=""),0,$Z3*5%) -> 0.23333333 | AG3: =IF(OR($Z3="",$O3=""),0,$Z3*10%) -> 0.46666667 | AH3: =IF($Z3="",0,IF(AND($P3="",$Q3=""),($Z3-$AE3-$AF3-$AG3-$AI3-$AK3-$AL3-$AM3-$AN3-$AO3),IF($P3="",0,IF($Q3="",($Z3-$AE3-$AF3-$AG3-$AI3-$AK3-$AL3-$AM3-$AN3-$AO3),($Z3-$AE3-$AF3-$AG3-$AI3-$AK3-$AL3-$AM3-$AN3-$AO3)*40%/(40%+15%))))) -> 0.38787879 | AI3: =IF($Z3="",0,IF($P3="",0,0.5)) -> 0.5 | AJ3: =IF($Z3="",0,IF(AND($P3="",$Q3=""),0,IF($Q3="",0,IF($P3="",($Z3-$AE3-$AF3-$AG3-$AI3-$AK3-$AL3-$AM3-$AN3-$AO3),($Z3-$AE3-$AF3-$AG3-$AI3-$AK3-$AL3-$AM3-$AN3-$AO3)*15%/(40%+15%))))) -> 0.14545455 | AK3: =IF($Z3="",0,$Z3*15%) -> 0.7 | AL3: =IF($Z3="",0,IF($R3="",0,$R3)) -> 0 | AM3: =IF(OR($Z3="",$S3=""),0,$Z3*5%) -> 0.23333333 | AN3: =IF(OR($Z3="",$T3=""),0,$Z3*10%) -> 0 | AO3: =IF($Z3="",0,IF($U3="",0,$U3)) -> 2
A4: =IF(D4="","",A3+1) -> 2 | D4: Alsons Data Compatibility POC with FintechFuel - (41h) | F4: PGL | O4: 5 | P4: 48 | Q4: 15 | U4: 2 | V4: =SUM(M4:U4) -> 70 | W4: =V4 - (V4 * (SUBSTITUTE(SUBSTITUTE($W$2, "Optimistic (", ""), "%)", "") / 100)) -> 35 | X4: =V4 + (V4 * (SUBSTITUTE(SUBSTITUTE($X$2, "Pessimistic (", ""), "%)", "") / 100)) -> 77 | Y4: =(W4+(4*V4)+X4)/6 -> 65.333333 | Z4: =Y4/2 -> 32.666667 | AE4: =IF($Z4="",0,IF($M4="",0,$M4)) -> 0 | AF4: =IF(OR($Z4="",$N4=""),0,$Z4*5%) -> 0 | AG4: =IF(OR($Z4="",$O4=""),0,$Z4*10%) -> 3.2666667 | AH4: =IF($Z4="",0,IF(AND($P4="",$Q4=""),($Z4-$AE4-$AF4-$AG4-$AI4-$AK4-$AL4-$AM4-$AN4-$AO4),IF($P4="",0,IF($Q4="",($Z4-$AE4-$AF4-$AG4-$AI4-$AK4-$AL4-$AM4-$AN4-$AO4),($Z4-$AE4-$AF4-$AG4-$AI4-$AK4-$AL4-$AM4-$AN4-$AO4)*40%/(40%+15%))))) -> 16 | AI4: =IF($Z4="",0,IF($P4="",0,0.5)) -> 0.5 | AJ4: =IF($Z4="",0,IF(AND($P4="",$Q4=""),0,IF($Q4="",0,IF($P4="",($Z4-$AE4-$AF4-$AG4-$AI4-$AK4-$AL4-$AM4-$AN4-$AO4),($Z4-$AE4-$AF4-$AG4-$AI4-$AK4-$AL4-$AM4-$AN4-$AO4)*15%/(40%+15%))))) -> 6 | AK4: =IF($Z4="",0,$Z4*15%) -> 4.9 | AL4: =IF($Z4="",0,IF($R4="",0,$R4)) -> 0 | AM4: =IF(OR($Z4="",$S4=""),0,$Z4*5%) -> 0 | AN4: =IF(OR($Z4="",$T4=""),0,$Z4*10%) -> 0 | AO4: =IF($Z4="",0,IF($U4="",0,$U4)) -> 2
D5: Alsons Integration with FintechFuel | F5: RnD | N5: 0 | O5: 0 | P5: 23 | Q5: 15 | S5: 5 | T5: 15 | U5: 2 | V5: =SUM(M5:U5) -> 60 | W5: =V5 - (V5 * (SUBSTITUTE(SUBSTITUTE($W$2, "Optimistic (", ""), "%)", "") / 100)) -> 30 | X5: =V5 + (V5 * (SUBSTITUTE(SUBSTITUTE($X$2, "Pessimistic (", ""), "%)", "") / 100)) -> 66 | Y5: =(W5+(4*V5)+X5)/6 -> 56 | Z5: =Y5/2 -> 28 | AA5: 46111 | AB5: 46126 | AC5: 46127 | AD5: 46148 | AE5: =IF($Z5="",0,IF($M5="",0,$M5)) -> 0 | AF5: =IF(OR($Z5="",$N5=""),0,$Z5*5%) -> 1.4 | AG5: =IF(OR($Z5="",$O5=""),0,$Z5*10%) -> 2.8 | AH5: =IF($Z5="",0,IF(AND($P5="",$Q5=""),($Z5-$AE5-$AF5-$AG5-$AI5-$AK5-$AL5-$AM5-$AN5-$AO5),IF($P5="",0,IF($Q5="",($Z5-$AE5-$AF5-$AG5-$AI5-$AK5-$AL5-$AM5-$AN5-$AO5),($Z5-$AE5-$AF5-$AG5-$AI5-$AK5-$AL5-$AM5-$AN5-$AO5)*40%/(40%+15%))))) -> 9.3818182 | AI5: =IF($Z5="",0,IF($P5="",0,0.5)) -> 0.5 | AJ5: =IF($Z5="",0,IF(AND($P5="",$Q5=""),0,IF($Q5="",0,IF($P5="",($Z5-$AE5-$AF5-$AG5-$AI5-$AK5-$AL5-$AM5-$AN5-$AO5),($Z5-$AE5-$AF5-$AG5-$AI5-$AK5-$AL5-$AM5-$AN5-$AO5)*15%/(40%+15%))))) -> 3.5181818 | AK5: =IF($Z5="",0,$Z5*15%) -> 4.2 | AL5: =IF($Z5="",0,IF($R5="",0,$R5)) -> 0 | AM5: =IF(OR($Z5="",$S5=""),0,$Z5*5%) -> 1.4 | AN5: =IF(OR($Z5="",$T5=""),0,$Z5*10%) -> 2.8 | AO5: =IF($Z5="",0,IF($U5="",0,$U5)) -> 2
A6: =IF(D6="","",A4+1) -> 3 | B6: Enrichment | C6: Business Alarms | D6: Configurable alert thresholds and Recipients (done) | F6: PGL | O6: 15 | P6: 32 | Q6: 7 | S6: 4 | T6: 6 | U6: 2 | V6: =SUM(M6:U6) -> 66 | W6: =V6 - (V6 * (SUBSTITUTE(SUBSTITUTE($W$2, "Optimistic (", ""), "%)", "") / 100)) -> 33 | X6: =V6 + (V6 * (SUBSTITUTE(SUBSTITUTE($X$2, "Pessimistic (", ""), "%)", "") / 100)) -> 72.6 | Y6: =(W6+(4*V6)+X6)/6 -> 61.6 | Z6: =Y6/2 -> 30.8 | AE6: =IF($Z6="",0,IF($M6="",0,$M6)) -> 0 | AF6: =IF(OR($Z6="",$N6=""),0,$Z6*5%) -> 0 | AG6: =IF(OR($Z6="",$O6=""),0,$Z6*10%) -> 3.08 | AH6: =IF($Z6="",0,IF(AND($P6="",$Q6=""),($Z6-$AE6-$AF6-$AG6-$AI6-$AK6-$AL6-$AM6-$AN6-$AO6),IF($P6="",0,IF($Q6="",($Z6-$AE6-$AF6-$AG6-$AI6-$AK6-$AL6-$AM6-$AN6-$AO6),($Z6-$AE6-$AF6-$AG6-$AI6-$AK6-$AL6-$AM6-$AN6-$AO6)*40%/(40%+15%))))) -> 11.621818 | AI6: =IF($Z6="",0,IF($P6="",0,0.5)) -> 0.5 | AJ6: =IF($Z6="",0,IF(AND($P6="",$Q6=""),0,IF($Q6="",0,IF($P6="",($Z6-$AE6-$AF6-$AG6-$AI6-$AK6-$AL6-$AM6-$AN6-$AO6),($Z6-$AE6-$AF6-$AG6-$AI6-$AK6-$AL6-$AM6-$AN6-$AO6)*15%/(40%+15%))))) -> 4.3581818 | AK6: =IF($Z6="",0,$Z6*15%) -> 4.62 | AL6: =IF($Z6="",0,IF($R6="",0,$R6)) -> 0 | AM6: =IF(OR($Z6="",$S6=""),0,$Z6*5%) -> 1.54 | AN6: =IF(OR($Z6="",$T6=""),0,$Z6*10%) -> 3.08 | AO6: =IF($Z6="",0,IF($U6="",0,$U6)) -> 2
A7: =IF(D7="","",A6+1) -> 4 | D7: Leak and theft alerts | F7: PGL | O7: 3 | P7: 5 | Q7: 3 | S7: 1 | T7: 5 | U7: 2 | V7: =SUM(M7:U7) -> 19 | W7: =V7 - (V7 * (SUBSTITUTE(SUBSTITUTE($W$2, "Optimistic (", ""), "%)", "") / 100)) -> 9.5 | X7: =V7 + (V7 * (SUBSTITUTE(SUBSTITUTE($X$2, "Pessimistic (", ""), "%)", "") / 100)) -> 20.9 | Y7: =(W7+(4*V7)+X7)/6 -> 17.733333 | Z7: =Y7/2 -> 8.8666667 | AE7: =IF($Z7="",0,IF($M7="",0,$M7)) -> 0 | AF7: =IF(OR($Z7="",$N7=""),0,$Z7*5%) -> 0 | AG7: =IF(OR($Z7="",$O7=""),0,$Z7*10%) -> 0.88666667 | AH7: =IF($Z7="",0,IF(AND($P7="",$Q7=""),($Z7-$AE7-$AF7-$AG7-$AI7-$AK7-$AL7-$AM7-$AN7-$AO7),IF($P7="",0,IF($Q7="",($Z7-$AE7-$AF7-$AG7-$AI7-$AK7-$AL7-$AM7-$AN7-$AO7),($Z7-$AE7-$AF7-$AG7-$AI7-$AK7-$AL7-$AM7-$AN7-$AO7)*40%/(40%+15%))))) -> 2.0509091 | AI7: =IF($Z7="",0,IF($P7="",0,0.5)) -> 0.5 | AJ7: =IF($Z7="",0,IF(AND($P7="",$Q7=""),0,IF($Q7="",0,IF($P7="",($Z7-$AE7-$AF7-$AG7-$AI7-$AK7-$AL7-$AM7-$AN7-$AO7),($Z7-$AE7-$AF7-$AG7-$AI7-$AK7-$AL7-$AM7-$AN7-$AO7)*15%/(40%+15%))))) -> 0.76909091 | AK7: =IF($Z7="",0,$Z7*15%) -> 1.33 | AL7: =IF($Z7="",0,IF($R7="",0,$R7)) -> 0 | AM7: =IF(OR($Z7="",$S7=""),0,$Z7*5%) -> 0.44333333 | AN7: =IF(OR($Z7="",$T7=""),0,$Z7*10%) -> 0.88666667 | AO7: =IF($Z7="",0,IF($U7="",0,$U7)) -> 2
A8: =IF(D8="","",A7+1) -> 5 | D8: Theft detection (internal/external) | F8: PGL | O8: 3 | P8: 5 | Q8: 3 | S8: 1 | T8: 5 | U8: 2 | V8: =SUM(M8:U8) -> 19 | W8: =V8 - (V8 * (SUBSTITUTE(SUBSTITUTE($W$2, "Optimistic (", ""), "%)", "") / 100)) -> 9.5 | X8: =V8 + (V8 * (SUBSTITUTE(SUBSTITUTE($X$2, "Pessimistic (", ""), "%)", "") / 100)) -> 20.9 | Y8: =(W8+(4*V8)+X8)/6 -> 17.733333 | Z8: =Y8/2 -> 8.8666667 | AE8: =IF($Z8="",0,IF($M8="",0,$M8)) -> 0 | AF8: =IF(OR($Z8="",$N8=""),0,$Z8*5%) -> 0 | AG8: =IF(OR($Z8="",$O8=""),0,$Z8*10%) -> 0.88666667 | AH8: =IF($Z8="",0,IF(AND($P8="",$Q8=""),($Z8-$AE8-$AF8-$AG8-$AI8-$AK8-$AL8-$AM8-$AN8-$AO8),IF($P8="",0,IF($Q8="",($Z8-$AE8-$AF8-$AG8-$AI8-$AK8-$AL8-$AM8-$AN8-$AO8),($Z8-$AE8-$AF8-$AG8-$AI8-$AK8-$AL8-$AM8-$AN8-$AO8)*40%/(40%+15%))))) -> 2.0509091 | AI8: =IF($Z8="",0,IF($P8="",0,0.5)) -> 0.5 | AJ8: =IF($Z8="",0,IF(AND($P8="",$Q8=""),0,IF($Q8="",0,IF($P8="",($Z8-$AE8-$AF8-$AG8-$AI8-$AK8-$AL8-$AM8-$AN8-$AO8),($Z8-$AE8-$AF8-$AG8-$AI8-$AK8-$AL8-$AM8-$AN8-$AO8)*15%/(40%+15%))))) -> 0.76909091 | AK8: =IF($Z8="",0,$Z8*15%) -> 1.33 | AL8: =IF($Z8="",0,IF($R8="",0,$R8)) -> 0 | AM8: =IF(OR($Z8="",$S8=""),0,$Z8*5%) -> 0.44333333 | AN8: =IF(OR($Z8="",$T8=""),0,$Z8*10%) -> 0.88666667 | AO8: =IF($Z8="",0,IF($U8="",0,$U8)) -> 2
A9: =IF(D9="","",A8+1) -> 6 | D9: Nozzle bypass detection | F9: PGL | O9: 3 | P9: 5 | Q9: 3 | S9: 1 | T9: 5 | U9: 2 | V9: =SUM(M9:U9) -> 19 | W9: =V9 - (V9 * (SUBSTITUTE(SUBSTITUTE($W$2, "Optimistic (", ""), "%)", "") / 100)) -> 9.5 | X9: =V9 + (V9 * (SUBSTITUTE(SUBSTITUTE($X$2, "Pessimistic (", ""), "%)", "") / 100)) -> 20.9 | Y9: =(W9+(4*V9)+X9)/6 -> 17.733333 | Z9: =Y9/2 -> 8.8666667 | AE9: =IF($Z9="",0,IF($M9="",0,$M9)) -> 0 | AF9: =IF(OR($Z9="",$N9=""),0,$Z9*5%) -> 0 | AG9: =IF(OR($Z9="",$O9=""),0,$Z9*10%) -> 0.88666667 | AH9: =IF($Z9="",0,IF(AND($P9="",$Q9=""),($Z9-$AE9-$AF9-$AG9-$AI9-$AK9-$AL9-$AM9-$AN9-$AO9),IF($P9="",0,IF($Q9="",($Z9-$AE9-$AF9-$AG9-$AI9-$AK9-$AL9-$AM9-$AN9-$AO9),($Z9-$AE9-$AF9-$AG9-$AI9-$AK9-$AL9-$AM9-$AN9-$AO9)*40%/(40%+15%))))) -> 2.0509091 | AI9: =IF($Z9="",0,IF($P9="",0,0.5)) -> 0.5 | AJ9: =IF($Z9="",0,IF(AND($P9="",$Q9=""),0,IF($Q9="",0,IF($P9="",($Z9-$AE9-$AF9-$AG9-$AI9-$AK9-$AL9-$AM9-$AN9-$AO9),($Z9-$AE9-$AF9-$AG9-$AI9-$AK9-$AL9-$AM9-$AN9-$AO9)*15%/(40%+15%))))) -> 0.76909091 | AK9: =IF($Z9="",0,$Z9*15%) -> 1.33 | AL9: =IF($Z9="",0,IF($R9="",0,$R9)) -> 0 | AM9: =IF(OR($Z9="",$S9=""),0,$Z9*5%) -> 0.44333333 | AN9: =IF(OR($Z9="",$T9=""),0,$Z9*10%) -> 0.88666667 | AO9: =IF($Z9="",0,IF($U9="",0,$U9)) -> 2
A10: =IF(D10="","",A9+1) -> 7 | D10: Calibration drift alerts | F10: PGL | O10: 3 | P10: 5 | Q10: 3 | S10: 1 | T10: 5 | U10: 2 | V10: =SUM(M10:U10) -> 19 | W10: =V10 - (V10 * (SUBSTITUTE(SUBSTITUTE($W$2, "Optimistic (", ""), "%)", "") / 100)) -> 9.5 | X10: =V10 + (V10 * (SUBSTITUTE(SUBSTITUTE($X$2, "Pessimistic (", ""), "%)", "") / 100)) -> 20.9 | Y10: =(W10+(4*V10)+X10)/6 -> 17.733333 | Z10: =Y10/2 -> 8.8666667 | AE10: =IF($Z10="",0,IF($M10="",0,$M10)) -> 0 | AF10: =IF(OR($Z10="",$N10=""),0,$Z10*5%) -> 0 | AG10: =IF(OR($Z10="",$O10=""),0,$Z10*10%) -> 0.88666667 | AH10: =IF($Z10="",0,IF(AND($P10="",$Q10=""),($Z10-$AE10-$AF10-$AG10-$AI10-$AK10-$AL10-$AM10-$AN10-$AO10),IF($P10="",0,IF($Q10="",($Z10-$AE10-$AF10-$AG10-$AI10-$AK10-$AL10-$AM10-$AN10-$AO10),($Z10-$AE10-$AF10-$AG10-$AI10-$AK10-$AL10-$AM10-$AN10-$AO10)*40%/(40%+15%))))) -> 2.0509091 | AI10: =IF($Z10="",0,IF($P10="",0,0.5)) -> 0.5 | AJ10: =IF($Z10="",0,IF(AND($P10="",$Q10=""),0,IF($Q10="",0,IF($P10="",($Z10-$AE10-$AF10-$AG10-$AI10-$AK10-$AL10-$AM10-$AN10-$AO10),($Z10-$AE10-$AF10-$AG10-$AI10-$AK10-$AL10-$AM10-$AN10-$AO10)*15%/(40%+15%))))) -> 0.76909091 | AK10: =IF($Z10="",0,$Z10*15%) -> 1.33 | AL10: =IF($Z10="",0,IF($R10="",0,$R10)) -> 0 | AM10: =IF(OR($Z10="",$S10=""),0,$Z10*5%) -> 0.44333333 | AN10: =IF(OR($Z10="",$T10=""),0,$Z10*10%) -> 0.88666667 | AO10: =IF($Z10="",0,IF($U10="",0,$U10)) -> 2
A11: =IF(D11="","",A10+1) -> 8 | D11: Sensor malfunction alerts | F11: PGL | O11: 3 | P11: 5 | Q11: 3 | S11: 1 | T11: 5 | U11: 2 | V11: =SUM(M11:U11) -> 19 | W11: =V11 - (V11 * (SUBSTITUTE(SUBSTITUTE($W$2, "Optimistic (", ""), "%)", "") / 100)) -> 9.5 | X11: =V11 + (V11 * (SUBSTITUTE(SUBSTITUTE($X$2, "Pessimistic (", ""), "%)", "") / 100)) -> 20.9 | Y11: =(W11+(4*V11)+X11)/6 -> 17.733333 | Z11: =Y11/2 -> 8.8666667 | AE11: =IF($Z11="",0,IF($M11="",0,$M11)) -> 0 | AF11: =IF(OR($Z11="",$N11=""),0,$Z11*5%) -> 0 | AG11: =IF(OR($Z11="",$O11=""),0,$Z11*10%) -> 0.88666667 | AH11: =IF($Z11="",0,IF(AND($P11="",$Q11=""),($Z11-$AE11-$AF11-$AG11-$AI11-$AK11-$AL11-$AM11-$AN11-$AO11),IF($P11="",0,IF($Q11="",($Z11-$AE11-$AF11-$AG11-$AI11-$AK11-$AL11-$AM11-$AN11-$AO11),($Z11-$AE11-$AF11-$AG11-$AI11-$AK11-$AL11-$AM11-$AN11-$AO11)*40%/(40%+15%))))) -> 2.0509091 | AI11: =IF($Z11="",0,IF($P11="",0,0.5)) -> 0.5 | AJ11: =IF($Z11="",0,IF(AND($P11="",$Q11=""),0,IF($Q11="",0,IF($P11="",($Z11-$AE11-$AF11-$AG11-$AI11-$AK11-$AL11-$AM11-$AN11-$AO11),($Z11-$AE11-$AF11-$AG11-$AI11-$AK11-$AL11-$AM11-$AN11-$AO11)*15%/(40%+15%))))) -> 0.76909091 | AK11: =IF($Z11="",0,$Z11*15%) -> 1.33 | AL11: =IF($Z11="",0,IF($R11="",0,$R11)) -> 0 | AM11: =IF(OR($Z11="",$S11=""),0,$Z11*5%) -> 0.44333333 | AN11: =IF(OR($Z11="",$T11=""),0,$Z11*10%) -> 0.88666667 | AO11: =IF($Z11="",0,IF($U11="",0,$U11)) -> 2
A12: =IF(D12="","",A11+1) -> 9 | D12: Unauthorized dispensing alerts | F12: PGL | O12: 3 | P12: 5 | Q12: 3 | S12: 1 | T12: 5 | U12: 2 | V12: =SUM(M12:U12) -> 19 | W12: =V12 - (V12 * (SUBSTITUTE(SUBSTITUTE($W$2, "Optimistic (", ""), "%)", "") / 100)) -> 9.5 | X12: =V12 + (V12 * (SUBSTITUTE(SUBSTITUTE($X$2, "Pessimistic (", ""), "%)", "") / 100)) -> 20.9 | Y12: =(W12+(4*V12)+X12)/6 -> 17.733333 | Z12: =Y12/2 -> 8.8666667 | AE12: =IF($Z12="",0,IF($M12="",0,$M12)) -> 0 | AF12: =IF(OR($Z12="",$N12=""),0,$Z12*5%) -> 0 | AG12: =IF(OR($Z12="",$O12=""),0,$Z12*10%) -> 0.88666667 | AH12: =IF($Z12="",0,IF(AND($P12="",$Q12=""),($Z12-$AE12-$AF12-$AG12-$AI12-$AK12-$AL12-$AM12-$AN12-$AO12),IF($P12="",0,IF($Q12="",($Z12-$AE12-$AF12-$AG12-$AI12-$AK12-$AL12-$AM12-$AN12-$AO12),($Z12-$AE12-$AF12-$AG12-$AI12-$AK12-$AL12-$AM12-$AN12-$AO12)*40%/(40%+15%))))) -> 2.0509091 | AI12: =IF($Z12="",0,IF($P12="",0,0.5)) -> 0.5 | AJ12: =IF($Z12="",0,IF(AND($P12="",$Q12=""),0,IF($Q12="",0,IF($P12="",($Z12-$AE12-$AF12-$AG12-$AI12-$AK12-$AL12-$AM12-$AN12-$AO12),($Z12-$AE12-$AF12-$AG12-$AI12-$AK12-$AL12-$AM12-$AN12-$AO12)*15%/(40%+15%))))) -> 0.76909091 | AK12: =IF($Z12="",0,$Z12*15%) -> 1.33 | AL12: =IF($Z12="",0,IF($R12="",0,$R12)) -> 0 | AM12: =IF(OR($Z12="",$S12=""),0,$Z12*5%) -> 0.44333333 | AN12: =IF(OR($Z12="",$T12=""),0,$Z12*10%) -> 0.88666667 | AO12: =IF($Z12="",0,IF($U12="",0,$U12)) -> 2
A13: =IF(D13="","",A12+1) -> 10 | D13: Power outage detection | F13: PGL | O13: 3 | P13: 5 | Q13: 3 | S13: 1 | T13: 5 | U13: 2 | V13: =SUM(M13:U13) -> 19 | W13: =V13 - (V13 * (SUBSTITUTE(SUBSTITUTE($W$2, "Optimistic (", ""), "%)", "") / 100)) -> 9.5 | X13: =V13 + (V13 * (SUBSTITUTE(SUBSTITUTE($X$2, "Pessimistic (", ""), "%)", "") / 100)) -> 20.9 | Y13: =(W13+(4*V13)+X13)/6 -> 17.733333 | Z13: =Y13/2 -> 8.8666667 | AE13: =IF($Z13="",0,IF($M13="",0,$M13)) -> 0 | AF13: =IF(OR($Z13="",$N13=""),0,$Z13*5%) -> 0 | AG13: =IF(OR($Z13="",$O13=""),0,$Z13*10%) -> 0.88666667 | AH13: =IF($Z13="",0,IF(AND($P13="",$Q13=""),($Z13-$AE13-$AF13-$AG13-$AI13-$AK13-$AL13-$AM13-$AN13-$AO13),IF($P13="",0,IF($Q13="",($Z13-$AE13-$AF13-$AG13-$AI13-$AK13-$AL13-$AM13-$AN13-$AO13),($Z13-$AE13-$AF13-$AG13-$AI13-$AK13-$AL13-$AM13-$AN13-$AO13)*40%/(40%+15%))))) -> 2.0509091 | AI13: =IF($Z13="",0,IF($P13="",0,0.5)) -> 0.5 | AJ13: =IF($Z13="",0,IF(AND($P13="",$Q13=""),0,IF($Q13="",0,IF($P13="",($Z13-$AE13-$AF13-$AG13-$AI13-$AK13-$AL13-$AM13-$AN13-$AO13),($Z13-$AE13-$AF13-$AG13-$AI13-$AK13-$AL13-$AM13-$AN13-$AO13)*15%/(40%+15%))))) -> 0.76909091 | AK13: =IF($Z13="",0,$Z13*15%) -> 1.33 | AL13: =IF($Z13="",0,IF($R13="",0,$R13)) -> 0 | AM13: =IF(OR($Z13="",$S13=""),0,$Z13*5%) -> 0.44333333 | AN13: =IF(OR($Z13="",$T13=""),0,$Z13*10%) -> 0.88666667 | AO13: =IF($Z13="",0,IF($U13="",0,$U13)) -> 2
A14: =IF(D14="","",A13+1) -> 11 | D14: Alert escalation workflows | F14: PGL | O14: 3 | P14: 5 | Q14: 3 | S14: 1 | T14: 5 | U14: 2 | V14: =SUM(M14:U14) -> 19 | W14: =V14 - (V14 * (SUBSTITUTE(SUBSTITUTE($W$2, "Optimistic (", ""), "%)", "") / 100)) -> 9.5 | X14: =V14 + (V14 * (SUBSTITUTE(SUBSTITUTE($X$2, "Pessimistic (", ""), "%)", "") / 100)) -> 20.9 | Y14: =(W14+(4*V14)+X14)/6 -> 17.733333 | Z14: =Y14/2 -> 8.8666667 | AE14: =IF($Z14="",0,IF($M14="",0,$M14)) -> 0 | AF14: =IF(OR($Z14="",$N14=""),0,$Z14*5%) -> 0 | AG14: =IF(OR($Z14="",$O14=""),0,$Z14*10%) -> 0.88666667 | AH14: =IF($Z14="",0,IF(AND($P14="",$Q14=""),($Z14-$AE14-$AF14-$AG14-$AI14-$AK14-$AL14-$AM14-$AN14-$AO14),IF($P14="",0,IF($Q14="",($Z14-$AE14-$AF14-$AG14-$AI14-$AK14-$AL14-$AM14-$AN14-$AO14),($Z14-$AE14-$AF14-$AG14-$AI14-$AK14-$AL14-$AM14-$AN14-$AO14)*40%/(40%+15%))))) -> 2.0509091 | AI14: =IF($Z14="",0,IF($P14="",0,0.5)) -> 0.5 | AJ14: =IF($Z14="",0,IF(AND($P14="",$Q14=""),0,IF($Q14="",0,IF($P14="",($Z14-$AE14-$AF14-$AG14-$AI14-$AK14-$AL14-$AM14-$AN14-$AO14),($Z14-$AE14-$AF14-$AG14-$AI14-$AK14-$AL14-$AM14-$AN14-$AO14)*15%/(40%+15%))))) -> 0.76909091 | AK14: =IF($Z14="",0,$Z14*15%) -> 1.33 | AL14: =IF($Z14="",0,IF($R14="",0,$R14)) -> 0 | AM14: =IF(OR($Z14="",$S14=""),0,$Z14*5%) -> 0.44333333 | AN14: =IF(OR($Z14="",$T14=""),0,$Z14*10%) -> 0.88666667 | AO14: =IF($Z14="",0,IF($U14="",0,$U14)) -> 2
A15: =IF(D15="","",A14+1) -> 12 | D15: Alert acknowledgment and resolution tracking | F15: PGL | O15: 3 | P15: 5 | Q15: 3 | S15: 1 | T15: 5 | U15: 2 | V15: =SUM(M15:U15) -> 19 | W15: =V15 - (V15 * (SUBSTITUTE(SUBSTITUTE($W$2, "Optimistic (", ""), "%)", "") / 100)) -> 9.5 | X15: =V15 + (V15 * (SUBSTITUTE(SUBSTITUTE($X$2, "Pessimistic (", ""), "%)", "") / 100)) -> 20.9 | Y15: =(W15+(4*V15)+X15)/6 -> 17.733333 | Z15: =Y15/2 -> 8.8666667 | AE15: =IF($Z15="",0,IF($M15="",0,$M15)) -> 0 | AF15: =IF(OR($Z15="",$N15=""),0,$Z15*5%) -> 0 | AG15: =IF(OR($Z15="",$O15=""),0,$Z15*10%) -> 0.88666667 | AH15: =IF($Z15="",0,IF(AND($P15="",$Q15=""),($Z15-$AE15-$AF15-$AG15-$AI15-$AK15-$AL15-$AM15-$AN15-$AO15),IF($P15="",0,IF($Q15="",($Z15-$AE15-$AF15-$AG15-$AI15-$AK15-$AL15-$AM15-$AN15-$AO15),($Z15-$AE15-$AF15-$AG15-$AI15-$AK15-$AL15-$AM15-$AN15-$AO15)*40%/(40%+15%))))) -> 2.0509091 | AI15: =IF($Z15="",0,IF($P15="",0,0.5)) -> 0.5 | AJ15: =IF($Z15="",0,IF(AND($P15="",$Q15=""),0,IF($Q15="",0,IF($P15="",($Z15-$AE15-$AF15-$AG15-$AI15-$AK15-$AL15-$AM15-$AN15-$AO15),($Z15-$AE15-$AF15-$AG15-$AI15-$AK15-$AL15-$AM15-$AN15-$AO15)*15%/(40%+15%))))) -> 0.76909091 | AK15: =IF($Z15="",0,$Z15*15%) -> 1.33 | AL15: =IF($Z15="",0,IF($R15="",0,$R15)) -> 0 | AM15: =IF(OR($Z15="",$S15=""),0,$Z15*5%) -> 0.44333333 | AN15: =IF(OR($Z15="",$T15=""),0,$Z15*10%) -> 0.88666667 | AO15: =IF($Z15="",0,IF($U15="",0,$U15)) -> 2
A16: =IF(D16="","",A15+1) -> 13 | D16: Nozzle flow rate | F16: Competitive | O16: 3 | P16: 5 | Q16: 3 | S16: 1 | T16: 5 | U16: 2 | V16: =SUM(M16:U16) -> 19 | W16: =V16 - (V16 * (SUBSTITUTE(SUBSTITUTE($W$2, "Optimistic (", ""), "%)", "") / 100)) -> 9.5 | X16: =V16 + (V16 * (SUBSTITUTE(SUBSTITUTE($X$2, "Pessimistic (", ""), "%)", "") / 100)) -> 20.9 | Y16: =(W16+(4*V16)+X16)/6 -> 17.733333 | Z16: =Y16/2 -> 8.8666667 | AE16: =IF($Z16="",0,IF($M16="",0,$M16)) -> 0 | AF16: =IF(OR($Z16="",$N16=""),0,$Z16*5%) -> 0 | AG16: =IF(OR($Z16="",$O16=""),0,$Z16*10%) -> 0.88666667 | AH16: =IF($Z16="",0,IF(AND($P16="",$Q16=""),($Z16-$AE16-$AF16-$AG16-$AI16-$AK16-$AL16-$AM16-$AN16-$AO16),IF($P16="",0,IF($Q16="",($Z16-$AE16-$AF16-$AG16-$AI16-$AK16-$AL16-$AM16-$AN16-$AO16),($Z16-$AE16-$AF16-$AG16-$AI16-$AK16-$AL16-$AM16-$AN16-$AO16)*40%/(40%+15%))))) -> 2.0509091 | AI16: =IF($Z16="",0,IF($P16="",0,0.5)) -> 0.5 | AJ16: =IF($Z16="",0,IF(AND($P16="",$Q16=""),0,IF($Q16="",0,IF($P16="",($Z16-$AE16-$AF16-$AG16-$AI16-$AK16-$AL16-$AM16-$AN16-$AO16),($Z16-$AE16-$AF16-$AG16-$AI16-$AK16-$AL16-$AM16-$AN16-$AO16)*15%/(40%+15%))))) -> 0.76909091 | AK16: =IF($Z16="",0,$Z16*15%) -> 1.33 | AL16: =IF($Z16="",0,IF($R16="",0,$R16)) -> 0 | AM16: =IF(OR($Z16="",$S16=""),0,$Z16*5%) -> 0.44333333 | AN16: =IF(OR($Z16="",$T16=""),0,$Z16*10%) -> 0.88666667 | AO16: =IF($Z16="",0,IF($U16="",0,$U16)) -> 2
A17: =IF(D17="","",A16+1) -> 14 | D17: Under-Dispensing | F17: Competitive | O17: 3 | P17: 5 | Q17: 3 | S17: 1 | T17: 5 | U17: 2 | V17: =SUM(M17:U17) -> 19 | W17: =V17 - (V17 * (SUBSTITUTE(SUBSTITUTE($W$2, "Optimistic (", ""), "%)", "") / 100)) -> 9.5 | X17: =V17 + (V17 * (SUBSTITUTE(SUBSTITUTE($X$2, "Pessimistic (", ""), "%)", "") / 100)) -> 20.9 | Y17: =(W17+(4*V17)+X17)/6 -> 17.733333 | Z17: =Y17/2 -> 8.8666667 | AE17: =IF($Z17="",0,IF($M17="",0,$M17)) -> 0 | AF17: =IF(OR($Z17="",$N17=""),0,$Z17*5%) -> 0 | AG17: =IF(OR($Z17="",$O17=""),0,$Z17*10%) -> 0.88666667 | AH17: =IF($Z17="",0,IF(AND($P17="",$Q17=""),($Z17-$AE17-$AF17-$AG17-$AI17-$AK17-$AL17-$AM17-$AN17-$AO17),IF($P17="",0,IF($Q17="",($Z17-$AE17-$AF17-$AG17-$AI17-$AK17-$AL17-$AM17-$AN17-$AO17),($Z17-$AE17-$AF17-$AG17-$AI17-$AK17-$AL17-$AM17-$AN17-$AO17)*40%/(40%+15%))))) -> 2.0509091 | AI17: =IF($Z17="",0,IF($P17="",0,0.5)) -> 0.5 | AJ17: =IF($Z17="",0,IF(AND($P17="",$Q17=""),0,IF($Q17="",0,IF($P17="",($Z17-$AE17-$AF17-$AG17-$AI17-$AK17-$AL17-$AM17-$AN17-$AO17),($Z17-$AE17-$AF17-$AG17-$AI17-$AK17-$AL17-$AM17-$AN17-$AO17)*15%/(40%+15%))))) -> 0.76909091 | AK17: =IF($Z17="",0,$Z17*15%) -> 1.33 | AL17: =IF($Z17="",0,IF($R17="",0,$R17)) -> 0 | AM17: =IF(OR($Z17="",$S17=""),0,$Z17*5%) -> 0.44333333 | AN17: =IF(OR($Z17="",$T17=""),0,$Z17*10%) -> 0.88666667 | AO17: =IF($Z17="",0,IF($U17="",0,$U17)) -> 2
A18: =IF(D18="","",A17+1) -> 15 | C18: System Alarms | D18: Connectivity loss alerts (done) | F18: PGL | O18: 2 | P18: 5 | Q18: 2 | S18: 1 | T18: 2 | U18: 2 | V18: =SUM(M18:U18) -> 14 | W18: =V18 - (V18 * (SUBSTITUTE(SUBSTITUTE($W$2, "Optimistic (", ""), "%)", "") / 100)) -> 7 | X18: =V18 + (V18 * (SUBSTITUTE(SUBSTITUTE($X$2, "Pessimistic (", ""), "%)", "") / 100)) -> 15.4 | Y18: =(W18+(4*V18)+X18)/6 -> 13.066667 | Z18: =Y18/2 -> 6.5333333 | AE18: =IF($Z18="",0,IF($M18="",0,$M18)) -> 0 | AF18: =IF(OR($Z18="",$N18=""),0,$Z18*5%) -> 0 | AG18: =IF(OR($Z18="",$O18=""),0,$Z18*10%) -> 0.65333333 | AH18: =IF($Z18="",0,IF(AND($P18="",$Q18=""),($Z18-$AE18-$AF18-$AG18-$AI18-$AK18-$AL18-$AM18-$AN18-$AO18),IF($P18="",0,IF($Q18="",($Z18-$AE18-$AF18-$AG18-$AI18-$AK18-$AL18-$AM18-$AN18-$AO18),($Z18-$AE18-$AF18-$AG18-$AI18-$AK18-$AL18-$AM18-$AN18-$AO18)*40%/(40%+15%))))) -> 1.0327273 | AI18: =IF($Z18="",0,IF($P18="",0,0.5)) -> 0.5 | AJ18: =IF($Z18="",0,IF(AND($P18="",$Q18=""),0,IF($Q18="",0,IF($P18="",($Z18-$AE18-$AF18-$AG18-$AI18-$AK18-$AL18-$AM18-$AN18-$AO18),($Z18-$AE18-$AF18-$AG18-$AI18-$AK18-$AL18-$AM18-$AN18-$AO18)*15%/(40%+15%))))) -> 0.38727273 | AK18: =IF($Z18="",0,$Z18*15%) -> 0.98 | AL18: =IF($Z18="",0,IF($R18="",0,$R18)) -> 0 | AM18: =IF(OR($Z18="",$S18=""),0,$Z18*5%) -> 0.32666667 | AN18: =IF(OR($Z18="",$T18=""),0,$Z18*10%) -> 0.65333333 | AO18: =IF($Z18="",0,IF($U18="",0,$U18)) -> 2
A19: =IF(D19="","",A18+1) -> 16 | C19: ML | D19: Pricing/profit optimization | F19: Competitive | U19: 2 | V19: =SUM(M19:U19) -> 2 | W19: =V19 - (V19 * (SUBSTITUTE(SUBSTITUTE($W$2, "Optimistic (", ""), "%)", "") / 100)) -> 1 | X19: =V19 + (V19 * (SUBSTITUTE(SUBSTITUTE($X$2, "Pessimistic (", ""), "%)", "") / 100)) -> 2.2 | Y19: =(W19+(4*V19)+X19)/6 -> 1.8666667 | Z19: =Y19/2 -> 0.93333333 | AE19: =IF($Z19="",0,IF($M19="",0,$M19)) -> 0 | AF19: =IF(OR($Z19="",$N19=""),0,$Z19*5%) -> 0 | AG19: =IF(OR($Z19="",$O19=""),0,$Z19*10%) -> 0 | AH19: =IF($Z19="",0,IF(AND($P19="",$Q19=""),($Z19-$AE19-$AF19-$AG19-$AI19-$AK19-$AL19-$AM19-$AN19-$AO19),IF($P19="",0,IF($Q19="",($Z19-$AE19-$AF19-$AG19-$AI19-$AK19-$AL19-$AM19-$AN19-$AO19),($Z19-$AE19-$AF19-$AG19-$AI19-$AK19-$AL19-$AM19-$AN19-$AO19)*40%/(40%+15%))))) -> -1.2066667 | AI19: =IF($Z19="",0,IF($P19="",0,0.5)) -> 0 | AJ19: =IF($Z19="",0,IF(AND($P19="",$Q19=""),0,IF($Q19="",0,IF($P19="",($Z19-$AE19-$AF19-$AG19-$AI19-$AK19-$AL19-$AM19-$AN19-$AO19),($Z19-$AE19-$AF19-$AG19-$AI19-$AK19-$AL19-$AM19-$AN19-$AO19)*15%/(40%+15%))))) -> 0 | AK19: =IF($Z19="",0,$Z19*15%) -> 0.14 | AL19: =IF($Z19="",0,IF($R19="",0,$R19)) -> 0 | AM19: =IF(OR($Z19="",$S19=""),0,$Z19*5%) -> 0 | AN19: =IF(OR($Z19="",$T19=""),0,$Z19*10%) -> 0 | AO19: =IF($Z19="",0,IF($U19="",0,$U19)) -> 2
A20: =IF(D20="","",A19+1) -> 17 | D20: Predictive Maintenance | F20: Competitive | U20: 2 | V20: =SUM(M20:U20) -> 2 | W20: =V20 - (V20 * (SUBSTITUTE(SUBSTITUTE($W$2, "Optimistic (", ""), "%)", "") / 100)) -> 1 | X20: =V20 + (V20 * (SUBSTITUTE(SUBSTITUTE($X$2, "Pessimistic (", ""), "%)", "") / 100)) -> 2.2 | Y20: =(W20+(4*V20)+X20)/6 -> 1.8666667 | Z20: =Y20/2 -> 0.93333333 | AE20: =IF($Z20="",0,IF($M20="",0,$M20)) -> 0 | AF20: =IF(OR($Z20="",$N20=""),0,$Z20*5%) -> 0 | AG20: =IF(OR($Z20="",$O20=""),0,$Z20*10%) -> 0 | AH20: =IF($Z20="",0,IF(AND($P20="",$Q20=""),($Z20-$AE20-$AF20-$AG20-$AI20-$AK20-$AL20-$AM20-$AN20-$AO20),IF($P20="",0,IF($Q20="",($Z20-$AE20-$AF20-$AG20-$AI20-$AK20-$AL20-$AM20-$AN20-$AO20),($Z20-$AE20-$AF20-$AG20-$AI20-$AK20-$AL20-$AM20-$AN20-$AO20)*40%/(40%+15%))))) -> -1.2066667 | AI20: =IF($Z20="",0,IF($P20="",0,0.5)) -> 0 | AJ20: =IF($Z20="",0,IF(AND($P20="",$Q20=""),0,IF($Q20="",0,IF($P20="",($Z20-$AE20-$AF20-$AG20-$AI20-$AK20-$AL20-$AM20-$AN20-$AO20),($Z20-$AE20-$AF20-$AG20-$AI20-$AK20-$AL20-$AM20-$AN20-$AO20)*15%/(40%+15%))))) -> 0 | AK20: =IF($Z20="",0,$Z20*15%) -> 0.14 | AL20: =IF($Z20="",0,IF($R20="",0,$R20)) -> 0 | AM20: =IF(OR($Z20="",$S20=""),0,$Z20*5%) -> 0 | AN20: =IF(OR($Z20="",$T20=""),0,$Z20*10%) -> 0 | AO20: =IF($Z20="",0,IF($U20="",0,$U20)) -> 2
A21: =IF(D21="","",A20+1) -> 18 | D21: Sudden Loss indicator | F21: Competitive | U21: 2 | V21: =SUM(M21:U21) -> 2 | W21: =V21 - (V21 * (SUBSTITUTE(SUBSTITUTE($W$2, "Optimistic (", ""), "%)", "") / 100)) -> 1 | X21: =V21 + (V21 * (SUBSTITUTE(SUBSTITUTE($X$2, "Pessimistic (", ""), "%)", "") / 100)) -> 2.2 | Y21: =(W21+(4*V21)+X21)/6 -> 1.8666667 | Z21: =Y21/2 -> 0.93333333 | AE21: =IF($Z21="",0,IF($M21="",0,$M21)) -> 0 | AF21: =IF(OR($Z21="",$N21=""),0,$Z21*5%) -> 0 | AG21: =IF(OR($Z21="",$O21=""),0,$Z21*10%) -> 0 | AH21: =IF($Z21="",0,IF(AND($P21="",$Q21=""),($Z21-$AE21-$AF21-$AG21-$AI21-$AK21-$AL21-$AM21-$AN21-$AO21),IF($P21="",0,IF($Q21="",($Z21-$AE21-$AF21-$AG21-$AI21-$AK21-$AL21-$AM21-$AN21-$AO21),($Z21-$AE21-$AF21-$AG21-$AI21-$AK21-$AL21-$AM21-$AN21-$AO21)*40%/(40%+15%))))) -> -1.2066667 | AI21: =IF($Z21="",0,IF($P21="",0,0.5)) -> 0 | AJ21: =IF($Z21="",0,IF(AND($P21="",$Q21=""),0,IF($Q21="",0,IF($P21="",($Z21-$AE21-$AF21-$AG21-$AI21-$AK21-$AL21-$AM21-$AN21-$AO21),($Z21-$AE21-$AF21-$AG21-$AI21-$AK21-$AL21-$AM21-$AN21-$AO21)*15%/(40%+15%))))) -> 0 | AK21: =IF($Z21="",0,$Z21*15%) -> 0.14 | AL21: =IF($Z21="",0,IF($R21="",0,$R21)) -> 0 | AM21: =IF(OR($Z21="",$S21=""),0,$Z21*5%) -> 0 | AN21: =IF(OR($Z21="",$T21=""),0,$Z21*10%) -> 0 | AO21: =IF($Z21="",0,IF($U21="",0,$U21)) -> 2
A22: =IF(D22="","",A21+1) -> 19 | B22: Administration | C22: URM | D22: User & role management | E22: https://octopusdtlsupport.atlassian.net/browse/FF-541 | F22: PGL | O22: 5 | P22: 6 | Q22: 3 | S22: 3 | T22: 5 | U22: 2 | V22: =SUM(M22:U22) -> 24 | W22: =V22 - (V22 * (SUBSTITUTE(SUBSTITUTE($W$2, "Optimistic (", ""), "%)", "") / 100)) -> 12 | X22: =V22 + (V22 * (SUBSTITUTE(SUBSTITUTE($X$2, "Pessimistic (", ""), "%)", "") / 100)) -> 26.4 | Y22: =(W22+(4*V22)+X22)/6 -> 22.4 | Z22: =Y22/2 -> 11.2 | AA22: 46227 | AE22: =IF($Z22="",0,IF($M22="",0,$M22)) -> 0 | AF22: =IF(OR($Z22="",$N22=""),0,$Z22*5%) -> 0 | AG22: =IF(OR($Z22="",$O22=""),0,$Z22*10%) -> 1.12 | AH22: =IF($Z22="",0,IF(AND($P22="",$Q22=""),($Z22-$AE22-$AF22-$AG22-$AI22-$AK22-$AL22-$AM22-$AN22-$AO22),IF($P22="",0,IF($Q22="",($Z22-$AE22-$AF22-$AG22-$AI22-$AK22-$AL22-$AM22-$AN22-$AO22),($Z22-$AE22-$AF22-$AG22-$AI22-$AK22-$AL22-$AM22-$AN22-$AO22)*40%/(40%+15%))))) -> 3.0690909 | AI22: =IF($Z22="",0,IF($P22="",0,0.5)) -> 0.5 | AJ22: =IF($Z22="",0,IF(AND($P22="",$Q22=""),0,IF($Q22="",0,IF($P22="",($Z22-$AE22-$AF22-$AG22-$AI22-$AK22-$AL22-$AM22-$AN22-$AO22),($Z22-$AE22-$AF22-$AG22-$AI22-$AK22-$AL22-$AM22-$AN22-$AO22)*15%/(40%+15%))))) -> 1.1509091 | AK22: =IF($Z22="",0,$Z22*15%) -> 1.68 | AL22: =IF($Z22="",0,IF($R22="",0,$R22)) -> 0 | AM22: =IF(OR($Z22="",$S22=""),0,$Z22*5%) -> 0.56 | AN22: =IF(OR($Z22="",$T22=""),0,$Z22*10%) -> 1.12 | AO22: =IF($Z22="",0,IF($U22="",0,$U22)) -> 2
A23: =IF(D23="","",A22+1) -> 20 | C23: Configuration | D23: Station and tank configuration | F23: PGL | O23: 3 | P23: 5 | Q23: 4 | S23: 1 | T23: 3 | U23: 2 | V23: =SUM(M23:U23) -> 18 | W23: =V23 - (V23 * (SUBSTITUTE(SUBSTITUTE($W$2, "Optimistic (", ""), "%)", "") / 100)) -> 9 | X23: =V23 + (V23 * (SUBSTITUTE(SUBSTITUTE($X$2, "Pessimistic (", ""), "%)", "") / 100)) -> 19.8 | Y23: =(W23+(4*V23)+X23)/6 -> 16.8 | Z23: =Y23/2 -> 8.4 | AE23: =IF($Z23="",0,IF($M23="",0,$M23)) -> 0 | AF23: =IF(OR($Z23="",$N23=""),0,$Z23*5%) -> 0 | AG23: =IF(OR($Z23="",$O23=""),0,$Z23*10%) -> 0.84 | AH23: =IF($Z23="",0,IF(AND($P23="",$Q23=""),($Z23-$AE23-$AF23-$AG23-$AI23-$AK23-$AL23-$AM23-$AN23-$AO23),IF($P23="",0,IF($Q23="",($Z23-$AE23-$AF23-$AG23-$AI23-$AK23-$AL23-$AM23-$AN23-$AO23),($Z23-$AE23-$AF23-$AG23-$AI23-$AK23-$AL23-$AM23-$AN23-$AO23)*40%/(40%+15%))))) -> 1.8472727 | AI23: =IF($Z23="",0,IF($P23="",0,0.5)) -> 0.5 | AJ23: =IF($Z23="",0,IF(AND($P23="",$Q23=""),0,IF($Q23="",0,IF($P23="",($Z23-$AE23-$AF23-$AG23-$AI23-$AK23-$AL23-$AM23-$AN23-$AO23),($Z23-$AE23-$AF23-$AG23-$AI23-$AK23-$AL23-$AM23-$AN23-$AO23)*15%/(40%+15%))))) -> 0.69272727 | AK23: =IF($Z23="",0,$Z23*15%) -> 1.26 | AL23: =IF($Z23="",0,IF($R23="",0,$R23)) -> 0 | AM23: =IF(OR($Z23="",$S23=""),0,$Z23*5%) -> 0.42 | AN23: =IF(OR($Z23="",$T23=""),0,$Z23*10%) -> 0.84 | AO23: =IF($Z23="",0,IF($U23="",0,$U23)) -> 2
A24: =IF(D24="","",A23+1) -> 21 | D24: Product mapping | F24: PGL | O24: 3 | P24: 3 | Q24: 2 | S24: 1 | T24: 3 | U24: 2 | V24: =SUM(M24:U24) -> 14 | W24: =V24 - (V24 * (SUBSTITUTE(SUBSTITUTE($W$2, "Optimistic (", ""), "%)", "") / 100)) -> 7 | X24: =V24 + (V24 * (SUBSTITUTE(SUBSTITUTE($X$2, "Pessimistic (", ""), "%)", "") / 100)) -> 15.4 | Y24: =(W24+(4*V24)+X24)/6 -> 13.066667 | Z24: =Y24/2 -> 6.5333333 | AE24: =IF($Z24="",0,IF($M24="",0,$M24)) -> 0 | AF24: =IF(OR($Z24="",$N24=""),0,$Z24*5%) -> 0 | AG24: =IF(OR($Z24="",$O24=""),0,$Z24*10%) -> 0.65333333 | AH24: =IF($Z24="",0,IF(AND($P24="",$Q24=""),($Z24-$AE24-$AF24-$AG24-$AI24-$AK24-$AL24-$AM24-$AN24-$AO24),IF($P24="",0,IF($Q24="",($Z24-$AE24-$AF24-$AG24-$AI24-$AK24-$AL24-$AM24-$AN24-$AO24),($Z24-$AE24-$AF24-$AG24-$AI24-$AK24-$AL24-$AM24-$AN24-$AO24)*40%/(40%+15%))))) -> 1.0327273 | AI24: =IF($Z24="",0,IF($P24="",0,0.5)) -> 0.5 | AJ24: =IF($Z24="",0,IF(AND($P24="",$Q24=""),0,IF($Q24="",0,IF($P24="",($Z24-$AE24-$AF24-$AG24-$AI24-$AK24-$AL24-$AM24-$AN24-$AO24),($Z24-$AE24-$AF24-$AG24-$AI24-$AK24-$AL24-$AM24-$AN24-$AO24)*15%/(40%+15%))))) -> 0.38727273 | AK24: =IF($Z24="",0,$Z24*15%) -> 0.98 | AL24: =IF($Z24="",0,IF($R24="",0,$R24)) -> 0 | AM24: =IF(OR($Z24="",$S24=""),0,$Z24*5%) -> 0.32666667 | AN24: =IF(OR($Z24="",$T24=""),0,$Z24*10%) -> 0.65333333 | AO24: =IF($Z24="",0,IF($U24="",0,$U24)) -> 2
A25: =IF(D25="","",A24+1) -> 22 | D25: Unit and currency settings | F25: PGL | O25: 4 | P25: 10 | Q25: 5 | S25: 3 | T25: 6 | U25: 2 | V25: =SUM(M25:U25) -> 30 | W25: =V25 - (V25 * (SUBSTITUTE(SUBSTITUTE($W$2, "Optimistic (", ""), "%)", "") / 100)) -> 15 | X25: =V25 + (V25 * (SUBSTITUTE(SUBSTITUTE($X$2, "Pessimistic (", ""), "%)", "") / 100)) -> 33 | Y25: =(W25+(4*V25)+X25)/6 -> 28 | Z25: =Y25/2 -> 14 | AE25: =IF($Z25="",0,IF($M25="",0,$M25)) -> 0 | AF25: =IF(OR($Z25="",$N25=""),0,$Z25*5%) -> 0 | AG25: =IF(OR($Z25="",$O25=""),0,$Z25*10%) -> 1.4 | AH25: =IF($Z25="",0,IF(AND($P25="",$Q25=""),($Z25-$AE25-$AF25-$AG25-$AI25-$AK25-$AL25-$AM25-$AN25-$AO25),IF($P25="",0,IF($Q25="",($Z25-$AE25-$AF25-$AG25-$AI25-$AK25-$AL25-$AM25-$AN25-$AO25),($Z25-$AE25-$AF25-$AG25-$AI25-$AK25-$AL25-$AM25-$AN25-$AO25)*40%/(40%+15%))))) -> 4.2909091 | AI25: =IF($Z25="",0,IF($P25="",0,0.5)) -> 0.5 | AJ25: =IF($Z25="",0,IF(AND($P25="",$Q25=""),0,IF($Q25="",0,IF($P25="",($Z25-$AE25-$AF25-$AG25-$AI25-$AK25-$AL25-$AM25-$AN25-$AO25),($Z25-$AE25-$AF25-$AG25-$AI25-$AK25-$AL25-$AM25-$AN25-$AO25)*15%/(40%+15%))))) -> 1.6090909 | AK25: =IF($Z25="",0,$Z25*15%) -> 2.1 | AL25: =IF($Z25="",0,IF($R25="",0,$R25)) -> 0 | AM25: =IF(OR($Z25="",$S25=""),0,$Z25*5%) -> 0.7 | AN25: =IF(OR($Z25="",$T25=""),0,$Z25*10%) -> 1.4 | AO25: =IF($Z25="",0,IF($U25="",0,$U25)) -> 2 | AQ25: *Would require a session with IA as well for showing data on dashboard of sites with different currencies *Understanding session is required with PGL
A26: =IF(D26="","",A25+1) -> 23 | C26: Audit | D26: Audit trails (phase 1) - User-management | E26: https://octopusdtlsupport.atlassian.net/browse/FF-446 | F26: PGL | O26: 5 | P26: 15 | Q26: 5 | U26: 2 | V26: =SUM(M26:U26) -> 27 | W26: =V26 - (V26 * (SUBSTITUTE(SUBSTITUTE($W$2, "Optimistic (", ""), "%)", "") / 100)) -> 13.5 | X26: =V26 + (V26 * (SUBSTITUTE(SUBSTITUTE($X$2, "Pessimistic (", ""), "%)", "") / 100)) -> 29.7 | Y26: =(W26+(4*V26)+X26)/6 -> 25.2 | Z26: =Y26/2 -> 12.6 | AA26: 46160 | AB26: 46171 | AC26: 46174 | AD26: 46176 | AE26: =IF($Z26="",0,IF($M26="",0,$M26)) -> 0 | AF26: =IF(OR($Z26="",$N26=""),0,$Z26*5%) -> 0 | AG26: =IF(OR($Z26="",$O26=""),0,$Z26*10%) -> 1.26 | AH26: =IF($Z26="",0,IF(AND($P26="",$Q26=""),($Z26-$AE26-$AF26-$AG26-$AI26-$AK26-$AL26-$AM26-$AN26-$AO26),IF($P26="",0,IF($Q26="",($Z26-$AE26-$AF26-$AG26-$AI26-$AK26-$AL26-$AM26-$AN26-$AO26),($Z26-$AE26-$AF26-$AG26-$AI26-$AK26-$AL26-$AM26-$AN26-$AO26)*40%/(40%+15%))))) -> 5.0545455 | AI26: =IF($Z26="",0,IF($P26="",0,0.5)) -> 0.5 | AJ26: =IF($Z26="",0,IF(AND($P26="",$Q26=""),0,IF($Q26="",0,IF($P26="",($Z26-$AE26-$AF26-$AG26-$AI26-$AK26-$AL26-$AM26-$AN26-$AO26),($Z26-$AE26-$AF26-$AG26-$AI26-$AK26-$AL26-$AM26-$AN26-$AO26)*15%/(40%+15%))))) -> 1.8954545 | AK26: =IF($Z26="",0,$Z26*15%) -> 1.89 | AL26: =IF($Z26="",0,IF($R26="",0,$R26)) -> 0 | AM26: =IF(OR($Z26="",$S26=""),0,$Z26*5%) -> 0 | AN26: =IF(OR($Z26="",$T26=""),0,$Z26*10%) -> 0 | AO26: =IF($Z26="",0,IF($U26="",0,$U26)) -> 2
A27: =IF(D27="","",A26+1) -> 24 | D27: Audit trails (phase 2) - Module Interaction | E27: https://octopusdtlsupport.atlassian.net/browse/FF-512 | F27: PGL | O27: 5 | P27: =12+3 -> 15 | Q27: 5 | S27: 2 | T27: 5 | U27: 2 | V27: =SUM(M27:U27) -> 34 | W27: =V27 - (V27 * (SUBSTITUTE(SUBSTITUTE($W$2, "Optimistic (", ""), "%)", "") / 100)) -> 17 | X27: =V27 + (V27 * (SUBSTITUTE(SUBSTITUTE($X$2, "Pessimistic (", ""), "%)", "") / 100)) -> 37.4 | Y27: =(W27+(4*V27)+X27)/6 -> 31.733333 | Z27: =Y27/2 -> 15.866667 | AA27: 46177 | AB27: 46190 | AC27: 46191 | AD27: 46195 | AE27: =IF($Z27="",0,IF($M27="",0,$M27)) -> 0 | AF27: =IF(OR($Z27="",$N27=""),0,$Z27*5%) -> 0 | AG27: =IF(OR($Z27="",$O27=""),0,$Z27*10%) -> 1.5866667 | AH27: =IF($Z27="",0,IF(AND($P27="",$Q27=""),($Z27-$AE27-$AF27-$AG27-$AI27-$AK27-$AL27-$AM27-$AN27-$AO27),IF($P27="",0,IF($Q27="",($Z27-$AE27-$AF27-$AG27-$AI27-$AK27-$AL27-$AM27-$AN27-$AO27),($Z27-$AE27-$AF27-$AG27-$AI27-$AK27-$AL27-$AM27-$AN27-$AO27)*40%/(40%+15%))))) -> 5.1054545 | AI27: =IF($Z27="",0,IF($P27="",0,0.5)) -> 0.5 | AJ27: =IF($Z27="",0,IF(AND($P27="",$Q27=""),0,IF($Q27="",0,IF($P27="",($Z27-$AE27-$AF27-$AG27-$AI27-$AK27-$AL27-$AM27-$AN27-$AO27),($Z27-$AE27-$AF27-$AG27-$AI27-$AK27-$AL27-$AM27-$AN27-$AO27)*15%/(40%+15%))))) -> 1.9145455 | AK27: =IF($Z27="",0,$Z27*15%) -> 2.38 | AL27: =IF($Z27="",0,IF($R27="",0,$R27)) -> 0 | AM27: =IF(OR($Z27="",$S27=""),0,$Z27*5%) -> 0.79333333 | AN27: =IF(OR($Z27="",$T27=""),0,$Z27*10%) -> 1.5866667 | AO27: =IF($Z27="",0,IF($U27="",0,$U27)) -> 2
A28: =IF(D28="","",A27+1) -> 25 | D28: Audit trails (phase 3) - Activity Log | E28: https://octopusdtlsupport.atlassian.net/browse/FF-517 | F28: PGL | O28: 5 | P28: =7+3 -> 10 | Q28: 5 | S28: 2 | T28: 5 | U28: 2 | V28: =SUM(M28:U28) -> 29 | W28: =V28 - (V28 * (SUBSTITUTE(SUBSTITUTE($W$2, "Optimistic (", ""), "%)", "") / 100)) -> 14.5 | X28: =V28 + (V28 * (SUBSTITUTE(SUBSTITUTE($X$2, "Pessimistic (", ""), "%)", "") / 100)) -> 31.9 | Y28: =(W28+(4*V28)+X28)/6 -> 27.066667 | Z28: =Y28/2 -> 13.533333 | AA28: 46195 | AB28: 46203 | AC28: 46204 | AD28: 46206 | AE28: =IF($Z28="",0,IF($M28="",0,$M28)) -> 0 | AF28: =IF(OR($Z28="",$N28=""),0,$Z28*5%) -> 0 | AG28: =IF(OR($Z28="",$O28=""),0,$Z28*10%) -> 1.3533333 | AH28: =IF($Z28="",0,IF(AND($P28="",$Q28=""),($Z28-$AE28-$AF28-$AG28-$AI28-$AK28-$AL28-$AM28-$AN28-$AO28),IF($P28="",0,IF($Q28="",($Z28-$AE28-$AF28-$AG28-$AI28-$AK28-$AL28-$AM28-$AN28-$AO28),($Z28-$AE28-$AF28-$AG28-$AI28-$AK28-$AL28-$AM28-$AN28-$AO28)*40%/(40%+15%))))) -> 4.0872727 | AI28: =IF($Z28="",0,IF($P28="",0,0.5)) -> 0.5 | AJ28: =IF($Z28="",0,IF(AND($P28="",$Q28=""),0,IF($Q28="",0,IF($P28="",($Z28-$AE28-$AF28-$AG28-$AI28-$AK28-$AL28-$AM28-$AN28-$AO28),($Z28-$AE28-$AF28-$AG28-$AI28-$AK28-$AL28-$AM28-$AN28-$AO28)*15%/(40%+15%))))) -> 1.5327273 | AK28: =IF($Z28="",0,$Z28*15%) -> 2.03 | AL28: =IF($Z28="",0,IF($R28="",0,$R28)) -> 0 | AM28: =IF(OR($Z28="",$S28=""),0,$Z28*5%) -> 0.67666667 | AN28: =IF(OR($Z28="",$T28=""),0,$Z28*10%) -> 1.3533333 | AO28: =IF($Z28="",0,IF($U28="",0,$U28)) -> 2
A29: =IF(D29="","",A28+1) -> 26 | B29: OutPut | C29: Mobile | D29: Mobile View without Manual submit Data | F29: Competitive | N29: 5 | O29: 3 | P29: 15 | Q29: 10 | S29: 3 | T29: 5 | U29: 2 | V29: =SUM(M29:U29) -> 43 | W29: =V29 - (V29 * (SUBSTITUTE(SUBSTITUTE($W$2, "Optimistic (", ""), "%)", "") / 100)) -> 21.5 | X29: =V29 + (V29 * (SUBSTITUTE(SUBSTITUTE($X$2, "Pessimistic (", ""), "%)", "") / 100)) -> 47.3 | Y29: =(W29+(4*V29)+X29)/6 -> 40.133333 | Z29: =Y29/2 -> 20.066667 | AE29: =IF($Z29="",0,IF($M29="",0,$M29)) -> 0 | AF29: =IF(OR($Z29="",$N29=""),0,$Z29*5%) -> 1.0033333 | AG29: =IF(OR($Z29="",$O29=""),0,$Z29*10%) -> 2.0066667 | AH29: =IF($Z29="",0,IF(AND($P29="",$Q29=""),($Z29-$AE29-$AF29-$AG29-$AI29-$AK29-$AL29-$AM29-$AN29-$AO29),IF($P29="",0,IF($Q29="",($Z29-$AE29-$AF29-$AG29-$AI29-$AK29-$AL29-$AM29-$AN29-$AO29),($Z29-$AE29-$AF29-$AG29-$AI29-$AK29-$AL29-$AM29-$AN29-$AO29)*40%/(40%+15%))))) -> 6.2084848 | AI29: =IF($Z29="",0,IF($P29="",0,0.5)) -> 0.5 | AJ29: =IF($Z29="",0,IF(AND($P29="",$Q29=""),0,IF($Q29="",0,IF($P29="",($Z29-$AE29-$AF29-$AG29-$AI29-$AK29-$AL29-$AM29-$AN29-$AO29),($Z29-$AE29-$AF29-$AG29-$AI29-$AK29-$AL29-$AM29-$AN29-$AO29)*15%/(40%+15%))))) -> 2.3281818 | AK29: =IF($Z29="",0,$Z29*15%) -> 3.01 | AL29: =IF($Z29="",0,IF($R29="",0,$R29)) -> 0 | AM29: =IF(OR($Z29="",$S29=""),0,$Z29*5%) -> 1.0033333 | AN29: =IF(OR($Z29="",$T29=""),0,$Z29*10%) -> 2.0066667 | AO29: =IF($Z29="",0,IF($U29="",0,$U29)) -> 2
A30: =IF(D30="","",A29+1) -> 27 | C30: ReadAPI | D30: ReadAPI to pull data from FintechFuel - (21h) | F30: Competitive | P30: 20 | Q30: 10 | S30: 5 | T30: 6 | U30: 2 | V30: =SUM(M30:U30) -> 43 | W30: =V30 - (V30 * (SUBSTITUTE(SUBSTITUTE($W$2, "Optimistic (", ""), "%)", "") / 100)) -> 21.5 | X30: =V30 + (V30 * (SUBSTITUTE(SUBSTITUTE($X$2, "Pessimistic (", ""), "%)", "") / 100)) -> 47.3 | Y30: =(W30+(4*V30)+X30)/6 -> 40.133333 | Z30: =Y30/2 -> 20.066667 | AA30: 46209 | AB30: 46220 | AC30: 46220 | AD30: 46227 | AE30: =IF($Z30="",0,IF($M30="",0,$M30)) -> 0 | AF30: =IF(OR($Z30="",$N30=""),0,$Z30*5%) -> 0 | AG30: =IF(OR($Z30="",$O30=""),0,$Z30*10%) -> 0 | AH30: =IF($Z30="",0,IF(AND($P30="",$Q30=""),($Z30-$AE30-$AF30-$AG30-$AI30-$AK30-$AL30-$AM30-$AN30-$AO30),IF($P30="",0,IF($Q30="",($Z30-$AE30-$AF30-$AG30-$AI30-$AK30-$AL30-$AM30-$AN30-$AO30),($Z30-$AE30-$AF30-$AG30-$AI30-$AK30-$AL30-$AM30-$AN30-$AO30)*40%/(40%+15%))))) -> 8.3975758 | AI30: =IF($Z30="",0,IF($P30="",0,0.5)) -> 0.5 | AJ30: =IF($Z30="",0,IF(AND($P30="",$Q30=""),0,IF($Q30="",0,IF($P30="",($Z30-$AE30-$AF30-$AG30-$AI30-$AK30-$AL30-$AM30-$AN30-$AO30),($Z30-$AE30-$AF30-$AG30-$AI30-$AK30-$AL30-$AM30-$AN30-$AO30)*15%/(40%+15%))))) -> 3.1490909 | AK30: =IF($Z30="",0,$Z30*15%) -> 3.01 | AL30: =IF($Z30="",0,IF($R30="",0,$R30)) -> 0 | AM30: =IF(OR($Z30="",$S30=""),0,$Z30*5%) -> 1.0033333 | AN30: =IF(OR($Z30="",$T30=""),0,$Z30*10%) -> 2.0066667 | AO30: =IF($Z30="",0,IF($U30="",0,$U30)) -> 2
A31: =IF(D31="","",A30+1) -> 28 | C31: Write-Back | D31: Write-Back Price to stations - (10h) | E31: https://octopusdtlsupport.atlassian.net/browse/FF-302 | F31: PGL | O31: =5+1 -> 6 | P31: =16+10 -> 26 | Q31: 10 | T31: 3 | U31: 2 | V31: =SUM(M31:U31) -> 47 | W31: =V31 - (V31 * (SUBSTITUTE(SUBSTITUTE($W$2, "Optimistic (", ""), "%)", "") / 100)) -> 23.5 | X31: =V31 + (V31 * (SUBSTITUTE(SUBSTITUTE($X$2, "Pessimistic (", ""), "%)", "") / 100)) -> 51.7 | Y31: =(W31+(4*V31)+X31)/6 -> 43.866667 | Z31: =Y31/2 -> 21.933333 | AA31: 46132 | AB31: 46142 | AC31: 46143 | AD31: 46153 | AE31: =IF($Z31="",0,IF($M31="",0,$M31)) -> 0 | AF31: =IF(OR($Z31="",$N31=""),0,$Z31*5%) -> 0 | AG31: =IF(OR($Z31="",$O31=""),0,$Z31*10%) -> 2.1933333 | AH31: =IF($Z31="",0,IF(AND($P31="",$Q31=""),($Z31-$AE31-$AF31-$AG31-$AI31-$AK31-$AL31-$AM31-$AN31-$AO31),IF($P31="",0,IF($Q31="",($Z31-$AE31-$AF31-$AG31-$AI31-$AK31-$AL31-$AM31-$AN31-$AO31),($Z31-$AE31-$AF31-$AG31-$AI31-$AK31-$AL31-$AM31-$AN31-$AO31)*40%/(40%+15%))))) -> 8.550303 | AI31: =IF($Z31="",0,IF($P31="",0,0.5)) -> 0.5 | AJ31: =IF($Z31="",0,IF(AND($P31="",$Q31=""),0,IF($Q31="",0,IF($P31="",($Z31-$AE31-$AF31-$AG31-$AI31-$AK31-$AL31-$AM31-$AN31-$AO31),($Z31-$AE31-$AF31-$AG31-$AI31-$AK31-$AL31-$AM31-$AN31-$AO31)*15%/(40%+15%))))) -> 3.2063636 | AK31: =IF($Z31="",0,$Z31*15%) -> 3.29 | AL31: =IF($Z31="",0,IF($R31="",0,$R31)) -> 0 | AM31: =IF(OR($Z31="",$S31=""),0,$Z31*5%) -> 0 | AN31: =IF(OR($Z31="",$T31=""),0,$Z31*10%) -> 2.1933333 | AO31: =IF($Z31="",0,IF($U31="",0,$U31)) -> 2
A32: =IF(D32="","",A31+1) -> 29 | C32: Notification | D32: Notification via Email /SMS | F32: PGL | O32: 1 | P32: 2 | Q32: 2 | S32: 1 | T32: 2 | V32: =SUM(M32:U32) -> 8 | W32: =V32 - (V32 * (SUBSTITUTE(SUBSTITUTE($W$2, "Optimistic (", ""), "%)", "") / 100)) -> 4 | X32: =V32 + (V32 * (SUBSTITUTE(SUBSTITUTE($X$2, "Pessimistic (", ""), "%)", "") / 100)) -> 8.8 | Y32: =(W32+(4*V32)+X32)/6 -> 7.4666667 | Z32: =Y32/2 -> 3.7333333 | AE32: =IF($Z32="",0,IF($M32="",0,$M32)) -> 0 | AF32: =IF(OR($Z32="",$N32=""),0,$Z32*5%) -> 0 | AG32: =IF(OR($Z32="",$O32=""),0,$Z32*10%) -> 0.37333333 | AH32: =IF($Z32="",0,IF(AND($P32="",$Q32=""),($Z32-$AE32-$AF32-$AG32-$AI32-$AK32-$AL32-$AM32-$AN32-$AO32),IF($P32="",0,IF($Q32="",($Z32-$AE32-$AF32-$AG32-$AI32-$AK32-$AL32-$AM32-$AN32-$AO32),($Z32-$AE32-$AF32-$AG32-$AI32-$AK32-$AL32-$AM32-$AN32-$AO32)*40%/(40%+15%))))) -> 1.2654545 | AI32: =IF($Z32="",0,IF($P32="",0,0.5)) -> 0.5 | AJ32: =IF($Z32="",0,IF(AND($P32="",$Q32=""),0,IF($Q32="",0,IF($P32="",($Z32-$AE32-$AF32-$AG32-$AI32-$AK32-$AL32-$AM32-$AN32-$AO32),($Z32-$AE32-$AF32-$AG32-$AI32-$AK32-$AL32-$AM32-$AN32-$AO32)*15%/(40%+15%))))) -> 0.47454545 | AK32: =IF($Z32="",0,$Z32*15%) -> 0.56 | AL32: =IF($Z32="",0,IF($R32="",0,$R32)) -> 0 | AM32: =IF(OR($Z32="",$S32=""),0,$Z32*5%) -> 0.18666667 | AN32: =IF(OR($Z32="",$T32=""),0,$Z32*10%) -> 0.37333333 | AO32: =IF($Z32="",0,IF($U32="",0,$U32)) -> 0
A33: =IF(D33="","",A32+1) -> 30 | C33: Gen AI | D33: FuelChat - Summarized version | E33: https://octopusdtlsupport.atlassian.net/browse/FF-312 | F33: RnD | O33: 3 | P33: 10 | Q33: 10 | T33: 2 | U33: 1 | V33: =SUM(M33:U33) -> 26 | W33: =V33 - (V33 * (SUBSTITUTE(SUBSTITUTE($W$2, "Optimistic (", ""), "%)", "") / 100)) -> 13 | X33: =V33 + (V33 * (SUBSTITUTE(SUBSTITUTE($X$2, "Pessimistic (", ""), "%)", "") / 100)) -> 28.6 | Y33: =(W33+(4*V33)+X33)/6 -> 24.266667 | Z33: =Y33/2 -> 12.133333 | AA33: 46146 | AB33: 46153 | AC33: 46154 | AD33: 46160 | AE33: =IF($Z33="",0,IF($M33="",0,$M33)) -> 0 | AF33: =IF(OR($Z33="",$N33=""),0,$Z33*5%) -> 0 | AG33: =IF(OR($Z33="",$O33=""),0,$Z33*10%) -> 1.2133333 | AH33: =IF($Z33="",0,IF(AND($P33="",$Q33=""),($Z33-$AE33-$AF33-$AG33-$AI33-$AK33-$AL33-$AM33-$AN33-$AO33),IF($P33="",0,IF($Q33="",($Z33-$AE33-$AF33-$AG33-$AI33-$AK33-$AL33-$AM33-$AN33-$AO33),($Z33-$AE33-$AF33-$AG33-$AI33-$AK33-$AL33-$AM33-$AN33-$AO33)*40%/(40%+15%))))) -> 4.6448485 | AI33: =IF($Z33="",0,IF($P33="",0,0.5)) -> 0.5 | AJ33: =IF($Z33="",0,IF(AND($P33="",$Q33=""),0,IF($Q33="",0,IF($P33="",($Z33-$AE33-$AF33-$AG33-$AI33-$AK33-$AL33-$AM33-$AN33-$AO33),($Z33-$AE33-$AF33-$AG33-$AI33-$AK33-$AL33-$AM33-$AN33-$AO33)*15%/(40%+15%))))) -> 1.7418182 | AK33: =IF($Z33="",0,$Z33*15%) -> 1.82 | AL33: =IF($Z33="",0,IF($R33="",0,$R33)) -> 0 | AM33: =IF(OR($Z33="",$S33=""),0,$Z33*5%) -> 0 | AN33: =IF(OR($Z33="",$T33=""),0,$Z33*10%) -> 1.2133333 | AO33: =IF($Z33="",0,IF($U33="",0,$U33)) -> 1
A34: =IF(D34="","",A33+1) -> 31 | C34: Multi-language | D34: Support for multi language | E34: https://octopusdtlsupport.atlassian.net/browse/FF-498 | F34: Competitive | O34: =5+2 -> 7 | P34: =10+5 -> 15 | Q34: 5 | S34: 3 | T34: 3 | V34: =SUM(M34:U34) -> 33 | W34: =V34 - (V34 * (SUBSTITUTE(SUBSTITUTE($W$2, "Optimistic (", ""), "%)", "") / 100)) -> 16.5 | X34: =V34 + (V34 * (SUBSTITUTE(SUBSTITUTE($X$2, "Pessimistic (", ""), "%)", "") / 100)) -> 36.3 | Y34: =(W34+(4*V34)+X34)/6 -> 30.8 | Z34: =Y34/2 -> 15.4 | AA34: 46120 | AB34: 46134 | AC34: 46146 | AD34: 46148 | AE34: =IF($Z34="",0,IF($M34="",0,$M34)) -> 0 | AF34: =IF(OR($Z34="",$N34=""),0,$Z34*5%) -> 0 | AG34: =IF(OR($Z34="",$O34=""),0,$Z34*10%) -> 1.54 | AH34: =IF($Z34="",0,IF(AND($P34="",$Q34=""),($Z34-$AE34-$AF34-$AG34-$AI34-$AK34-$AL34-$AM34-$AN34-$AO34),IF($P34="",0,IF($Q34="",($Z34-$AE34-$AF34-$AG34-$AI34-$AK34-$AL34-$AM34-$AN34-$AO34),($Z34-$AE34-$AF34-$AG34-$AI34-$AK34-$AL34-$AM34-$AN34-$AO34)*40%/(40%+15%))))) -> 6.3563636 | AI34: =IF($Z34="",0,IF($P34="",0,0.5)) -> 0.5 | AJ34: =IF($Z34="",0,IF(AND($P34="",$Q34=""),0,IF($Q34="",0,IF($P34="",($Z34-$AE34-$AF34-$AG34-$AI34-$AK34-$AL34-$AM34-$AN34-$AO34),($Z34-$AE34-$AF34-$AG34-$AI34-$AK34-$AL34-$AM34-$AN34-$AO34)*15%/(40%+15%))))) -> 2.3836364 | AK34: =IF($Z34="",0,$Z34*15%) -> 2.31 | AL34: =IF($Z34="",0,IF($R34="",0,$R34)) -> 0 | AM34: =IF(OR($Z34="",$S34=""),0,$Z34*5%) -> 0.77 | AN34: =IF(OR($Z34="",$T34=""),0,$Z34*10%) -> 1.54 | AO34: =IF($Z34="",0,IF($U34="",0,$U34)) -> 0
A35: =IF(D35="","",A34+1) -> 32 | B35: Support Tickets | C35: Support Tickets | D35: None | V35: =SUM(M35:U35) -> 0 | W35: =V35 - (V35 * (SUBSTITUTE(SUBSTITUTE($W$2, "Optimistic (", ""), "%)", "") / 100)) -> 0 | X35: =V35 + (V35 * (SUBSTITUTE(SUBSTITUTE($X$2, "Pessimistic (", ""), "%)", "") / 100)) -> 0 | Y35: =(W35+(4*V35)+X35)/6 -> 0 | Z35: =Y35/2 -> 0 | AE35: =IF($Z35="",0,IF($M35="",0,$M35)) -> 0 | AF35: =IF(OR($Z35="",$N35=""),0,$Z35*5%) -> 0 | AG35: =IF(OR($Z35="",$O35=""),0,$Z35*10%) -> 0 | AH35: =IF($Z35="",0,IF(AND($P35="",$Q35=""),($Z35-$AE35-$AF35-$AG35-$AI35-$AK35-$AL35-$AM35-$AN35-$AO35),IF($P35="",0,IF($Q35="",($Z35-$AE35-$AF35-$AG35-$AI35-$AK35-$AL35-$AM35-$AN35-$AO35),($Z35-$AE35-$AF35-$AG35-$AI35-$AK35-$AL35-$AM35-$AN35-$AO35)*40%/(40%+15%))))) -> 0 | AI35: =IF($Z35="",0,IF($P35="",0,0.5)) -> 0 | AJ35: =IF($Z35="",0,IF(AND($P35="",$Q35=""),0,IF($Q35="",0,IF($P35="",($Z35-$AE35-$AF35-$AG35-$AI35-$AK35-$AL35-$AM35-$AN35-$AO35),($Z35-$AE35-$AF35-$AG35-$AI35-$AK35-$AL35-$AM35-$AN35-$AO35)*15%/(40%+15%))))) -> 0 | AK35: =IF($Z35="",0,$Z35*15%) -> 0 | AL35: =IF($Z35="",0,IF($R35="",0,$R35)) -> 0 | AM35: =IF(OR($Z35="",$S35=""),0,$Z35*5%) -> 0 | AN35: =IF(OR($Z35="",$T35=""),0,$Z35*10%) -> 0 | AO35: =IF($Z35="",0,IF($U35="",0,$U35)) -> 0
A36: =IF(D36="","",A35+1) -> 33 | B36: TO CATEGORIZE YET | C36: TO CATEGORIZE YET | D36: System health monitoring(Site Diagnostic) - (12h) | E36: https://octopusdtlsupport.atlassian.net/browse/FF-274 | F36: PGL | O36: 5 | P36: 35 | Q36: 5 | S36: 5 | U36: 2 | V36: =SUM(M36:U36) -> 52 | W36: =V36 - (V36 * (SUBSTITUTE(SUBSTITUTE($W$2, "Optimistic (", ""), "%)", "") / 100)) -> 26 | X36: =V36 + (V36 * (SUBSTITUTE(SUBSTITUTE($X$2, "Pessimistic (", ""), "%)", "") / 100)) -> 57.2 | Y36: =(W36+(4*V36)+X36)/6 -> 48.533333 | Z36: =Y36/2 -> 24.266667 | AA36: 46120 | AB36: 46129 | AC36: 46146 | AD36: 46148 | AE36: =IF($Z36="",0,IF($M36="",0,$M36)) -> 0 | AF36: =IF(OR($Z36="",$N36=""),0,$Z36*5%) -> 0 | AG36: =IF(OR($Z36="",$O36=""),0,$Z36*10%) -> 2.4266667 | AH36: =IF($Z36="",0,IF(AND($P36="",$Q36=""),($Z36-$AE36-$AF36-$AG36-$AI36-$AK36-$AL36-$AM36-$AN36-$AO36),IF($P36="",0,IF($Q36="",($Z36-$AE36-$AF36-$AG36-$AI36-$AK36-$AL36-$AM36-$AN36-$AO36),($Z36-$AE36-$AF36-$AG36-$AI36-$AK36-$AL36-$AM36-$AN36-$AO36)*40%/(40%+15%))))) -> 10.535758 | AI36: =IF($Z36="",0,IF($P36="",0,0.5)) -> 0.5 | AJ36: =IF($Z36="",0,IF(AND($P36="",$Q36=""),0,IF($Q36="",0,IF($P36="",($Z36-$AE36-$AF36-$AG36-$AI36-$AK36-$AL36-$AM36-$AN36-$AO36),($Z36-$AE36-$AF36-$AG36-$AI36-$AK36-$AL36-$AM36-$AN36-$AO36)*15%/(40%+15%))))) -> 3.9509091 | AK36: =IF($Z36="",0,$Z36*15%) -> 3.64 | AL36: =IF($Z36="",0,IF($R36="",0,$R36)) -> 0 | AM36: =IF(OR($Z36="",$S36=""),0,$Z36*5%) -> 1.2133333 | AN36: =IF(OR($Z36="",$T36=""),0,$Z36*10%) -> 0 | AO36: =IF($Z36="",0,IF($U36="",0,$U36)) -> 2
A37: =IF(D37="","",A36+1) -> 34 | B37: TO CATEGORIZE YET | C37: TO CATEGORIZE YET | D37: Calculate Tank delivery (Alsons device) | E37: https://octopusdtlsupport.atlassian.net/browse/FF-542 | F37: PGL | O37: 3 | P37: 3 | Q37: 2 | S37: 5 | U37: 2 | V37: =SUM(M37:U37) -> 15 | W37: =V37 - (V37 * (SUBSTITUTE(SUBSTITUTE($W$2, "Optimistic (", ""), "%)", "") / 100)) -> 7.5 | X37: =V37 + (V37 * (SUBSTITUTE(SUBSTITUTE($X$2, "Pessimistic (", ""), "%)", "") / 100)) -> 16.5 | Y37: =(W37+(4*V37)+X37)/6 -> 14 | Z37: =Y37/2 -> 7 | AE37: =IF($Z37="",0,IF($M37="",0,$M37)) -> 0 | AF37: =IF(OR($Z37="",$N37=""),0,$Z37*5%) -> 0 | AG37: =IF(OR($Z37="",$O37=""),0,$Z37*10%) -> 0.7 | AH37: =IF($Z37="",0,IF(AND($P37="",$Q37=""),($Z37-$AE37-$AF37-$AG37-$AI37-$AK37-$AL37-$AM37-$AN37-$AO37),IF($P37="",0,IF($Q37="",($Z37-$AE37-$AF37-$AG37-$AI37-$AK37-$AL37-$AM37-$AN37-$AO37),($Z37-$AE37-$AF37-$AG37-$AI37-$AK37-$AL37-$AM37-$AN37-$AO37)*40%/(40%+15%))))) -> 1.7454545 | AI37: =IF($Z37="",0,IF($P37="",0,0.5)) -> 0.5 | AJ37: =IF($Z37="",0,IF(AND($P37="",$Q37=""),0,IF($Q37="",0,IF($P37="",($Z37-$AE37-$AF37-$AG37-$AI37-$AK37-$AL37-$AM37-$AN37-$AO37),($Z37-$AE37-$AF37-$AG37-$AI37-$AK37-$AL37-$AM37-$AN37-$AO37)*15%/(40%+15%))))) -> 0.65454545 | AK37: =IF($Z37="",0,$Z37*15%) -> 1.05 | AL37: =IF($Z37="",0,IF($R37="",0,$R37)) -> 0 | AM37: =IF(OR($Z37="",$S37=""),0,$Z37*5%) -> 0.35 | AN37: =IF(OR($Z37="",$T37=""),0,$Z37*10%) -> 0 | AO37: =IF($Z37="",0,IF($U37="",0,$U37)) -> 2
A38: =IF(D38="","",A37+1) -> 35 | B38: TO CATEGORIZE YET | C38: TO CATEGORIZE YET | D38: Unified Platform & Multi-Site Visibility (Consolidated view for all sites) - The client wants a unified platform that provides information from all plant sites in one place. - Key data points requested in the unified view include storage tank volume and timestamped deliveries. - The solution must support network-scale visibility for hundreds of sites, not just a small pilot set. - Different user levels, including management, leadership, supervisors, and operations teams, need different views of the same data. - Visibility of sites, targets, and data should follow the assigned user hierarchy. | F38: PGL | O38: 4 | P38: 10 | Q38: 5 | S38: 5 | U38: 2 | V38: =SUM(M38:U38) -> 26 | W38: =V38 - (V38 * (SUBSTITUTE(SUBSTITUTE($W$2, "Optimistic (", ""), "%)", "") / 100)) -> 13 | X38: =V38 + (V38 * (SUBSTITUTE(SUBSTITUTE($X$2, "Pessimistic (", ""), "%)", "") / 100)) -> 28.6 | Y38: =(W38+(4*V38)+X38)/6 -> 24.266667 | Z38: =Y38/2 -> 12.133333 | AE38: =IF($Z38="",0,IF($M38="",0,$M38)) -> 0 | AF38: =IF(OR($Z38="",$N38=""),0,$Z38*5%) -> 0 | AG38: =IF(OR($Z38="",$O38=""),0,$Z38*10%) -> 1.2133333 | AH38: =IF($Z38="",0,IF(AND($P38="",$Q38=""),($Z38-$AE38-$AF38-$AG38-$AI38-$AK38-$AL38-$AM38-$AN38-$AO38),IF($P38="",0,IF($Q38="",($Z38-$AE38-$AF38-$AG38-$AI38-$AK38-$AL38-$AM38-$AN38-$AO38),($Z38-$AE38-$AF38-$AG38-$AI38-$AK38-$AL38-$AM38-$AN38-$AO38)*40%/(40%+15%))))) -> 4.3587879 | AI38: =IF($Z38="",0,IF($P38="",0,0.5)) -> 0.5 | AJ38: =IF($Z38="",0,IF(AND($P38="",$Q38=""),0,IF($Q38="",0,IF($P38="",($Z38-$AE38-$AF38-$AG38-$AI38-$AK38-$AL38-$AM38-$AN38-$AO38),($Z38-$AE38-$AF38-$AG38-$AI38-$AK38-$AL38-$AM38-$AN38-$AO38)*15%/(40%+15%))))) -> 1.6345455 | AK38: =IF($Z38="",0,$Z38*15%) -> 1.82 | AL38: =IF($Z38="",0,IF($R38="",0,$R38)) -> 0 | AM38: =IF(OR($Z38="",$S38=""),0,$Z38*5%) -> 0.60666667 | AN38: =IF(OR($Z38="",$T38=""),0,$Z38*10%) -> 0 | AO38: =IF($Z38="",0,IF($U38="",0,$U38)) -> 2
A39: =IF(D39="","",A38+1) -> 36 | B39: TO CATEGORIZE YET | C39: TO CATEGORIZE YET | D39: Deliveries & Delivery Identification - Deliveries are already available with timestamps in Fintech Fuel. - The client wants to distinguish PGL deliveries from non-PGL deliveries, with a clear classification such as PGL and Not PGL. - At COCO sites, current deliveries are considered PGL deliveries. - At DODO sites, the client needs a way to identify who decanted product into storage because multiple providers may use the same storage. - The current level of control at DODO sites is weaker than at COCO sites, and the client wants better controls in Fintech Fuel. - The Deliveries page should use the industry term Delivery Note instead of Bill of Lading. - For imported products, a delivery note or lading reference should be captured on the UI. - A lading reference is currently seen as a reference point only and not as a full control mechanism. - The client wants this requirement captured as a KPI or future control area even if it is initially implemented as a wish-list item. - The system should highlight cases where actual decanted quantity exceeds expected quantity. - Manual delivery references alone are not sufficient to establish end-to-end control. | F39: PGL | O39: 4 | P39: 4 | Q39: 3 | S39: 5 | U39: 2 | V39: =SUM(M39:U39) -> 18 | W39: =V39 - (V39 * (SUBSTITUTE(SUBSTITUTE($W$2, "Optimistic (", ""), "%)", "") / 100)) -> 9 | X39: =V39 + (V39 * (SUBSTITUTE(SUBSTITUTE($X$2, "Pessimistic (", ""), "%)", "") / 100)) -> 19.8 | Y39: =(W39+(4*V39)+X39)/6 -> 16.8 | Z39: =Y39/2 -> 8.4 | AE39: =IF($Z39="",0,IF($M39="",0,$M39)) -> 0 | AF39: =IF(OR($Z39="",$N39=""),0,$Z39*5%) -> 0 | AG39: =IF(OR($Z39="",$O39=""),0,$Z39*10%) -> 0.84 | AH39: =IF($Z39="",0,IF(AND($P39="",$Q39=""),($Z39-$AE39-$AF39-$AG39-$AI39-$AK39-$AL39-$AM39-$AN39-$AO39),IF($P39="",0,IF($Q39="",($Z39-$AE39-$AF39-$AG39-$AI39-$AK39-$AL39-$AM39-$AN39-$AO39),($Z39-$AE39-$AF39-$AG39-$AI39-$AK39-$AL39-$AM39-$AN39-$AO39)*40%/(40%+15%))))) -> 2.4581818 | AI39: =IF($Z39="",0,IF($P39="",0,0.5)) -> 0.5 | AJ39: =IF($Z39="",0,IF(AND($P39="",$Q39=""),0,IF($Q39="",0,IF($P39="",($Z39-$AE39-$AF39-$AG39-$AI39-$AK39-$AL39-$AM39-$AN39-$AO39),($Z39-$AE39-$AF39-$AG39-$AI39-$AK39-$AL39-$AM39-$AN39-$AO39)*15%/(40%+15%))))) -> 0.92181818 | AK39: =IF($Z39="",0,$Z39*15%) -> 1.26 | AL39: =IF($Z39="",0,IF($R39="",0,$R39)) -> 0 | AM39: =IF(OR($Z39="",$S39=""),0,$Z39*5%) -> 0.42 | AN39: =IF(OR($Z39="",$T39=""),0,$Z39*10%) -> 0 | AO39: =IF($Z39="",0,IF($U39="",0,$U39)) -> 2
A40: =IF(D40="","",A39+1) -> 37 | B40: TO CATEGORIZE YET | C40: TO CATEGORIZE YET | D40: Dashboard Enhancements - Visual representations - Sales vs target trend must be dynamic not just last 7 days - Stock level must be dynamic not just last 7 days - Remove minute-level filters - Show time of fetched data on stock-level - positive/negative variance with color coding | F40: PGL | O40: 0 | P40: 2 | Q40: 2 | S40: 5 | U40: 2 | V40: =SUM(M40:U40) -> 11 | W40: =V40 - (V40 * (SUBSTITUTE(SUBSTITUTE($W$2, "Optimistic (", ""), "%)", "") / 100)) -> 5.5 | X40: =V40 + (V40 * (SUBSTITUTE(SUBSTITUTE($X$2, "Pessimistic (", ""), "%)", "") / 100)) -> 12.1 | Y40: =(W40+(4*V40)+X40)/6 -> 10.266667 | Z40: =Y40/2 -> 5.1333333 | AE40: =IF($Z40="",0,IF($M40="",0,$M40)) -> 0 | AF40: =IF(OR($Z40="",$N40=""),0,$Z40*5%) -> 0 | AG40: =IF(OR($Z40="",$O40=""),0,$Z40*10%) -> 0.51333333 | AH40: =IF($Z40="",0,IF(AND($P40="",$Q40=""),($Z40-$AE40-$AF40-$AG40-$AI40-$AK40-$AL40-$AM40-$AN40-$AO40),IF($P40="",0,IF($Q40="",($Z40-$AE40-$AF40-$AG40-$AI40-$AK40-$AL40-$AM40-$AN40-$AO40),($Z40-$AE40-$AF40-$AG40-$AI40-$AK40-$AL40-$AM40-$AN40-$AO40)*40%/(40%+15%))))) -> 0.79515152 | AI40: =IF($Z40="",0,IF($P40="",0,0.5)) -> 0.5 | AJ40: =IF($Z40="",0,IF(AND($P40="",$Q40=""),0,IF($Q40="",0,IF($P40="",($Z40-$AE40-$AF40-$AG40-$AI40-$AK40-$AL40-$AM40-$AN40-$AO40),($Z40-$AE40-$AF40-$AG40-$AI40-$AK40-$AL40-$AM40-$AN40-$AO40)*15%/(40%+15%))))) -> 0.29818182 | AK40: =IF($Z40="",0,$Z40*15%) -> 0.77 | AL40: =IF($Z40="",0,IF($R40="",0,$R40)) -> 0 | AM40: =IF(OR($Z40="",$S40=""),0,$Z40*5%) -> 0.25666667 | AN40: =IF(OR($Z40="",$T40=""),0,$Z40*10%) -> 0 | AO40: =IF($Z40="",0,IF($U40="",0,$U40)) -> 2
A41: =IF(D41="","",A40+1) -> 38 | B41: TO CATEGORIZE YET | C41: TO CATEGORIZE YET | D41: Historical Comparison & Trend Analysis - Comparison of different metrices like sales vs deliveries etc. | F41: PGL | O41: 2 | P41: 6 | Q41: 3 | S41: 5 | U41: 2 | V41: =SUM(M41:U41) -> 18 | W41: =V41 - (V41 * (SUBSTITUTE(SUBSTITUTE($W$2, "Optimistic (", ""), "%)", "") / 100)) -> 9 | X41: =V41 + (V41 * (SUBSTITUTE(SUBSTITUTE($X$2, "Pessimistic (", ""), "%)", "") / 100)) -> 19.8 | Y41: =(W41+(4*V41)+X41)/6 -> 16.8 | Z41: =Y41/2 -> 8.4 | AE41: =IF($Z41="",0,IF($M41="",0,$M41)) -> 0 | AF41: =IF(OR($Z41="",$N41=""),0,$Z41*5%) -> 0 | AG41: =IF(OR($Z41="",$O41=""),0,$Z41*10%) -> 0.84 | AH41: =IF($Z41="",0,IF(AND($P41="",$Q41=""),($Z41-$AE41-$AF41-$AG41-$AI41-$AK41-$AL41-$AM41-$AN41-$AO41),IF($P41="",0,IF($Q41="",($Z41-$AE41-$AF41-$AG41-$AI41-$AK41-$AL41-$AM41-$AN41-$AO41),($Z41-$AE41-$AF41-$AG41-$AI41-$AK41-$AL41-$AM41-$AN41-$AO41)*40%/(40%+15%))))) -> 2.4581818 | AI41: =IF($Z41="",0,IF($P41="",0,0.5)) -> 0.5 | AJ41: =IF($Z41="",0,IF(AND($P41="",$Q41=""),0,IF($Q41="",0,IF($P41="",($Z41-$AE41-$AF41-$AG41-$AI41-$AK41-$AL41-$AM41-$AN41-$AO41),($Z41-$AE41-$AF41-$AG41-$AI41-$AK41-$AL41-$AM41-$AN41-$AO41)*15%/(40%+15%))))) -> 0.92181818 | AK41: =IF($Z41="",0,$Z41*15%) -> 1.26 | AL41: =IF($Z41="",0,IF($R41="",0,$R41)) -> 0 | AM41: =IF(OR($Z41="",$S41=""),0,$Z41*5%) -> 0.42 | AN41: =IF(OR($Z41="",$T41=""),0,$Z41*10%) -> 0 | AO41: =IF($Z41="",0,IF($U41="",0,$U41)) -> 2
A42: =IF(D42="","",A41+1) -> 39 | B42: TO CATEGORIZE YET | C42: TO CATEGORIZE YET | D42: Reconciliation & Variance Analysis - Reconciliation is a key area for the client, especially to monitor external uplifting. - The reconciliation report should help users see how frequently variation occurs over time. - The client wants anomaly highlighting for variances above selected thresholds. - The current tabulated Excel-like representation is difficult to consume and needs a better UI/UX treatment. - The user wants a product-tile style interaction where clicking a product reveals its reconciliation details. - There is currently no way to define a threshold value in the system; the client asked for configurable selected thresholds. - The system should highlight anomalies at the time of reconciliation. - The reconciliation workflow should support investigation into why a difference exists. - Initial anomaly reasons should at least include data disconnectivity, whether due to internet issues or equipment malfunction. - The reconciliation report must show consistent data and clearly reflect when a site is not transmitting data. - If data is missing, the report should show an exclusion note so the variance can be interpreted correctly. - The client suggested a rule such as flagging any site where no data transmission happens for 60 or more minutes. - Capturing the anomaly event is considered the first priority; the detailed report presentation can be refined with users afterward. - The report should include a summary table on top for the selected period with one row per product, instead of only date-by-date product entries. - The user emphasized that reconciliation UI/UX quality is a possible road blocker. | F42: PGL | O42: 5 | P42: 17 | Q42: 5 | S42: 5 | U42: 2 | V42: =SUM(M42:U42) -> 34 | W42: =V42 - (V42 * (SUBSTITUTE(SUBSTITUTE($W$2, "Optimistic (", ""), "%)", "") / 100)) -> 17 | X42: =V42 + (V42 * (SUBSTITUTE(SUBSTITUTE($X$2, "Pessimistic (", ""), "%)", "") / 100)) -> 37.4 | Y42: =(W42+(4*V42)+X42)/6 -> 31.733333 | Z42: =Y42/2 -> 15.866667 | AE42: =IF($Z42="",0,IF($M42="",0,$M42)) -> 0 | AF42: =IF(OR($Z42="",$N42=""),0,$Z42*5%) -> 0 | AG42: =IF(OR($Z42="",$O42=""),0,$Z42*10%) -> 1.5866667 | AH42: =IF($Z42="",0,IF(AND($P42="",$Q42=""),($Z42-$AE42-$AF42-$AG42-$AI42-$AK42-$AL42-$AM42-$AN42-$AO42),IF($P42="",0,IF($Q42="",($Z42-$AE42-$AF42-$AG42-$AI42-$AK42-$AL42-$AM42-$AN42-$AO42),($Z42-$AE42-$AF42-$AG42-$AI42-$AK42-$AL42-$AM42-$AN42-$AO42)*40%/(40%+15%))))) -> 6.2593939 | AI42: =IF($Z42="",0,IF($P42="",0,0.5)) -> 0.5 | AJ42: =IF($Z42="",0,IF(AND($P42="",$Q42=""),0,IF($Q42="",0,IF($P42="",($Z42-$AE42-$AF42-$AG42-$AI42-$AK42-$AL42-$AM42-$AN42-$AO42),($Z42-$AE42-$AF42-$AG42-$AI42-$AK42-$AL42-$AM42-$AN42-$AO42)*15%/(40%+15%))))) -> 2.3472727 | AK42: =IF($Z42="",0,$Z42*15%) -> 2.38 | AL42: =IF($Z42="",0,IF($R42="",0,$R42)) -> 0 | AM42: =IF(OR($Z42="",$S42=""),0,$Z42*5%) -> 0.79333333 | AN42: =IF(OR($Z42="",$T42=""),0,$Z42*10%) -> 0 | AO42: =IF($Z42="",0,IF($U42="",0,$U42)) -> 2
A43: =IF(D43="","",A42+1) -> 40 | B43: TO CATEGORIZE YET | C43: TO CATEGORIZE YET | D43: Data Accuracy, Connectivity & Equipment Failure - Data accuracy is a major concern for the client. - Two primary failure scenarios were identified: -- Internet disconnectivity between the site and the cloud. -- Site hardware or controller malfunction. - In internet disconnectivity scenarios, the controller device must accumulate data and transmit it once connectivity is restored. - No data loss is acceptable when internet connectivity is interrupted. - If the controller or site equipment is not working, the system must raise an alert. - The client wants the system to inform users whether a site cannot reconcile because of internet disconnectivity or equipment malfunction. - If equipment fails and data is not captured, the system must provide manual entry for lost site data. - Manual entry is considered necessary to maintain 100% data accuracy and complete reconciliation. - The client requested an admin-level tool for manual data entry when ATG or related equipment is down. - The discussion referenced a practical case where if ATG is down for two hours, the system should allow offline or manual input. - Offline input data is therefore a required feature. | F43: PGL | O43: 3 | P43: 23 | Q43: 5 | S43: 5 | U43: 2 | V43: =SUM(M43:U43) -> 38 | W43: =V43 - (V43 * (SUBSTITUTE(SUBSTITUTE($W$2, "Optimistic (", ""), "%)", "") / 100)) -> 19 | X43: =V43 + (V43 * (SUBSTITUTE(SUBSTITUTE($X$2, "Pessimistic (", ""), "%)", "") / 100)) -> 41.8 | Y43: =(W43+(4*V43)+X43)/6 -> 35.466667 | Z43: =Y43/2 -> 17.733333 | AE43: =IF($Z43="",0,IF($M43="",0,$M43)) -> 0 | AF43: =IF(OR($Z43="",$N43=""),0,$Z43*5%) -> 0 | AG43: =IF(OR($Z43="",$O43=""),0,$Z43*10%) -> 1.7733333 | AH43: =IF($Z43="",0,IF(AND($P43="",$Q43=""),($Z43-$AE43-$AF43-$AG43-$AI43-$AK43-$AL43-$AM43-$AN43-$AO43),IF($P43="",0,IF($Q43="",($Z43-$AE43-$AF43-$AG43-$AI43-$AK43-$AL43-$AM43-$AN43-$AO43),($Z43-$AE43-$AF43-$AG43-$AI43-$AK43-$AL43-$AM43-$AN43-$AO43)*40%/(40%+15%))))) -> 7.209697 | AI43: =IF($Z43="",0,IF($P43="",0,0.5)) -> 0.5 | AJ43: =IF($Z43="",0,IF(AND($P43="",$Q43=""),0,IF($Q43="",0,IF($P43="",($Z43-$AE43-$AF43-$AG43-$AI43-$AK43-$AL43-$AM43-$AN43-$AO43),($Z43-$AE43-$AF43-$AG43-$AI43-$AK43-$AL43-$AM43-$AN43-$AO43)*15%/(40%+15%))))) -> 2.7036364 | AK43: =IF($Z43="",0,$Z43*15%) -> 2.66 | AL43: =IF($Z43="",0,IF($R43="",0,$R43)) -> 0 | AM43: =IF(OR($Z43="",$S43=""),0,$Z43*5%) -> 0.88666667 | AN43: =IF(OR($Z43="",$T43=""),0,$Z43*10%) -> 0 | AO43: =IF($Z43="",0,IF($U43="",0,$U43)) -> 2
A44: =IF(D44="","",A43+1) -> 41 | B44: TO CATEGORIZE YET | C44: TO CATEGORIZE YET | D44: Alerts, Diagnostics & Notifications - Alerts should not remain isolated in one report; they should connect with diagnostics and related operational reports. - Email notifications should be available for alerts. - A diagnostics or connectivity view should show which sites are disconnected. - Connectivity and equipment-down conditions should raise alerts. - If a device fails to ping within a configured time period, the system should raise an alert if the controller supports that information. - The client suggested using controller ping behavior as a simple basis for equipment-down alerting. - Thresholds for alarms should be configurable. - A 0.5% threshold was specifically mentioned in the discussion. | F44: PGL | O44: 1 | P44: 5 | Q44: 3 | S44: 5 | U44: 2 | V44: =SUM(M44:U44) -> 16 | W44: =V44 - (V44 * (SUBSTITUTE(SUBSTITUTE($W$2, "Optimistic (", ""), "%)", "") / 100)) -> 8 | X44: =V44 + (V44 * (SUBSTITUTE(SUBSTITUTE($X$2, "Pessimistic (", ""), "%)", "") / 100)) -> 17.6 | Y44: =(W44+(4*V44)+X44)/6 -> 14.933333 | Z44: =Y44/2 -> 7.4666667 | AE44: =IF($Z44="",0,IF($M44="",0,$M44)) -> 0 | AF44: =IF(OR($Z44="",$N44=""),0,$Z44*5%) -> 0 | AG44: =IF(OR($Z44="",$O44=""),0,$Z44*10%) -> 0.74666667 | AH44: =IF($Z44="",0,IF(AND($P44="",$Q44=""),($Z44-$AE44-$AF44-$AG44-$AI44-$AK44-$AL44-$AM44-$AN44-$AO44),IF($P44="",0,IF($Q44="",($Z44-$AE44-$AF44-$AG44-$AI44-$AK44-$AL44-$AM44-$AN44-$AO44),($Z44-$AE44-$AF44-$AG44-$AI44-$AK44-$AL44-$AM44-$AN44-$AO44)*40%/(40%+15%))))) -> 1.9830303 | AI44: =IF($Z44="",0,IF($P44="",0,0.5)) -> 0.5 | AJ44: =IF($Z44="",0,IF(AND($P44="",$Q44=""),0,IF($Q44="",0,IF($P44="",($Z44-$AE44-$AF44-$AG44-$AI44-$AK44-$AL44-$AM44-$AN44-$AO44),($Z44-$AE44-$AF44-$AG44-$AI44-$AK44-$AL44-$AM44-$AN44-$AO44)*15%/(40%+15%))))) -> 0.74363636 | AK44: =IF($Z44="",0,$Z44*15%) -> 1.12 | AL44: =IF($Z44="",0,IF($R44="",0,$R44)) -> 0 | AM44: =IF(OR($Z44="",$S44=""),0,$Z44*5%) -> 0.37333333 | AN44: =IF(OR($Z44="",$T44=""),0,$Z44*10%) -> 0 | AO44: =IF($Z44="",0,IF($U44="",0,$U44)) -> 2
A45: =IF(D45="","",A44+1) -> 42 | B45: TO CATEGORIZE YET | C45: TO CATEGORIZE YET | D45: Reporting, Terminology & Units - Nozzle-level sales are not clear to the client, partly because of the nomenclature used in the nozzle report. - The transaction report does not clearly mention the unit of measure. - The client wants units such as liters or currency to be visible consistently across the application. - Report terminology and naming should be reviewed so reports are easier for the business to understand. - The client asked the team to review nomenclature used in summarized and detailed reports. | F45: PGL | O45: 0 | P45: 2 | Q45: 1 | S45: 5 | U45: 2 | V45: =SUM(M45:U45) -> 10 | W45: =V45 - (V45 * (SUBSTITUTE(SUBSTITUTE($W$2, "Optimistic (", ""), "%)", "") / 100)) -> 5 | X45: =V45 + (V45 * (SUBSTITUTE(SUBSTITUTE($X$2, "Pessimistic (", ""), "%)", "") / 100)) -> 11 | Y45: =(W45+(4*V45)+X45)/6 -> 9.3333333 | Z45: =Y45/2 -> 4.6666667 | AE45: =IF($Z45="",0,IF($M45="",0,$M45)) -> 0 | AF45: =IF(OR($Z45="",$N45=""),0,$Z45*5%) -> 0 | AG45: =IF(OR($Z45="",$O45=""),0,$Z45*10%) -> 0.46666667 | AH45: =IF($Z45="",0,IF(AND($P45="",$Q45=""),($Z45-$AE45-$AF45-$AG45-$AI45-$AK45-$AL45-$AM45-$AN45-$AO45),IF($P45="",0,IF($Q45="",($Z45-$AE45-$AF45-$AG45-$AI45-$AK45-$AL45-$AM45-$AN45-$AO45),($Z45-$AE45-$AF45-$AG45-$AI45-$AK45-$AL45-$AM45-$AN45-$AO45)*40%/(40%+15%))))) -> 0.55757576 | AI45: =IF($Z45="",0,IF($P45="",0,0.5)) -> 0.5 | AJ45: =IF($Z45="",0,IF(AND($P45="",$Q45=""),0,IF($Q45="",0,IF($P45="",($Z45-$AE45-$AF45-$AG45-$AI45-$AK45-$AL45-$AM45-$AN45-$AO45),($Z45-$AE45-$AF45-$AG45-$AI45-$AK45-$AL45-$AM45-$AN45-$AO45)*15%/(40%+15%))))) -> 0.20909091 | AK45: =IF($Z45="",0,$Z45*15%) -> 0.7 | AL45: =IF($Z45="",0,IF($R45="",0,$R45)) -> 0 | AM45: =IF(OR($Z45="",$S45=""),0,$Z45*5%) -> 0.23333333 | AN45: =IF(OR($Z45="",$T45=""),0,$Z45*10%) -> 0 | AO45: =IF($Z45="",0,IF($U45="",0,$U45)) -> 2
A46: =IF(D46="","",A45+1) -> 43 | B46: TO CATEGORIZE YET | C46: TO CATEGORIZE YET | D46: Loss/Gain Analytics & Tank Illustration - The client asked for tank-wise visibility in addition to product-wise views. - The discussion clarified that this requirement is already fulfilled through the Stock Levels report. - The gap identified was client awareness and product discoverability, not missing functionality. - Tank illustration is also required. | F46: PGL | O46: 0 | P46: 1 | Q46: 2 | S46: 5 | U46: 2 | V46: =SUM(M46:U46) -> 10 | W46: =V46 - (V46 * (SUBSTITUTE(SUBSTITUTE($W$2, "Optimistic (", ""), "%)", "") / 100)) -> 5 | X46: =V46 + (V46 * (SUBSTITUTE(SUBSTITUTE($X$2, "Pessimistic (", ""), "%)", "") / 100)) -> 11 | Y46: =(W46+(4*V46)+X46)/6 -> 9.3333333 | Z46: =Y46/2 -> 4.6666667 | AE46: =IF($Z46="",0,IF($M46="",0,$M46)) -> 0 | AF46: =IF(OR($Z46="",$N46=""),0,$Z46*5%) -> 0 | AG46: =IF(OR($Z46="",$O46=""),0,$Z46*10%) -> 0.46666667 | AH46: =IF($Z46="",0,IF(AND($P46="",$Q46=""),($Z46-$AE46-$AF46-$AG46-$AI46-$AK46-$AL46-$AM46-$AN46-$AO46),IF($P46="",0,IF($Q46="",($Z46-$AE46-$AF46-$AG46-$AI46-$AK46-$AL46-$AM46-$AN46-$AO46),($Z46-$AE46-$AF46-$AG46-$AI46-$AK46-$AL46-$AM46-$AN46-$AO46)*40%/(40%+15%))))) -> 0.55757576 | AI46: =IF($Z46="",0,IF($P46="",0,0.5)) -> 0.5 | AJ46: =IF($Z46="",0,IF(AND($P46="",$Q46=""),0,IF($Q46="",0,IF($P46="",($Z46-$AE46-$AF46-$AG46-$AI46-$AK46-$AL46-$AM46-$AN46-$AO46),($Z46-$AE46-$AF46-$AG46-$AI46-$AK46-$AL46-$AM46-$AN46-$AO46)*15%/(40%+15%))))) -> 0.20909091 | AK46: =IF($Z46="",0,$Z46*15%) -> 0.7 | AL46: =IF($Z46="",0,IF($R46="",0,$R46)) -> 0 | AM46: =IF(OR($Z46="",$S46=""),0,$Z46*5%) -> 0.23333333 | AN46: =IF(OR($Z46="",$T46=""),0,$Z46*10%) -> 0 | AO46: =IF($Z46="",0,IF($U46="",0,$U46)) -> 2
A47: =IF(D47="","",A46+1) -> 44 | B47: TO CATEGORIZE YET | C47: TO CATEGORIZE YET | D47: Sales Targets & Organizational Hierarchy - Sales targets are maintained at multiple levels, including yearly, quarterly, monthly, and weekly. - The client does not use daily targets as a primary planning level. - Weekly contribution to yearly targets is important. - Targets are established globally for fuel and are often maintained in Excel at area and station level. - The client wants an Excel upload feature so sales targets can be populated in bulk. - A sample Excel file is to be shared by the client after checking with the sales team. - The client also wants targets and sites linked to territory managers and other organizational roles. - The current page can partially support target assignment but does not fully reflect the organizational hierarchy such as region-wise or territory-manager-wise structures. - Further alignment with the sales team is needed to define how targets should be modeled in Fintech Fuel and to set expectations. | F47: PGL | O47: 3 | P47: 15 | Q47: 5 | S47: 5 | U47: 2 | V47: =SUM(M47:U47) -> 30 | W47: =V47 - (V47 * (SUBSTITUTE(SUBSTITUTE($W$2, "Optimistic (", ""), "%)", "") / 100)) -> 15 | X47: =V47 + (V47 * (SUBSTITUTE(SUBSTITUTE($X$2, "Pessimistic (", ""), "%)", "") / 100)) -> 33 | Y47: =(W47+(4*V47)+X47)/6 -> 28 | Z47: =Y47/2 -> 14 | AE47: =IF($Z47="",0,IF($M47="",0,$M47)) -> 0 | AF47: =IF(OR($Z47="",$N47=""),0,$Z47*5%) -> 0 | AG47: =IF(OR($Z47="",$O47=""),0,$Z47*10%) -> 1.4 | AH47: =IF($Z47="",0,IF(AND($P47="",$Q47=""),($Z47-$AE47-$AF47-$AG47-$AI47-$AK47-$AL47-$AM47-$AN47-$AO47),IF($P47="",0,IF($Q47="",($Z47-$AE47-$AF47-$AG47-$AI47-$AK47-$AL47-$AM47-$AN47-$AO47),($Z47-$AE47-$AF47-$AG47-$AI47-$AK47-$AL47-$AM47-$AN47-$AO47)*40%/(40%+15%))))) -> 5.3090909 | AI47: =IF($Z47="",0,IF($P47="",0,0.5)) -> 0.5 | AJ47: =IF($Z47="",0,IF(AND($P47="",$Q47=""),0,IF($Q47="",0,IF($P47="",($Z47-$AE47-$AF47-$AG47-$AI47-$AK47-$AL47-$AM47-$AN47-$AO47),($Z47-$AE47-$AF47-$AG47-$AI47-$AK47-$AL47-$AM47-$AN47-$AO47)*15%/(40%+15%))))) -> 1.9909091 | AK47: =IF($Z47="",0,$Z47*15%) -> 2.1 | AL47: =IF($Z47="",0,IF($R47="",0,$R47)) -> 0 | AM47: =IF(OR($Z47="",$S47=""),0,$Z47*5%) -> 0.7 | AN47: =IF(OR($Z47="",$T47=""),0,$Z47*10%) -> 0 | AO47: =IF($Z47="",0,IF($U47="",0,$U47)) -> 2
A48: =IF(D48="","",A47+1) -> 45 | B48: TO CATEGORIZE YET | C48: TO CATEGORIZE YET | D48: Date Range & Time Handling - The client objected to 8 AM to 8 PM reconciliation windows from a UX perspective. - Date filtering should behave as full-day selection: - Single day selection should mean 00:00 to 23:59. - Multi-day selection should mean from the start of the first day to the end of the last day. - Site-level time window configuration exists, but implementation would require client approval. - A possible tolerance buffer of 5% to 10% was discussed to account for timing-related variances such as transactions crossing midnight. - The team agreed that the transaction end time is the correct timestamp to use for calculations. | F48: PGL | O48: 0 | P48: 3 | Q48: 3 | S48: 5 | U48: 2 | V48: =SUM(M48:U48) -> 13 | W48: =V48 - (V48 * (SUBSTITUTE(SUBSTITUTE($W$2, "Optimistic (", ""), "%)", "") / 100)) -> 6.5 | X48: =V48 + (V48 * (SUBSTITUTE(SUBSTITUTE($X$2, "Pessimistic (", ""), "%)", "") / 100)) -> 14.3 | Y48: =(W48+(4*V48)+X48)/6 -> 12.133333 | Z48: =Y48/2 -> 6.0666667 | AE48: =IF($Z48="",0,IF($M48="",0,$M48)) -> 0 | AF48: =IF(OR($Z48="",$N48=""),0,$Z48*5%) -> 0 | AG48: =IF(OR($Z48="",$O48=""),0,$Z48*10%) -> 0.60666667 | AH48: =IF($Z48="",0,IF(AND($P48="",$Q48=""),($Z48-$AE48-$AF48-$AG48-$AI48-$AK48-$AL48-$AM48-$AN48-$AO48),IF($P48="",0,IF($Q48="",($Z48-$AE48-$AF48-$AG48-$AI48-$AK48-$AL48-$AM48-$AN48-$AO48),($Z48-$AE48-$AF48-$AG48-$AI48-$AK48-$AL48-$AM48-$AN48-$AO48)*40%/(40%+15%))))) -> 1.270303 | AI48: =IF($Z48="",0,IF($P48="",0,0.5)) -> 0.5 | AJ48: =IF($Z48="",0,IF(AND($P48="",$Q48=""),0,IF($Q48="",0,IF($P48="",($Z48-$AE48-$AF48-$AG48-$AI48-$AK48-$AL48-$AM48-$AN48-$AO48),($Z48-$AE48-$AF48-$AG48-$AI48-$AK48-$AL48-$AM48-$AN48-$AO48)*15%/(40%+15%))))) -> 0.47636364 | AK48: =IF($Z48="",0,$Z48*15%) -> 0.91 | AL48: =IF($Z48="",0,IF($R48="",0,$R48)) -> 0 | AM48: =IF(OR($Z48="",$S48=""),0,$Z48*5%) -> 0.30333333 | AN48: =IF(OR($Z48="",$T48=""),0,$Z48*10%) -> 0 | AO48: =IF($Z48="",0,IF($U48="",0,$U48)) -> 2
A49: =IF(D49="","",A48+1) -> 46 | B49: TO CATEGORIZE YET | C49: TO CATEGORIZE YET | D49: Price Monitoring & Control - The client wants head-office price communication to each dispenser. - This feature has been built for ALSONs and is in progress for the DOVER Fusion Controller. - If a site changes the selling price from the approved head-office price, Fintech Fuel should raise an alert. - The client gave an example where a site selling at a higher price than the approved price must be flagged. - The client expects exact price matching and does not want a tolerance-based comparison here. - If no transaction has occurred, the current logic may not receive PPU data; this limitation needs a workaround. - Price comparison and price history should be visible in the application. - Price change alerting should not depend only on transactions because the damage may already be done by then. - The team needs to confirm whether the FC controller communicates price changes directly. | F49: PGL | O49: 5 | P49: 15 | Q49: 8 | S49: 5 | U49: 2 | V49: =SUM(M49:U49) -> 35 | W49: =V49 - (V49 * (SUBSTITUTE(SUBSTITUTE($W$2, "Optimistic (", ""), "%)", "") / 100)) -> 17.5 | X49: =V49 + (V49 * (SUBSTITUTE(SUBSTITUTE($X$2, "Pessimistic (", ""), "%)", "") / 100)) -> 38.5 | Y49: =(W49+(4*V49)+X49)/6 -> 32.666667 | Z49: =Y49/2 -> 16.333333 | AE49: =IF($Z49="",0,IF($M49="",0,$M49)) -> 0 | AF49: =IF(OR($Z49="",$N49=""),0,$Z49*5%) -> 0 | AG49: =IF(OR($Z49="",$O49=""),0,$Z49*10%) -> 1.6333333 | AH49: =IF($Z49="",0,IF(AND($P49="",$Q49=""),($Z49-$AE49-$AF49-$AG49-$AI49-$AK49-$AL49-$AM49-$AN49-$AO49),IF($P49="",0,IF($Q49="",($Z49-$AE49-$AF49-$AG49-$AI49-$AK49-$AL49-$AM49-$AN49-$AO49),($Z49-$AE49-$AF49-$AG49-$AI49-$AK49-$AL49-$AM49-$AN49-$AO49)*40%/(40%+15%))))) -> 6.4969697 | AI49: =IF($Z49="",0,IF($P49="",0,0.5)) -> 0.5 | AJ49: =IF($Z49="",0,IF(AND($P49="",$Q49=""),0,IF($Q49="",0,IF($P49="",($Z49-$AE49-$AF49-$AG49-$AI49-$AK49-$AL49-$AM49-$AN49-$AO49),($Z49-$AE49-$AF49-$AG49-$AI49-$AK49-$AL49-$AM49-$AN49-$AO49)*15%/(40%+15%))))) -> 2.4363636 | AK49: =IF($Z49="",0,$Z49*15%) -> 2.45 | AL49: =IF($Z49="",0,IF($R49="",0,$R49)) -> 0 | AM49: =IF(OR($Z49="",$S49=""),0,$Z49*5%) -> 0.81666667 | AN49: =IF(OR($Z49="",$T49=""),0,$Z49*10%) -> 0 | AO49: =IF($Z49="",0,IF($U49="",0,$U49)) -> 2
A50: =IF(D50="","",A49+1) -> 47 | B50: TO CATEGORIZE YET | C50: TO CATEGORIZE YET | D50: Role-Based Access - Ground staff should have read-only access. - Head-office staff should have edit and configuration control. - Manual entry and sensitive corrections should follow user-role restrictions. - The client requested user management roles and an approval system through hierarchy for manual data entry and related control workflows. | F50: PGL | O50: 0 | P50: 6 | Q50: 4 | S50: 5 | U50: 2 | V50: =SUM(M50:U50) -> 17 | W50: =V50 - (V50 * (SUBSTITUTE(SUBSTITUTE($W$2, "Optimistic (", ""), "%)", "") / 100)) -> 8.5 | X50: =V50 + (V50 * (SUBSTITUTE(SUBSTITUTE($X$2, "Pessimistic (", ""), "%)", "") / 100)) -> 18.7 | Y50: =(W50+(4*V50)+X50)/6 -> 15.866667 | Z50: =Y50/2 -> 7.9333333 | AE50: =IF($Z50="",0,IF($M50="",0,$M50)) -> 0 | AF50: =IF(OR($Z50="",$N50=""),0,$Z50*5%) -> 0 | AG50: =IF(OR($Z50="",$O50=""),0,$Z50*10%) -> 0.79333333 | AH50: =IF($Z50="",0,IF(AND($P50="",$Q50=""),($Z50-$AE50-$AF50-$AG50-$AI50-$AK50-$AL50-$AM50-$AN50-$AO50),IF($P50="",0,IF($Q50="",($Z50-$AE50-$AF50-$AG50-$AI50-$AK50-$AL50-$AM50-$AN50-$AO50),($Z50-$AE50-$AF50-$AG50-$AI50-$AK50-$AL50-$AM50-$AN50-$AO50)*40%/(40%+15%))))) -> 2.2206061 | AI50: =IF($Z50="",0,IF($P50="",0,0.5)) -> 0.5 | AJ50: =IF($Z50="",0,IF(AND($P50="",$Q50=""),0,IF($Q50="",0,IF($P50="",($Z50-$AE50-$AF50-$AG50-$AI50-$AK50-$AL50-$AM50-$AN50-$AO50),($Z50-$AE50-$AF50-$AG50-$AI50-$AK50-$AL50-$AM50-$AN50-$AO50)*15%/(40%+15%))))) -> 0.83272727 | AK50: =IF($Z50="",0,$Z50*15%) -> 1.19 | AL50: =IF($Z50="",0,IF($R50="",0,$R50)) -> 0 | AM50: =IF(OR($Z50="",$S50=""),0,$Z50*5%) -> 0.39666667 | AN50: =IF(OR($Z50="",$T50=""),0,$Z50*10%) -> 0 | AO50: =IF($Z50="",0,IF($U50="",0,$U50)) -> 2
A51: =IF(D51="","",A50+1) -> 48 | B51: TO CATEGORIZE YET | C51: TO CATEGORIZE YET | D51: Leak & Theft Alerts | F51: PGL | S51: 5 | U51: 2 | V51: =SUM(M51:U51) -> 7 | W51: =V51 - (V51 * (SUBSTITUTE(SUBSTITUTE($W$2, "Optimistic (", ""), "%)", "") / 100)) -> 3.5 | X51: =V51 + (V51 * (SUBSTITUTE(SUBSTITUTE($X$2, "Pessimistic (", ""), "%)", "") / 100)) -> 7.7 | Y51: =(W51+(4*V51)+X51)/6 -> 6.5333333 | Z51: =Y51/2 -> 3.2666667 | AE51: =IF($Z51="",0,IF($M51="",0,$M51)) -> 0 | AF51: =IF(OR($Z51="",$N51=""),0,$Z51*5%) -> 0 | AG51: =IF(OR($Z51="",$O51=""),0,$Z51*10%) -> 0.32666667 | AH51: =IF($Z51="",0,IF(AND($P51="",$Q51=""),($Z51-$AE51-$AF51-$AG51-$AI51-$AK51-$AL51-$AM51-$AN51-$AO51),IF($P51="",0,IF($Q51="",($Z51-$AE51-$AF51-$AG51-$AI51-$AK51-$AL51-$AM51-$AN51-$AO51),($Z51-$AE51-$AF51-$AG51-$AI51-$AK51-$AL51-$AM51-$AN51-$AO51)*40%/(40%+15%))))) -> -0.15515152 | AI51: =IF($Z51="",0,IF($P51="",0,0.5)) -> 0.5 | AJ51: =IF($Z51="",0,IF(AND($P51="",$Q51=""),0,IF($Q51="",0,IF($P51="",($Z51-$AE51-$AF51-$AG51-$AI51-$AK51-$AL51-$AM51-$AN51-$AO51),($Z51-$AE51-$AF51-$AG51-$AI51-$AK51-$AL51-$AM51-$AN51-$AO51)*15%/(40%+15%))))) -> -0.058181818 | AK51: =IF($Z51="",0,$Z51*15%) -> 0.49 | AL51: =IF($Z51="",0,IF($R51="",0,$R51)) -> 0 | AM51: =IF(OR($Z51="",$S51=""),0,$Z51*5%) -> 0.16333333 | AN51: =IF(OR($Z51="",$T51=""),0,$Z51*10%) -> 0 | AO51: =IF($Z51="",0,IF($U51="",0,$U51)) -> 2
A52: =IF(D52="","",A51+1) -> 49 | B52: TO CATEGORIZE YET | C52: TO CATEGORIZE YET | D52: Sample test for litre quantity from dispenser and then pouring back to tank or detained (discarded) | F52: To compliance with OGRA | O52: 0 | P52: 3 | Q52: 1 | S52: 5 | U52: 2 | V52: =SUM(M52:U52) -> 11 | W52: =V52 - (V52 * (SUBSTITUTE(SUBSTITUTE($W$2, "Optimistic (", ""), "%)", "") / 100)) -> 5.5 | X52: =V52 + (V52 * (SUBSTITUTE(SUBSTITUTE($X$2, "Pessimistic (", ""), "%)", "") / 100)) -> 12.1 | Y52: =(W52+(4*V52)+X52)/6 -> 10.266667 | Z52: =Y52/2 -> 5.1333333 | AE52: =IF($Z52="",0,IF($M52="",0,$M52)) -> 0 | AF52: =IF(OR($Z52="",$N52=""),0,$Z52*5%) -> 0 | AG52: =IF(OR($Z52="",$O52=""),0,$Z52*10%) -> 0.51333333 | AH52: =IF($Z52="",0,IF(AND($P52="",$Q52=""),($Z52-$AE52-$AF52-$AG52-$AI52-$AK52-$AL52-$AM52-$AN52-$AO52),IF($P52="",0,IF($Q52="",($Z52-$AE52-$AF52-$AG52-$AI52-$AK52-$AL52-$AM52-$AN52-$AO52),($Z52-$AE52-$AF52-$AG52-$AI52-$AK52-$AL52-$AM52-$AN52-$AO52)*40%/(40%+15%))))) -> 0.79515152 | AI52: =IF($Z52="",0,IF($P52="",0,0.5)) -> 0.5 | AJ52: =IF($Z52="",0,IF(AND($P52="",$Q52=""),0,IF($Q52="",0,IF($P52="",($Z52-$AE52-$AF52-$AG52-$AI52-$AK52-$AL52-$AM52-$AN52-$AO52),($Z52-$AE52-$AF52-$AG52-$AI52-$AK52-$AL52-$AM52-$AN52-$AO52)*15%/(40%+15%))))) -> 0.29818182 | AK52: =IF($Z52="",0,$Z52*15%) -> 0.77 | AL52: =IF($Z52="",0,IF($R52="",0,$R52)) -> 0 | AM52: =IF(OR($Z52="",$S52=""),0,$Z52*5%) -> 0.25666667 | AN52: =IF(OR($Z52="",$T52=""),0,$Z52*10%) -> 0 | AO52: =IF($Z52="",0,IF($U52="",0,$U52)) -> 2
A53: =IF(D53="","",A52+1) -> 50 | B53: TO CATEGORIZE YET | C53: TO CATEGORIZE YET | D53: Get delivery data from OMC companies from their ERP via API and match with how much exact delivery is delivered to Tank at Site to make sure if the Dealer has decanted some delivery to else where or not. | F53: To compliance with OGRA | O53: 1 | P53: 3 | Q53: 1 | S53: 5 | U53: 2 | V53: =SUM(M53:U53) -> 12 | W53: =V53 - (V53 * (SUBSTITUTE(SUBSTITUTE($W$2, "Optimistic (", ""), "%)", "") / 100)) -> 6 | X53: =V53 + (V53 * (SUBSTITUTE(SUBSTITUTE($X$2, "Pessimistic (", ""), "%)", "") / 100)) -> 13.2 | Y53: =(W53+(4*V53)+X53)/6 -> 11.2 | Z53: =Y53/2 -> 5.6 | AE53: =IF($Z53="",0,IF($M53="",0,$M53)) -> 0 | AF53: =IF(OR($Z53="",$N53=""),0,$Z53*5%) -> 0 | AG53: =IF(OR($Z53="",$O53=""),0,$Z53*10%) -> 0.56 | AH53: =IF($Z53="",0,IF(AND($P53="",$Q53=""),($Z53-$AE53-$AF53-$AG53-$AI53-$AK53-$AL53-$AM53-$AN53-$AO53),IF($P53="",0,IF($Q53="",($Z53-$AE53-$AF53-$AG53-$AI53-$AK53-$AL53-$AM53-$AN53-$AO53),($Z53-$AE53-$AF53-$AG53-$AI53-$AK53-$AL53-$AM53-$AN53-$AO53)*40%/(40%+15%))))) -> 1.0327273 | AI53: =IF($Z53="",0,IF($P53="",0,0.5)) -> 0.5 | AJ53: =IF($Z53="",0,IF(AND($P53="",$Q53=""),0,IF($Q53="",0,IF($P53="",($Z53-$AE53-$AF53-$AG53-$AI53-$AK53-$AL53-$AM53-$AN53-$AO53),($Z53-$AE53-$AF53-$AG53-$AI53-$AK53-$AL53-$AM53-$AN53-$AO53)*15%/(40%+15%))))) -> 0.38727273 | AK53: =IF($Z53="",0,$Z53*15%) -> 0.84 | AL53: =IF($Z53="",0,IF($R53="",0,$R53)) -> 0 | AM53: =IF(OR($Z53="",$S53=""),0,$Z53*5%) -> 0.28 | AN53: =IF(OR($Z53="",$T53=""),0,$Z53*10%) -> 0 | AO53: =IF($Z53="",0,IF($U53="",0,$U53)) -> 2
A54: =IF(D54="","",A53+1) -> 51 | B54: TO CATEGORIZE YET | C54: TO CATEGORIZE YET | D54: Take manual dip reading with DateTime stamp for opening and closing stocks. And make separate reconciliation report wchih will take manual dip readings entered by user. | F54: To compliance with OGRA | O54: 1 | P54: 5 | Q54: 1 | S54: 5 | U54: 2 | V54: =SUM(M54:U54) -> 14 | W54: =V54 - (V54 * (SUBSTITUTE(SUBSTITUTE($W$2, "Optimistic (", ""), "%)", "") / 100)) -> 7 | X54: =V54 + (V54 * (SUBSTITUTE(SUBSTITUTE($X$2, "Pessimistic (", ""), "%)", "") / 100)) -> 15.4 | Y54: =(W54+(4*V54)+X54)/6 -> 13.066667 | Z54: =Y54/2 -> 6.5333333 | AE54: =IF($Z54="",0,IF($M54="",0,$M54)) -> 0 | AF54: =IF(OR($Z54="",$N54=""),0,$Z54*5%) -> 0 | AG54: =IF(OR($Z54="",$O54=""),0,$Z54*10%) -> 0.65333333 | AH54: =IF($Z54="",0,IF(AND($P54="",$Q54=""),($Z54-$AE54-$AF54-$AG54-$AI54-$AK54-$AL54-$AM54-$AN54-$AO54),IF($P54="",0,IF($Q54="",($Z54-$AE54-$AF54-$AG54-$AI54-$AK54-$AL54-$AM54-$AN54-$AO54),($Z54-$AE54-$AF54-$AG54-$AI54-$AK54-$AL54-$AM54-$AN54-$AO54)*40%/(40%+15%))))) -> 1.5078788 | AI54: =IF($Z54="",0,IF($P54="",0,0.5)) -> 0.5 | AJ54: =IF($Z54="",0,IF(AND($P54="",$Q54=""),0,IF($Q54="",0,IF($P54="",($Z54-$AE54-$AF54-$AG54-$AI54-$AK54-$AL54-$AM54-$AN54-$AO54),($Z54-$AE54-$AF54-$AG54-$AI54-$AK54-$AL54-$AM54-$AN54-$AO54)*15%/(40%+15%))))) -> 0.56545455 | AK54: =IF($Z54="",0,$Z54*15%) -> 0.98 | AL54: =IF($Z54="",0,IF($R54="",0,$R54)) -> 0 | AM54: =IF(OR($Z54="",$S54=""),0,$Z54*5%) -> 0.32666667 | AN54: =IF(OR($Z54="",$T54=""),0,$Z54*10%) -> 0 | AO54: =IF($Z54="",0,IF($U54="",0,$U54)) -> 2
A55: =IF(D55="","",A54+1) -> 52 | B55: TO CATEGORIZE YET | C55: TO CATEGORIZE YET | D55: Configurable Site Reconn. Time (done) | F55: PGL | O55: 0 | P55: 10 | Q55: 2 | V55: =SUM(M55:U55) -> 12 | W55: =V55 - (V55 * (SUBSTITUTE(SUBSTITUTE($W$2, "Optimistic (", ""), "%)", "") / 100)) -> 6 | X55: =V55 + (V55 * (SUBSTITUTE(SUBSTITUTE($X$2, "Pessimistic (", ""), "%)", "") / 100)) -> 13.2 | Y55: =(W55+(4*V55)+X55)/6 -> 11.2 | Z55: =Y55/2 -> 5.6 | AE55: =IF($Z55="",0,IF($M55="",0,$M55)) -> 0 | AF55: =IF(OR($Z55="",$N55=""),0,$Z55*5%) -> 0 | AG55: =IF(OR($Z55="",$O55=""),0,$Z55*10%) -> 0.56 | AH55: =IF($Z55="",0,IF(AND($P55="",$Q55=""),($Z55-$AE55-$AF55-$AG55-$AI55-$AK55-$AL55-$AM55-$AN55-$AO55),IF($P55="",0,IF($Q55="",($Z55-$AE55-$AF55-$AG55-$AI55-$AK55-$AL55-$AM55-$AN55-$AO55),($Z55-$AE55-$AF55-$AG55-$AI55-$AK55-$AL55-$AM55-$AN55-$AO55)*40%/(40%+15%))))) -> 2.6909091 | AI55: =IF($Z55="",0,IF($P55="",0,0.5)) -> 0.5 | AJ55: =IF($Z55="",0,IF(AND($P55="",$Q55=""),0,IF($Q55="",0,IF($P55="",($Z55-$AE55-$AF55-$AG55-$AI55-$AK55-$AL55-$AM55-$AN55-$AO55),($Z55-$AE55-$AF55-$AG55-$AI55-$AK55-$AL55-$AM55-$AN55-$AO55)*15%/(40%+15%))))) -> 1.0090909 | AK55: =IF($Z55="",0,$Z55*15%) -> 0.84 | AL55: =IF($Z55="",0,IF($R55="",0,$R55)) -> 0 | AM55: =IF(OR($Z55="",$S55=""),0,$Z55*5%) -> 0 | AN55: =IF(OR($Z55="",$T55=""),0,$Z55*10%) -> 0 | AO55: =IF($Z55="",0,IF($U55="",0,$U55)) -> 0
V56: =SUM(V3:V55)*Settings!I2 -> 0 | W56: =SUM(W3:W55)*Settings!I2 -> 0 | X56: =SUM(X3:X55)*Settings!I2 -> 0 | Y56: =SUM(Y3:Y55)*Settings!I2 -> 0 | Z56: =SUM(Z3:Z55)*Settings!I2 -> 0 | AG56: =IF(OR($Z56="",$O56=""),0,$Z56*10%) -> 0 | AH56: =IF($Z56="",0,IF(AND($P56="",$Q56=""),($Z56-$AE56-$AF56-$AG56-$AI56-$AK56-$AL56-$AM56-$AN56-$AO56),IF($P56="",0,IF($Q56="",($Z56-$AE56-$AF56-$AG56-$AI56-$AK56-$AL56-$AM56-$AN56-$AO56),($Z56-$AE56-$AF56-$AG56-$AI56-$AK56-$AL56-$AM56-$AN56-$AO56)*40%/(40%+15%))))) -> 0 | AI56: =IF($Z56="",0,IF($P56="",0,0.5)) -> 0 | AJ56: =IF($Z56="",0,IF(AND($P56="",$Q56=""),0,IF($Q56="",0,IF($P56="",($Z56-$AE56-$AF56-$AG56-$AI56-$AK56-$AL56-$AM56-$AN56-$AO56),($Z56-$AE56-$AF56-$AG56-$AI56-$AK56-$AL56-$AM56-$AN56-$AO56)*15%/(40%+15%))))) -> 0 | AK56: =IF($Z56="",0,$Z56*15%) -> 0 | AL56: =IF($Z56="",0,IF($R56="",0,$R56)) -> 0 | AM56: =IF(OR($Z56="",$S56=""),0,$Z56*5%) -> 0 | AN56: =IF(OR($Z56="",$T56=""),0,$Z56*10%) -> 0 | AO56: =IF($Z56="",0,IF($U56="",0,$U56)) -> 0
AG57: =IF(OR($Z57="",$O57=""),0,$Z57*10%) -> 0 | AH57: =IF($Z57="",0,IF(AND($P57="",$Q57=""),($Z57-$AE57-$AF57-$AG57-$AI57-$AK57-$AL57-$AM57-$AN57-$AO57),IF($P57="",0,IF($Q57="",($Z57-$AE57-$AF57-$AG57-$AI57-$AK57-$AL57-$AM57-$AN57-$AO57),($Z57-$AE57-$AF57-$AG57-$AI57-$AK57-$AL57-$AM57-$AN57-$AO57)*40%/(40%+15%))))) -> 0 | AI57: =IF($Z57="",0,IF($P57="",0,0.5)) -> 0 | AJ57: =IF($Z57="",0,IF(AND($P57="",$Q57=""),0,IF($Q57="",0,IF($P57="",($Z57-$AE57-$AF57-$AG57-$AI57-$AK57-$AL57-$AM57-$AN57-$AO57),($Z57-$AE57-$AF57-$AG57-$AI57-$AK57-$AL57-$AM57-$AN57-$AO57)*15%/(40%+15%))))) -> 0 | AK57: =IF($Z57="",0,$Z57*15%) -> 0 | AL57: =IF($Z57="",0,IF($R57="",0,$R57)) -> 0 | AM57: =IF(OR($Z57="",$S57=""),0,$Z57*5%) -> 0 | AN57: =IF(OR($Z57="",$T57=""),0,$Z57*10%) -> 0 | AO57: =IF($Z57="",0,IF($U57="",0,$U57)) -> 0
AG58: =IF(OR($Z58="",$O58=""),0,$Z58*10%) -> 0 | AH58: =IF($Z58="",0,IF(AND($P58="",$Q58=""),($Z58-$AE58-$AF58-$AG58-$AI58-$AK58-$AL58-$AM58-$AN58-$AO58),IF($P58="",0,IF($Q58="",($Z58-$AE58-$AF58-$AG58-$AI58-$AK58-$AL58-$AM58-$AN58-$AO58),($Z58-$AE58-$AF58-$AG58-$AI58-$AK58-$AL58-$AM58-$AN58-$AO58)*40%/(40%+15%))))) -> 0 | AI58: =IF($Z58="",0,IF($P58="",0,0.5)) -> 0 | AJ58: =IF($Z58="",0,IF(AND($P58="",$Q58=""),0,IF($Q58="",0,IF($P58="",($Z58-$AE58-$AF58-$AG58-$AI58-$AK58-$AL58-$AM58-$AN58-$AO58),($Z58-$AE58-$AF58-$AG58-$AI58-$AK58-$AL58-$AM58-$AN58-$AO58)*15%/(40%+15%))))) -> 0 | AK58: =IF($Z58="",0,$Z58*15%) -> 0 | AL58: =IF($Z58="",0,IF($R58="",0,$R58)) -> 0 | AM58: =IF(OR($Z58="",$S58=""),0,$Z58*5%) -> 0 | AN58: =IF(OR($Z58="",$T58=""),0,$Z58*10%) -> 0 | AO58: =IF($Z58="",0,IF($U58="",0,$U58)) -> 0
AG59: =IF(OR($Z59="",$O59=""),0,$Z59*10%) -> 0 | AH59: =IF($Z59="",0,IF(AND($P59="",$Q59=""),($Z59-$AE59-$AF59-$AG59-$AI59-$AK59-$AL59-$AM59-$AN59-$AO59),IF($P59="",0,IF($Q59="",($Z59-$AE59-$AF59-$AG59-$AI59-$AK59-$AL59-$AM59-$AN59-$AO59),($Z59-$AE59-$AF59-$AG59-$AI59-$AK59-$AL59-$AM59-$AN59-$AO59)*40%/(40%+15%))))) -> 0 | AI59: =IF($Z59="",0,IF($P59="",0,0.5)) -> 0 | AJ59: =IF($Z59="",0,IF(AND($P59="",$Q59=""),0,IF($Q59="",0,IF($P59="",($Z59-$AE59-$AF59-$AG59-$AI59-$AK59-$AL59-$AM59-$AN59-$AO59),($Z59-$AE59-$AF59-$AG59-$AI59-$AK59-$AL59-$AM59-$AN59-$AO59)*15%/(40%+15%))))) -> 0 | AK59: =IF($Z59="",0,$Z59*15%) -> 0 | AL59: =IF($Z59="",0,IF($R59="",0,$R59)) -> 0 | AM59: =IF(OR($Z59="",$S59=""),0,$Z59*5%) -> 0 | AN59: =IF(OR($Z59="",$T59=""),0,$Z59*10%) -> 0 | AO59: =IF($Z59="",0,IF($U59="",0,$U59)) -> 0
AG60: =IF(OR($Z60="",$O60=""),0,$Z60*10%) -> 0 | AH60: =IF($Z60="",0,IF(AND($P60="",$Q60=""),($Z60-$AE60-$AF60-$AG60-$AI60-$AK60-$AL60-$AM60-$AN60-$AO60),IF($P60="",0,IF($Q60="",($Z60-$AE60-$AF60-$AG60-$AI60-$AK60-$AL60-$AM60-$AN60-$AO60),($Z60-$AE60-$AF60-$AG60-$AI60-$AK60-$AL60-$AM60-$AN60-$AO60)*40%/(40%+15%))))) -> 0 | AI60: =IF($Z60="",0,IF($P60="",0,0.5)) -> 0 | AJ60: =IF($Z60="",0,IF(AND($P60="",$Q60=""),0,IF($Q60="",0,IF($P60="",($Z60-$AE60-$AF60-$AG60-$AI60-$AK60-$AL60-$AM60-$AN60-$AO60),($Z60-$AE60-$AF60-$AG60-$AI60-$AK60-$AL60-$AM60-$AN60-$AO60)*15%/(40%+15%))))) -> 0 | AK60: =IF($Z60="",0,$Z60*15%) -> 0 | AL60: =IF($Z60="",0,IF($R60="",0,$R60)) -> 0 | AM60: =IF(OR($Z60="",$S60=""),0,$Z60*5%) -> 0 | AN60: =IF(OR($Z60="",$T60=""),0,$Z60*10%) -> 0 | AO60: =IF($Z60="",0,IF($U60="",0,$U60)) -> 0

Sheet OmniChat RMI
A1: OmniChat Roadmap Items | H1: BHW | I1: TK | J1: AA | K1: TS | M1: RnD Most likely | W1: TK Budgeted
A2: Sr # | B2: Category | C2: Components | D2: Road Map Items | E2: Jira ID | F2: Originator | G2: Value | H2: Priority | I2: Priority | J2: Priority | K2: Priority | L2: Plan Status | M2: Prc Design | N2: R/URS | O2: R/DDS | P2: Dev | Q2: SQA | R2: Prc Test | S2: Doc | T2: Reg SQA | U2: Release | V2: Man Days | W2: ="Optimistic ("&Summary!E7&")" -> Optimistic (50%) | X2: Pessimistic (10%) | Y2: Est Formula | Z2: TK's TARGET | AA2: Start Date | AB2: Dev End | AC2: SQA HO | AD2: Prod Date | AE2: Prc Design | AF2: R/URS (5%) | AG2: R/DDS (10%) | AH2: Dev (40%) | AI2: Handover | AJ2: SQA (15%) | AK2: Bug Fixing (15%) | AL2: Prc Test | AM2: Doc (5%) | AN2: Reg SQA (10%) | AO2: Release
A3: 1 | B3: Input | V3: =SUM(M3:U3) -> 0 | W3: =V3 - (V3 * (SUBSTITUTE(SUBSTITUTE($W$2, "Optimistic (", ""), "%)", "") / 100)) -> 0 | X3: =V3 + (V3 * (SUBSTITUTE(SUBSTITUTE($X$2, "Pessimistic (", ""), "%)", "") / 100)) -> 0 | Y3: =(W3+(4*V3)+X3)/6 -> 0 | AE3: =IF($Z3="",0,IF($M3="",0,$M3)) -> 0 | AF3: =IF(OR($Z3="",$N3=""),0,$Z3*5%) -> 0 | AG3: =IF(OR($Z3="",$O3=""),0,$Z3*10%) -> 0 | AH3: =IF($Z3="",0,IF(AND($P3="",$Q3=""),($Z3-$AE3-$AF3-$AG3-$AI3-$AK3-$AL3-$AM3-$AN3-$AO3),IF($P3="",0,IF($Q3="",($Z3-$AE3-$AF3-$AG3-$AI3-$AK3-$AL3-$AM3-$AN3-$AO3),($Z3-$AE3-$AF3-$AG3-$AI3-$AK3-$AL3-$AM3-$AN3-$AO3)*40%/(40%+15%))))) -> 0 | AI3: =IF($Z3="",0,IF($P3="",0,0.5)) -> 0 | AJ3: =IF($Z3="",0,IF(AND($P3="",$Q3=""),0,IF($Q3="",0,IF($P3="",($Z3-$AE3-$AF3-$AG3-$AI3-$AK3-$AL3-$AM3-$AN3-$AO3),($Z3-$AE3-$AF3-$AG3-$AI3-$AK3-$AL3-$AM3-$AN3-$AO3)*15%/(40%+15%))))) -> 0 | AK3: =IF($Z3="",0,$Z3*15%) -> 0 | AL3: =IF($Z3="",0,IF($R3="",0,$R3)) -> 0 | AM3: =IF(OR($Z3="",$S3=""),0,$Z3*5%) -> 0 | AN3: =IF(OR($Z3="",$T3=""),0,$Z3*10%) -> 0 | AO3: =IF($Z3="",0,IF($U3="",0,$U3)) -> 0
A4: 2 | B4: Enrichment | C4: Omni Agent Connector | D4: Connects to OmniAgent via API for OC related queries | E4: https://octopusdtlsupport.atlassian.net/browse/O2-1461 | F4: RnD | N4: 0 | O4: 4 | P4: =43-15 -> 28 | Q4: 5 | R4: 5 | S4: 3 | T4: 5 | U4: 4 | V4: =SUM(M4:U4) -> 54 | W4: =V4 - (V4 * ( 50% )) -> 27 | X4: =V4 + (V4 * (SUBSTITUTE(SUBSTITUTE($X$2, "Pessimistic (", ""), "%)", "") / 100)) -> 59.4 | Y4: =(W4+(4*V4)+X4)/6 -> 50.4 | Z4: =Y4/2 -> 25.2 | AA4: 46076 | AB4: 46129 | AC4: 46132 | AD4: 46143 | AE4: =IF($Z4="",0,IF($M4="",0,$M4)) -> 0 | AF4: =IF(OR($Z4="",$N4=""),0,$Z4*5%) -> 1.26 | AG4: =IF(OR($Z4="",$O4=""),0,$Z4*10%) -> 2.52 | AH4: =IF($Z4="",0,IF(AND($P4="",$Q4=""),($Z4-$AE4-$AF4-$AG4-$AI4-$AK4-$AL4-$AM4-$AN4-$AO4),IF($P4="",0,IF($Q4="",($Z4-$AE4-$AF4-$AG4-$AI4-$AK4-$AL4-$AM4-$AN4-$AO4),($Z4-$AE4-$AF4-$AG4-$AI4-$AK4-$AL4-$AM4-$AN4-$AO4)*40%/(40%+15%))))) -> 3.1709091 | AI4: =IF($Z4="",0,IF($P4="",0,0.5)) -> 0.5 | AJ4: =IF($Z4="",0,IF(AND($P4="",$Q4=""),0,IF($Q4="",0,IF($P4="",($Z4-$AE4-$AF4-$AG4-$AI4-$AK4-$AL4-$AM4-$AN4-$AO4),($Z4-$AE4-$AF4-$AG4-$AI4-$AK4-$AL4-$AM4-$AN4-$AO4)*15%/(40%+15%))))) -> 1.1890909 | AK4: =IF($Z4="",0,$Z4*15%) -> 3.78 | AL4: =IF($Z4="",0,IF($R4="",0,$R4)) -> 5 | AM4: =IF(OR($Z4="",$S4=""),0,$Z4*5%) -> 1.26 | AN4: =IF(OR($Z4="",$T4=""),0,$Z4*10%) -> 2.52 | AO4: =IF($Z4="",0,IF($U4="",0,$U4)) -> 4
A5: 3 | C5: Dashboard | D5: Dashboard level Filtering | E5: https://octopusdtlsupport.atlassian.net/browse/MN-30 | F5: Impl Team | N5: 0 | O5: 0 | P5: 10 | Q5: 5 | R5: 5 | S5: 3 | T5: 5 | U5: 2 | V5: =SUM(M5:U5) -> 30 | W5: =V5 - (V5 * ( 50% )) -> 15 | X5: =V5 + (V5 * (SUBSTITUTE(SUBSTITUTE($X$2, "Pessimistic (", ""), "%)", "") / 100)) -> 33 | Y5: =(W5+(4*V5)+X5)/6 -> 28 | Z5: =Y5/2 -> 14 | AA5: 46132 | AB5: 46135 | AC5: 46136 | AD5: 46150 | AE5: =IF($Z5="",0,IF($M5="",0,$M5)) -> 0 | AF5: =IF(OR($Z5="",$N5=""),0,$Z5*5%) -> 0.7 | AG5: =IF(OR($Z5="",$O5=""),0,$Z5*10%) -> 1.4 | AH5: =IF($Z5="",0,IF(AND($P5="",$Q5=""),($Z5-$AE5-$AF5-$AG5-$AI5-$AK5-$AL5-$AM5-$AN5-$AO5),IF($P5="",0,IF($Q5="",($Z5-$AE5-$AF5-$AG5-$AI5-$AK5-$AL5-$AM5-$AN5-$AO5),($Z5-$AE5-$AF5-$AG5-$AI5-$AK5-$AL5-$AM5-$AN5-$AO5)*40%/(40%+15%))))) -> 0.14545455 | AI5: =IF($Z5="",0,IF($P5="",0,0.5)) -> 0.5 | AJ5: =IF($Z5="",0,IF(AND($P5="",$Q5=""),0,IF($Q5="",0,IF($P5="",($Z5-$AE5-$AF5-$AG5-$AI5-$AK5-$AL5-$AM5-$AN5-$AO5),($Z5-$AE5-$AF5-$AG5-$AI5-$AK5-$AL5-$AM5-$AN5-$AO5)*15%/(40%+15%))))) -> 0.054545455 | AK5: =IF($Z5="",0,$Z5*15%) -> 2.1 | AL5: =IF($Z5="",0,IF($R5="",0,$R5)) -> 5 | AM5: =IF(OR($Z5="",$S5=""),0,$Z5*5%) -> 0.7 | AN5: =IF(OR($Z5="",$T5=""),0,$Z5*10%) -> 1.4 | AO5: =IF($Z5="",0,IF($U5="",0,$U5)) -> 2
A6: 4 | D6: Panel level Filtering | E6: https://octopusdtlsupport.atlassian.net/browse/MN-75 | F6: Impl Team | N6: 0 | O6: 0 | P6: 10 | Q6: 5 | R6: 5 | S6: 5 | T6: 5 | U6: 2 | V6: =SUM(M6:U6) -> 32 | W6: =V6 - (V6 * ( 50% )) -> 16 | X6: =V6 + (V6 * (SUBSTITUTE(SUBSTITUTE($X$2, "Pessimistic (", ""), "%)", "") / 100)) -> 35.2 | Y6: =(W6+(4*V6)+X6)/6 -> 29.866667 | Z6: =Y6/2 -> 14.933333 | AA6: 46133 | AB6: 46143 | AC6: 46146 | AD6: 46154 | AE6: =IF($Z6="",0,IF($M6="",0,$M6)) -> 0 | AF6: =IF(OR($Z6="",$N6=""),0,$Z6*5%) -> 0.74666667 | AG6: =IF(OR($Z6="",$O6=""),0,$Z6*10%) -> 1.4933333 | AH6: =IF($Z6="",0,IF(AND($P6="",$Q6=""),($Z6-$AE6-$AF6-$AG6-$AI6-$AK6-$AL6-$AM6-$AN6-$AO6),IF($P6="",0,IF($Q6="",($Z6-$AE6-$AF6-$AG6-$AI6-$AK6-$AL6-$AM6-$AN6-$AO6),($Z6-$AE6-$AF6-$AG6-$AI6-$AK6-$AL6-$AM6-$AN6-$AO6)*40%/(40%+15%))))) -> 0.51878788 | AI6: =IF($Z6="",0,IF($P6="",0,0.5)) -> 0.5 | AJ6: =IF($Z6="",0,IF(AND($P6="",$Q6=""),0,IF($Q6="",0,IF($P6="",($Z6-$AE6-$AF6-$AG6-$AI6-$AK6-$AL6-$AM6-$AN6-$AO6),($Z6-$AE6-$AF6-$AG6-$AI6-$AK6-$AL6-$AM6-$AN6-$AO6)*15%/(40%+15%))))) -> 0.19454545 | AK6: =IF($Z6="",0,$Z6*15%) -> 2.24 | AL6: =IF($Z6="",0,IF($R6="",0,$R6)) -> 5 | AM6: =IF(OR($Z6="",$S6=""),0,$Z6*5%) -> 0.74666667 | AN6: =IF(OR($Z6="",$T6=""),0,$Z6*10%) -> 1.4933333 | AO6: =IF($Z6="",0,IF($U6="",0,$U6)) -> 2
A7: 5 | D7: Panel Resizing | E7: https://octopusdtlsupport.atlassian.net/browse/MN-76 | F7: Impl Team | N7: 0 | O7: 0 | P7: 5 | Q7: 5 | R7: 5 | S7: 5 | T7: 5 | U7: 2 | V7: =SUM(M7:U7) -> 27 | W7: =V7 - (V7 * ( 50% )) -> 13.5 | X7: =V7 + (V7 * (SUBSTITUTE(SUBSTITUTE($X$2, "Pessimistic (", ""), "%)", "") / 100)) -> 29.7 | Y7: =(W7+(4*V7)+X7)/6 -> 25.2 | Z7: =Y7/2 -> 12.6 | AA7: 46141 | AB7: 46148 | AC7: 46149 | AD7: 46164 | AE7: =IF($Z7="",0,IF($M7="",0,$M7)) -> 0 | AF7: =IF(OR($Z7="",$N7=""),0,$Z7*5%) -> 0.63 | AG7: =IF(OR($Z7="",$O7=""),0,$Z7*10%) -> 1.26 | AH7: =IF($Z7="",0,IF(AND($P7="",$Q7=""),($Z7-$AE7-$AF7-$AG7-$AI7-$AK7-$AL7-$AM7-$AN7-$AO7),IF($P7="",0,IF($Q7="",($Z7-$AE7-$AF7-$AG7-$AI7-$AK7-$AL7-$AM7-$AN7-$AO7),($Z7-$AE7-$AF7-$AG7-$AI7-$AK7-$AL7-$AM7-$AN7-$AO7)*40%/(40%+15%))))) -> -0.41454545 | AI7: =IF($Z7="",0,IF($P7="",0,0.5)) -> 0.5 | AJ7: =IF($Z7="",0,IF(AND($P7="",$Q7=""),0,IF($Q7="",0,IF($P7="",($Z7-$AE7-$AF7-$AG7-$AI7-$AK7-$AL7-$AM7-$AN7-$AO7),($Z7-$AE7-$AF7-$AG7-$AI7-$AK7-$AL7-$AM7-$AN7-$AO7)*15%/(40%+15%))))) -> -0.15545455 | AK7: =IF($Z7="",0,$Z7*15%) -> 1.89 | AL7: =IF($Z7="",0,IF($R7="",0,$R7)) -> 5 | AM7: =IF(OR($Z7="",$S7=""),0,$Z7*5%) -> 0.63 | AN7: =IF(OR($Z7="",$T7=""),0,$Z7*10%) -> 1.26 | AO7: =IF($Z7="",0,IF($U7="",0,$U7)) -> 2
A8: 6 | D8: Auto Dashboard sharing | E8: https://octopusdtlsupport.atlassian.net/browse/MN-77 | F8: Impl Team | N8: 0 | O8: 0 | P8: 10 | Q8: 5 | R8: 5 | S8: 5 | T8: 5 | U8: 2 | V8: =SUM(M8:U8) -> 32 | W8: =V8 - (V8 * ( 50% )) -> 16 | X8: =V8 + (V8 * (SUBSTITUTE(SUBSTITUTE($X$2, "Pessimistic (", ""), "%)", "") / 100)) -> 35.2 | Y8: =(W8+(4*V8)+X8)/6 -> 29.866667 | Z8: =Y8/2 -> 14.933333 | AA8: 46146 | AB8: 46146 | AC8: 46147 | AD8: 46164 | AE8: =IF($Z8="",0,IF($M8="",0,$M8)) -> 0 | AF8: =IF(OR($Z8="",$N8=""),0,$Z8*5%) -> 0.74666667 | AG8: =IF(OR($Z8="",$O8=""),0,$Z8*10%) -> 1.4933333 | AH8: =IF($Z8="",0,IF(AND($P8="",$Q8=""),($Z8-$AE8-$AF8-$AG8-$AI8-$AK8-$AL8-$AM8-$AN8-$AO8),IF($P8="",0,IF($Q8="",($Z8-$AE8-$AF8-$AG8-$AI8-$AK8-$AL8-$AM8-$AN8-$AO8),($Z8-$AE8-$AF8-$AG8-$AI8-$AK8-$AL8-$AM8-$AN8-$AO8)*40%/(40%+15%))))) -> 0.51878788 | AI8: =IF($Z8="",0,IF($P8="",0,0.5)) -> 0.5 | AJ8: =IF($Z8="",0,IF(AND($P8="",$Q8=""),0,IF($Q8="",0,IF($P8="",($Z8-$AE8-$AF8-$AG8-$AI8-$AK8-$AL8-$AM8-$AN8-$AO8),($Z8-$AE8-$AF8-$AG8-$AI8-$AK8-$AL8-$AM8-$AN8-$AO8)*15%/(40%+15%))))) -> 0.19454545 | AK8: =IF($Z8="",0,$Z8*15%) -> 2.24 | AL8: =IF($Z8="",0,IF($R8="",0,$R8)) -> 5 | AM8: =IF(OR($Z8="",$S8=""),0,$Z8*5%) -> 0.74666667 | AN8: =IF(OR($Z8="",$T8=""),0,$Z8*10%) -> 1.4933333 | AO8: =IF($Z8="",0,IF($U8="",0,$U8)) -> 2
D9: Text Overlap in Graphs (x-axis) | E9: https://octopusdtlsupport.atlassian.net/browse/MN-153 | V9: =SUM(M9:U9) -> 0 | W9: =V9 - (V9 * ( 50% )) -> 0 | X9: =V9 + (V9 * (SUBSTITUTE(SUBSTITUTE($X$2, "Pessimistic (", ""), "%)", "") / 100)) -> 0 | Y9: 15 | Z9: 7 | AA9: 46128 | AB9: 46129 | AC9: 46132 | AD9: 46134 | AE9: =IF($Z9="",0,IF($M9="",0,$M9)) -> 0 | AF9: =IF(OR($Z9="",$N9=""),0,$Z9*5%) -> 0 | AG9: =IF(OR($Z9="",$O9=""),0,$Z9*10%) -> 0 | AH9: =IF($Z9="",0,IF(AND($P9="",$Q9=""),($Z9-$AE9-$AF9-$AG9-$AI9-$AK9-$AL9-$AM9-$AN9-$AO9),IF($P9="",0,IF($Q9="",($Z9-$AE9-$AF9-$AG9-$AI9-$AK9-$AL9-$AM9-$AN9-$AO9),($Z9-$AE9-$AF9-$AG9-$AI9-$AK9-$AL9-$AM9-$AN9-$AO9)*40%/(40%+15%))))) -> 5.95 | AI9: =IF($Z9="",0,IF($P9="",0,0.5)) -> 0 | AJ9: =IF($Z9="",0,IF(AND($P9="",$Q9=""),0,IF($Q9="",0,IF($P9="",($Z9-$AE9-$AF9-$AG9-$AI9-$AK9-$AL9-$AM9-$AN9-$AO9),($Z9-$AE9-$AF9-$AG9-$AI9-$AK9-$AL9-$AM9-$AN9-$AO9)*15%/(40%+15%))))) -> 0 | AK9: =IF($Z9="",0,$Z9*15%) -> 1.05 | AL9: =IF($Z9="",0,IF($R9="",0,$R9)) -> 0 | AM9: =IF(OR($Z9="",$S9=""),0,$Z9*5%) -> 0 | AN9: =IF(OR($Z9="",$T9=""),0,$Z9*10%) -> 0 | AO9: =IF($Z9="",0,IF($U9="",0,$U9)) -> 0
A10: 7 | C10: DataSet | D10: Auto Dataset Selection | E10: https://octopusdtlsupport.atlassian.net/browse/MN-29 | F10: Impl Team | P10: 13 | Q10: 5 | R10: 3 | S10: 3 | T10: 3 | U10: 2 | V10: =SUM(M10:U10) -> 29 | W10: =V10 - (V10 * ( 50% )) -> 14.5 | X10: =V10 + (V10 * (SUBSTITUTE(SUBSTITUTE($X$2, "Pessimistic (", ""), "%)", "") / 100)) -> 31.9 | Y10: =(W10+(4*V10)+X10)/6 -> 27.066667 | Z10: =Y10/2 -> 13.533333 | AA10: 46143 | AB10: 46156 | AC10: 46157 | AD10: 46164 | AE10: =IF($Z10="",0,IF($M10="",0,$M10)) -> 0 | AF10: =IF(OR($Z10="",$N10=""),0,$Z10*5%) -> 0 | AG10: =IF(OR($Z10="",$O10=""),0,$Z10*10%) -> 0 | AH10: =IF($Z10="",0,IF(AND($P10="",$Q10=""),($Z10-$AE10-$AF10-$AG10-$AI10-$AK10-$AL10-$AM10-$AN10-$AO10),IF($P10="",0,IF($Q10="",($Z10-$AE10-$AF10-$AG10-$AI10-$AK10-$AL10-$AM10-$AN10-$AO10),($Z10-$AE10-$AF10-$AG10-$AI10-$AK10-$AL10-$AM10-$AN10-$AO10)*40%/(40%+15%))))) -> 2.889697 | AI10: =IF($Z10="",0,IF($P10="",0,0.5)) -> 0.5 | AJ10: =IF($Z10="",0,IF(AND($P10="",$Q10=""),0,IF($Q10="",0,IF($P10="",($Z10-$AE10-$AF10-$AG10-$AI10-$AK10-$AL10-$AM10-$AN10-$AO10),($Z10-$AE10-$AF10-$AG10-$AI10-$AK10-$AL10-$AM10-$AN10-$AO10)*15%/(40%+15%))))) -> 1.0836364 | AK10: =IF($Z10="",0,$Z10*15%) -> 2.03 | AL10: =IF($Z10="",0,IF($R10="",0,$R10)) -> 3 | AM10: =IF(OR($Z10="",$S10=""),0,$Z10*5%) -> 0.67666667 | AN10: =IF(OR($Z10="",$T10=""),0,$Z10*10%) -> 1.3533333 | AO10: =IF($Z10="",0,IF($U10="",0,$U10)) -> 2
A11: 8 | D11: Advanced Multiple Dataset | E11: https://octopusdtlsupport.atlassian.net/browse/MN-32 | F11: Impl Team | P11: 51 | Q11: 10 | R11: 5 | S11: 5 | T11: 2 | U11: 3 | V11: =SUM(M11:U11) -> 76 | W11: =V11 - (V11 * ( 50% )) -> 38 | X11: =V11 + (V11 * (SUBSTITUTE(SUBSTITUTE($X$2, "Pessimistic (", ""), "%)", "") / 100)) -> 83.6 | Y11: =(W11+(4*V11)+X11)/6 -> 70.933333 | Z11: =Y11/2 -> 35.466667 | AA11: 46161 | AB11: 46202 | AC11: 46203 | AD11: 46210 | AE11: =IF($Z11="",0,IF($M11="",0,$M11)) -> 0 | AF11: =IF(OR($Z11="",$N11=""),0,$Z11*5%) -> 0 | AG11: =IF(OR($Z11="",$O11=""),0,$Z11*10%) -> 0 | AH11: =IF($Z11="",0,IF(AND($P11="",$Q11=""),($Z11-$AE11-$AF11-$AG11-$AI11-$AK11-$AL11-$AM11-$AN11-$AO11),IF($P11="",0,IF($Q11="",($Z11-$AE11-$AF11-$AG11-$AI11-$AK11-$AL11-$AM11-$AN11-$AO11),($Z11-$AE11-$AF11-$AG11-$AI11-$AK11-$AL11-$AM11-$AN11-$AO11)*40%/(40%+15%))))) -> 11.873939 | AI11: =IF($Z11="",0,IF($P11="",0,0.5)) -> 0.5 | AJ11: =IF($Z11="",0,IF(AND($P11="",$Q11=""),0,IF($Q11="",0,IF($P11="",($Z11-$AE11-$AF11-$AG11-$AI11-$AK11-$AL11-$AM11-$AN11-$AO11),($Z11-$AE11-$AF11-$AG11-$AI11-$AK11-$AL11-$AM11-$AN11-$AO11)*15%/(40%+15%))))) -> 4.4527273 | AK11: =IF($Z11="",0,$Z11*15%) -> 5.32 | AL11: =IF($Z11="",0,IF($R11="",0,$R11)) -> 5 | AM11: =IF(OR($Z11="",$S11=""),0,$Z11*5%) -> 1.7733333 | AN11: =IF(OR($Z11="",$T11=""),0,$Z11*10%) -> 3.5466667 | AO11: =IF($Z11="",0,IF($U11="",0,$U11)) -> 3
A12: 9 | C12: Sharing | D12: Group Chat | E12: https://octopusdtlsupport.atlassian.net/browse/MN-31 | F12: Impl Team | M12: 0 | N12: 0 | O12: 3 | P12: 50 | Q12: 10 | R12: 5 | S12: 5 | T12: 10 | U12: 3 | V12: =SUM(M12:U12) -> 86 | W12: =V12 - (V12 * ( 50% )) -> 43 | X12: =V12 + (V12 * (SUBSTITUTE(SUBSTITUTE($X$2, "Pessimistic (", ""), "%)", "") / 100)) -> 94.6 | Y12: =(W12+(4*V12)+X12)/6 -> 80.266667 | Z12: =Y12/2 -> 40.133333 | AA12: 46204 | AB12: 46247 | AC12: 46251 | AD12: 46260 | AE12: =IF($Z12="",0,IF($M12="",0,$M12)) -> 0 | AF12: =IF(OR($Z12="",$N12=""),0,$Z12*5%) -> 2.0066667 | AG12: =IF(OR($Z12="",$O12=""),0,$Z12*10%) -> 4.0133333 | AH12: =IF($Z12="",0,IF(AND($P12="",$Q12=""),($Z12-$AE12-$AF12-$AG12-$AI12-$AK12-$AL12-$AM12-$AN12-$AO12),IF($P12="",0,IF($Q12="",($Z12-$AE12-$AF12-$AG12-$AI12-$AK12-$AL12-$AM12-$AN12-$AO12),($Z12-$AE12-$AF12-$AG12-$AI12-$AK12-$AL12-$AM12-$AN12-$AO12)*40%/(40%+15%))))) -> 9.8715152 | AI12: =IF($Z12="",0,IF($P12="",0,0.5)) -> 0.5 | AJ12: =IF($Z12="",0,IF(AND($P12="",$Q12=""),0,IF($Q12="",0,IF($P12="",($Z12-$AE12-$AF12-$AG12-$AI12-$AK12-$AL12-$AM12-$AN12-$AO12),($Z12-$AE12-$AF12-$AG12-$AI12-$AK12-$AL12-$AM12-$AN12-$AO12)*15%/(40%+15%))))) -> 3.7018182 | AK12: =IF($Z12="",0,$Z12*15%) -> 6.02 | AL12: =IF($Z12="",0,IF($R12="",0,$R12)) -> 5 | AM12: =IF(OR($Z12="",$S12=""),0,$Z12*5%) -> 2.0066667 | AN12: =IF(OR($Z12="",$T12=""),0,$Z12*10%) -> 4.0133333 | AO12: =IF($Z12="",0,IF($U12="",0,$U12)) -> 3
A13: 10 | C13: Communication Channels | D13: Extend quering to enterprise communication channels | F13: Impl Team | V13: =SUM(M13:U13) -> 0 | W13: =V13 - (V13 * ( 50% )) -> 0 | X13: =V13 + (V13 * (SUBSTITUTE(SUBSTITUTE($X$2, "Pessimistic (", ""), "%)", "") / 100)) -> 0 | Y13: =(W13+(4*V13)+X13)/6 -> 0 | Z13: =Y13/2 -> 0 | AE13: =IF($Z13="",0,IF($M13="",0,$M13)) -> 0 | AF13: =IF(OR($Z13="",$N13=""),0,$Z13*5%) -> 0 | AG13: =IF(OR($Z13="",$O13=""),0,$Z13*10%) -> 0 | AH13: =IF($Z13="",0,IF(AND($P13="",$Q13=""),($Z13-$AE13-$AF13-$AG13-$AI13-$AK13-$AL13-$AM13-$AN13-$AO13),IF($P13="",0,IF($Q13="",($Z13-$AE13-$AF13-$AG13-$AI13-$AK13-$AL13-$AM13-$AN13-$AO13),($Z13-$AE13-$AF13-$AG13-$AI13-$AK13-$AL13-$AM13-$AN13-$AO13)*40%/(40%+15%))))) -> 0 | AI13: =IF($Z13="",0,IF($P13="",0,0.5)) -> 0 | AJ13: =IF($Z13="",0,IF(AND($P13="",$Q13=""),0,IF($Q13="",0,IF($P13="",($Z13-$AE13-$AF13-$AG13-$AI13-$AK13-$AL13-$AM13-$AN13-$AO13),($Z13-$AE13-$AF13-$AG13-$AI13-$AK13-$AL13-$AM13-$AN13-$AO13)*15%/(40%+15%))))) -> 0 | AK13: =IF($Z13="",0,$Z13*15%) -> 0 | AL13: =IF($Z13="",0,IF($R13="",0,$R13)) -> 0 | AM13: =IF(OR($Z13="",$S13=""),0,$Z13*5%) -> 0 | AN13: =IF(OR($Z13="",$T13=""),0,$Z13*10%) -> 0 | AO13: =IF($Z13="",0,IF($U13="",0,$U13)) -> 0
A14: 11 | B14: Output | V14: =SUM(M14:U14) -> 0 | W14: =V14 - (V14 * ( 50% )) -> 0 | X14: =V14 + (V14 * (SUBSTITUTE(SUBSTITUTE($X$2, "Pessimistic (", ""), "%)", "") / 100)) -> 0 | Y14: =(W14+(4*V14)+X14)/6 -> 0 | Z14: =Y14/2 -> 0 | AE14: =IF($Z14="",0,IF($M14="",0,$M14)) -> 0 | AF14: =IF(OR($Z14="",$N14=""),0,$Z14*5%) -> 0 | AG14: =IF(OR($Z14="",$O14=""),0,$Z14*10%) -> 0 | AH14: =IF($Z14="",0,IF(AND($P14="",$Q14=""),($Z14-$AE14-$AF14-$AG14-$AI14-$AK14-$AL14-$AM14-$AN14-$AO14),IF($P14="",0,IF($Q14="",($Z14-$AE14-$AF14-$AG14-$AI14-$AK14-$AL14-$AM14-$AN14-$AO14),($Z14-$AE14-$AF14-$AG14-$AI14-$AK14-$AL14-$AM14-$AN14-$AO14)*40%/(40%+15%))))) -> 0 | AI14: =IF($Z14="",0,IF($P14="",0,0.5)) -> 0 | AJ14: =IF($Z14="",0,IF(AND($P14="",$Q14=""),0,IF($Q14="",0,IF($P14="",($Z14-$AE14-$AF14-$AG14-$AI14-$AK14-$AL14-$AM14-$AN14-$AO14),($Z14-$AE14-$AF14-$AG14-$AI14-$AK14-$AL14-$AM14-$AN14-$AO14)*15%/(40%+15%))))) -> 0 | AK14: =IF($Z14="",0,$Z14*15%) -> 0 | AL14: =IF($Z14="",0,IF($R14="",0,$R14)) -> 0 | AM14: =IF(OR($Z14="",$S14=""),0,$Z14*5%) -> 0 | AN14: =IF(OR($Z14="",$T14=""),0,$Z14*10%) -> 0 | AO14: =IF($Z14="",0,IF($U14="",0,$U14)) -> 0
A15: 12 | B15: Administration | C15: URM | D15: Password Reset | E15: https://octopusdtlsupport.atlassian.net/browse/MN-53 | F15: RnD | M15: 0 | N15: 0 | O15: 0 | P15: 2 | Q15: 3 | R15: 1 | S15: 2 | T15: 2 | U15: 1 | V15: =SUM(M15:U15) -> 11 | W15: =V15 - (V15 * ( 50% )) -> 5.5 | X15: =V15 + (V15 * (SUBSTITUTE(SUBSTITUTE($X$2, "Pessimistic (", ""), "%)", "") / 100)) -> 12.1 | Y15: =(W15+(4*V15)+X15)/6 -> 10.266667 | Z15: =Y15/2 -> 5.1333333 | AD15: 46132 | AE15: =IF($Z15="",0,IF($M15="",0,$M15)) -> 0 | AF15: =IF(OR($Z15="",$N15=""),0,$Z15*5%) -> 0.25666667 | AG15: =IF(OR($Z15="",$O15=""),0,$Z15*10%) -> 0.51333333 | AH15: =IF($Z15="",0,IF(AND($P15="",$Q15=""),($Z15-$AE15-$AF15-$AG15-$AI15-$AK15-$AL15-$AM15-$AN15-$AO15),IF($P15="",0,IF($Q15="",($Z15-$AE15-$AF15-$AG15-$AI15-$AK15-$AL15-$AM15-$AN15-$AO15),($Z15-$AE15-$AF15-$AG15-$AI15-$AK15-$AL15-$AM15-$AN15-$AO15)*40%/(40%+15%))))) -> 0.23515152 | AI15: =IF($Z15="",0,IF($P15="",0,0.5)) -> 0.5 | AJ15: =IF($Z15="",0,IF(AND($P15="",$Q15=""),0,IF($Q15="",0,IF($P15="",($Z15-$AE15-$AF15-$AG15-$AI15-$AK15-$AL15-$AM15-$AN15-$AO15),($Z15-$AE15-$AF15-$AG15-$AI15-$AK15-$AL15-$AM15-$AN15-$AO15)*15%/(40%+15%))))) -> 0.088181818 | AK15: =IF($Z15="",0,$Z15*15%) -> 0.77 | AL15: =IF($Z15="",0,IF($R15="",0,$R15)) -> 1 | AM15: =IF(OR($Z15="",$S15=""),0,$Z15*5%) -> 0.25666667 | AN15: =IF(OR($Z15="",$T15=""),0,$Z15*10%) -> 0.51333333 | AO15: =IF($Z15="",0,IF($U15="",0,$U15)) -> 1
A16: 13 | B16: Documentation | C16: Documentation | D16: User Manual | F16: RnD | V16: =SUM(M16:U16) -> 0 | W16: =V16 - (V16 * ( 50% )) -> 0 | X16: =V16 + (V16 * (SUBSTITUTE(SUBSTITUTE($X$2, "Pessimistic (", ""), "%)", "") / 100)) -> 0 | Y16: =(W16+(4*V16)+X16)/6 -> 0 | Z16: =Y16/2 -> 0 | AE16: =IF($Z16="",0,IF($M16="",0,$M16)) -> 0 | AF16: =IF(OR($Z16="",$N16=""),0,$Z16*5%) -> 0 | AG16: =IF(OR($Z16="",$O16=""),0,$Z16*10%) -> 0 | AH16: =IF($Z16="",0,IF(AND($P16="",$Q16=""),($Z16-$AE16-$AF16-$AG16-$AI16-$AK16-$AL16-$AM16-$AN16-$AO16),IF($P16="",0,IF($Q16="",($Z16-$AE16-$AF16-$AG16-$AI16-$AK16-$AL16-$AM16-$AN16-$AO16),($Z16-$AE16-$AF16-$AG16-$AI16-$AK16-$AL16-$AM16-$AN16-$AO16)*40%/(40%+15%))))) -> 0 | AI16: =IF($Z16="",0,IF($P16="",0,0.5)) -> 0 | AJ16: =IF($Z16="",0,IF(AND($P16="",$Q16=""),0,IF($Q16="",0,IF($P16="",($Z16-$AE16-$AF16-$AG16-$AI16-$AK16-$AL16-$AM16-$AN16-$AO16),($Z16-$AE16-$AF16-$AG16-$AI16-$AK16-$AL16-$AM16-$AN16-$AO16)*15%/(40%+15%))))) -> 0 | AK16: =IF($Z16="",0,$Z16*15%) -> 0 | AL16: =IF($Z16="",0,IF($R16="",0,$R16)) -> 0 | AM16: =IF(OR($Z16="",$S16=""),0,$Z16*5%) -> 0 | AN16: =IF(OR($Z16="",$T16=""),0,$Z16*10%) -> 0 | AO16: =IF($Z16="",0,IF($U16="",0,$U16)) -> 0
A17: 14 | B17: Support Tickets | C17: Issue Fixing | D17: Known Issues fixing (reported during handover) | E17: https://octopusdtlsupport.atlassian.net/browse/MN-78 | F17: Impl Team | M17: 0 | N17: 0 | O17: 0 | P17: 30 | Q17: 4 | R17: 0 | S17: 0 | T17: 0 | U17: 2 | V17: =SUM(M17:U17) -> 36 | W17: =V17 - (V17 * ( 50% )) -> 18 | X17: =V17 + (V17 * (SUBSTITUTE(SUBSTITUTE($X$2, "Pessimistic (", ""), "%)", "") / 100)) -> 39.6 | Y17: =(W17+(4*V17)+X17)/6 -> 33.6 | Z17: =Y17/2 -> 16.8 | AA17: 46132 | AB17: 46142 | AC17: 46143 | AD17: 46150 | AE17: =IF($Z17="",0,IF($M17="",0,$M17)) -> 0 | AF17: =IF(OR($Z17="",$N17=""),0,$Z17*5%) -> 0.84 | AG17: =IF(OR($Z17="",$O17=""),0,$Z17*10%) -> 1.68 | AH17: =IF($Z17="",0,IF(AND($P17="",$Q17=""),($Z17-$AE17-$AF17-$AG17-$AI17-$AK17-$AL17-$AM17-$AN17-$AO17),IF($P17="",0,IF($Q17="",($Z17-$AE17-$AF17-$AG17-$AI17-$AK17-$AL17-$AM17-$AN17-$AO17),($Z17-$AE17-$AF17-$AG17-$AI17-$AK17-$AL17-$AM17-$AN17-$AO17)*40%/(40%+15%))))) -> 4.9018182 | AI17: =IF($Z17="",0,IF($P17="",0,0.5)) -> 0.5 | AJ17: =IF($Z17="",0,IF(AND($P17="",$Q17=""),0,IF($Q17="",0,IF($P17="",($Z17-$AE17-$AF17-$AG17-$AI17-$AK17-$AL17-$AM17-$AN17-$AO17),($Z17-$AE17-$AF17-$AG17-$AI17-$AK17-$AL17-$AM17-$AN17-$AO17)*15%/(40%+15%))))) -> 1.8381818 | AK17: =IF($Z17="",0,$Z17*15%) -> 2.52 | AL17: =IF($Z17="",0,IF($R17="",0,$R17)) -> 0 | AM17: =IF(OR($Z17="",$S17=""),0,$Z17*5%) -> 0.84 | AN17: =IF(OR($Z17="",$T17=""),0,$Z17*10%) -> 1.68 | AO17: =IF($Z17="",0,IF($U17="",0,$U17)) -> 2 | AP17: First regression on OmniChat
V18: =SUM(V3:V17)*Settings!I2 -> 0 | W18: =V18 - (V18 * ( 50% )) -> 0 | X18: =V18 + (V18 * (10%)) -> 0 | Y18: =SUM(Y3:Y17)*Settings!I2 -> 0 | Z18: =SUM(Z3:Z17)*Settings!I2 -> 0 | AG18: =IF(OR($Z18="",$O18=""),0,$Z18*10%) -> 0 | AH18: =IF($Z18="",0,IF(AND($P18="",$Q18=""),($Z18-$AE18-$AF18-$AG18-$AI18-$AK18-$AL18-$AM18-$AN18-$AO18),IF($P18="",0,IF($Q18="",($Z18-$AE18-$AF18-$AG18-$AI18-$AK18-$AL18-$AM18-$AN18-$AO18),($Z18-$AE18-$AF18-$AG18-$AI18-$AK18-$AL18-$AM18-$AN18-$AO18)*40%/(40%+15%))))) -> 0 | AI18: =IF($Z18="",0,IF($P18="",0,0.5)) -> 0 | AJ18: =IF($Z18="",0,IF(AND($P18="",$Q18=""),0,IF($Q18="",0,IF($P18="",($Z18-$AE18-$AF18-$AG18-$AI18-$AK18-$AL18-$AM18-$AN18-$AO18),($Z18-$AE18-$AF18-$AG18-$AI18-$AK18-$AL18-$AM18-$AN18-$AO18)*15%/(40%+15%))))) -> 0 | AK18: =IF($Z18="",0,$Z18*15%) -> 0 | AL18: =IF($Z18="",0,IF($R18="",0,$R18)) -> 0 | AM18: =IF(OR($Z18="",$S18=""),0,$Z18*5%) -> 0 | AN18: =IF(OR($Z18="",$T18=""),0,$Z18*10%) -> 0 | AO18: =IF($Z18="",0,IF($U18="",0,$U18)) -> 0

Sheet Sheet4
C2: Estimations
B3: EPR | C3: Planned vs Actual
C4: Efficiency
C5: Schedule variance in days
B9: Later | C9: Technical Debt

Sheet Sheet1
A1: Digital Log - Absolute range | B1: DEV | C1: 30 | F1: 3 | H1: Enrichment
A2: Digital Log - Absolute range | B2: MAN | C2: 5 | H2: Enrichment | L2: Digital Log - Absolute range | M2: 35 | N2: Enrichment
A3: Digital Log - Attachment pic with each Checklist (, audio, video, pdf, etc) | B3: DEV | C3: 15 | F3: 3 | H3: Input | L3: Digital Log - Attachment pic with each Checklist (, audio, video, pdf, etc) | M3: 20 | N3: Input
A4: Digital Log - Attachment pic with each Checklist (, audio, video, pdf, etc) | B4: MAN | C4: 5 | H4: Input | L4: Digital Log - Attachments at remarks from approver1, approver2 | M4: 23 | N4: Input
A5: Digital Log - Attachments at remarks from approver1, approver2 | B5: DEV | C5: 18 | F5: 3 | H5: Input | L5: Digital Log - Bulk creation of parameters through importing CSV file(s) (User can develop a template of parameters and then can use for multiple areas/assets) | M5: 29 | N5: Input
A6: Digital Log - Attachments at remarks from approver1, approver2 | B6: MAN | C6: 5 | H6: Input | L6: Digital Log - Calculated tags | M6: 50 | N6: Enrichment
A7: Digital Log - Bulk creation of parameters through importing CSV file(s) (User can develop a template of parameters and then can use for multiple areas/assets) | B7: DEV | C7: 24 | F7: 3 | H7: Input | L7: Digital Log - Delete option to admin (to delete unclaimed checklists) Data Collector → Inbox | N7: Administration
A8: Digital Log - Bulk creation of parameters through importing CSV file(s) (User can develop a template of parameters and then can use for multiple areas/assets) | B8: MAN | C8: 5 | H8: Input | L8: Digital Log - DL Analytics (Dependent upon client need & Data) | N8: Enrichment
A9: Digital Log - Calculated tags | B9: DEV | C9: 45 | F9: 3 | H9: Enrichment | L9: Digital Log - DL Default Reports | N9: Enrichment
A10: Digital Log - Calculated tags | B10: MAN | C10: 5 | H10: Enrichment | L10: Digital Log - DL Trial on WebSite | N10: Input
A11: Digital Log - Delete option to admin (to delete unclaimed checklists) Data Collector → Inbox | B11: DEV | C11: 6 | F11: 3 | H11: Enrichment | L11: Digital Log - Domain Migration to Brand Octopus Digital | N11: Administration
A12: Digital Log - Delete option to admin (to delete unclaimed checklists) Data Collector → Inbox | B12: MAN | C12: 5 | H12: Enrichment
A13: Digital Log - DL Analytics (Dependent upon client need & Data) | B13: DEV | C13: 60 | F13: 3 | H13: Administration
A14: Digital Log - DL Analytics (Dependent upon client need & Data) | B14: MAN | C14: 5 | H14: Administration
A15: Digital Log - DL Default Reports | B15: DEV | C15: 45 | F15: 3 | H15: Enrichment
A16: Digital Log - DL Default Reports | B16: SQA | H16: Enrichment
A17: Digital Log - DL Default Reports | B17: MAN | C17: 5 | H17: Enrichment
A18: Digital Log - DL Default Reports - Research | C18: 3 | D18: 46031 | E18: 46035 | F18: 1 | H18: Enrichment
A19: Digital Log - DL Trial on WebSite | B19: DEV | C19: 75 | F19: 3 | H19: Enrichment
A20: Digital Log - DL Trial on WebSite | B20: MAN | C20: 5 | H20: Enrichment
A21: Digital Log - Domain Migration to Brand Octopus Digital | B21: DEV | C21: 12 | D21: 46062 | E21: 46065 | F21: 3 | H21: Enrichment
A22: Digital Log - Domain Migration to Brand Octopus Digital | B22: SQA | C22: 4 | D22: 46066 | E22: 46072 | F22: 1 | H22: Enrichment
A23: Digital Log - Domain Migration to Brand Octopus Digital | B23: MAN | C23: 5 | D23: 46066 | E23: 46072 | H23: Enrichment
A24: Digital Log - Email text formatting | B24: DEV | C24: 15 | F24: 3 | H24: Enrichment
A25: Digital Log - Email text formatting | B25: MAN | C25: 5 | H25: Enrichment

Sheet Digital Log RMI
A1: Digital Log Roadmap Items | H1: BHW | I1: TK | J1: AA | K1: TS | M1: RnD Most likely | W1: TK Budgeted
A2: Sr # | B2: Category | C2: Components | D2: Road Map Items | E2: JIRA ID | F2: Originator | G2: Value | H2: Priority | I2: Priority | J2: Priority | K2: Priority | L2: Plan Status | M2: Prc Design | N2: R/URS | O2: R/DDS | P2: Dev | Q2: SQA | R2: Prc Test | S2: Doc | T2: Reg SQA | U2: Release | V2: Man Days | W2: ="Optimistic ("&Summary!E7&")" -> Optimistic (50%) | X2: Pessimistic (10%) | Y2: Est Formula | Z2: TK's TARGET | AA2: Start Date | AB2: Dev End | AC2: SQA HO | AD2: Prod Date | AE2: Prc Design | AF2: R/URS (5%) | AG2: R/DDS (10%) | AH2: Dev (40%) | AI2: Handover | AJ2: SQA (15%) | AK2: Bug Fixing (15%) | AL2: Prc Test | AM2: Doc (5%) | AN2: Reg SQA (10%) | AO2: Release
A3: 1 | B3: Input | C3: Data Collector | D3: Journals for Web | F3: Competitive | N3: 1 | O3: 2 | P3: 23 | Q3: 2 | S3: 3 | T3: 3 | U3: 1 | V3: =SUM(M3:U3) -> 35 | W3: =V3 - (V3 * (SUBSTITUTE(SUBSTITUTE($W$2, "Optimistic (", ""), "%)", "") / 100)) -> 17.5 | X3: =V3 + (W3 * (SUBSTITUTE(SUBSTITUTE($W$2, "Optimistic (", ""), "%)", "") / 100)) -> 43.75 | Y3: =(W3+(4*V3)+X3)/6 -> 33.541667 | Z3: =Y3/2 -> 16.770833 | AE3: =IF($Z3="",0,IF($M3="",0,$M3)) -> 0 | AF3: =IF(OR($Z3="",$N3=""),0,$Z3*5%) -> 0.83854167 | AG3: =IF(OR($Z3="",$O3=""),0,$Z3*10%) -> 1.6770833 | AH3: =IF($Z3="",0,IF(AND($P3="",$Q3=""),($Z3-$AE3-$AF3-$AG3-$AI3-$AK3-$AL3-$AM3-$AN3-$AO3),IF($P3="",0,IF($Q3="",($Z3-$AE3-$AF3-$AG3-$AI3-$AK3-$AL3-$AM3-$AN3-$AO3),($Z3-$AE3-$AF3-$AG3-$AI3-$AK3-$AL3-$AM3-$AN3-$AO3)*40%/(40%+15%))))) -> 5.6174242 | AI3: =IF($Z3="",0,IF($P3="",0,0.5)) -> 0.5 | AJ3: =IF($Z3="",0,IF(AND($P3="",$Q3=""),0,IF($Q3="",0,IF($P3="",($Z3-$AE3-$AF3-$AG3-$AI3-$AK3-$AL3-$AM3-$AN3-$AO3),($Z3-$AE3-$AF3-$AG3-$AI3-$AK3-$AL3-$AM3-$AN3-$AO3)*15%/(40%+15%))))) -> 2.1065341 | AK3: =IF($Z3="",0,$Z3*15%) -> 2.515625 | AL3: =IF($Z3="",0,IF($R3="",0,$R3)) -> 0 | AM3: =IF(OR($Z3="",$S3=""),0,$Z3*5%) -> 0.83854167 | AN3: =IF(OR($Z3="",$T3=""),0,$Z3*10%) -> 1.6770833 | AO3: =IF($Z3="",0,IF($U3="",0,$U3)) -> 1
A4: 2 | D4: Journals for Mobile Android | F4: Competitive | N4: 1 | O4: 2 | P4: 23 | Q4: 2 | S4: 3 | T4: 3 | U4: 1 | V4: =SUM(M4:U4) -> 35 | W4: =V4 - (V4 * (SUBSTITUTE(SUBSTITUTE($W$2, "Optimistic (", ""), "%)", "") / 100)) -> 17.5 | X4: =V4 + (W4 * (SUBSTITUTE(SUBSTITUTE($W$2, "Optimistic (", ""), "%)", "") / 100)) -> 43.75 | Y4: =(W4+(4*V4)+X4)/6 -> 33.541667 | Z4: =Y4/2 -> 16.770833 | AE4: =IF($Z4="",0,IF($M4="",0,$M4)) -> 0 | AF4: =IF(OR($Z4="",$N4=""),0,$Z4*5%) -> 0.83854167 | AG4: =IF(OR($Z4="",$O4=""),0,$Z4*10%) -> 1.6770833 | AH4: =IF($Z4="",0,IF(AND($P4="",$Q4=""),($Z4-$AE4-$AF4-$AG4-$AI4-$AK4-$AL4-$AM4-$AN4-$AO4),IF($P4="",0,IF($Q4="",($Z4-$AE4-$AF4-$AG4-$AI4-$AK4-$AL4-$AM4-$AN4-$AO4),($Z4-$AE4-$AF4-$AG4-$AI4-$AK4-$AL4-$AM4-$AN4-$AO4)*40%/(40%+15%))))) -> 5.6174242 | AI4: =IF($Z4="",0,IF($P4="",0,0.5)) -> 0.5 | AJ4: =IF($Z4="",0,IF(AND($P4="",$Q4=""),0,IF($Q4="",0,IF($P4="",($Z4-$AE4-$AF4-$AG4-$AI4-$AK4-$AL4-$AM4-$AN4-$AO4),($Z4-$AE4-$AF4-$AG4-$AI4-$AK4-$AL4-$AM4-$AN4-$AO4)*15%/(40%+15%))))) -> 2.1065341 | AK4: =IF($Z4="",0,$Z4*15%) -> 2.515625 | AL4: =IF($Z4="",0,IF($R4="",0,$R4)) -> 0 | AM4: =IF(OR($Z4="",$S4=""),0,$Z4*5%) -> 0.83854167 | AN4: =IF(OR($Z4="",$T4=""),0,$Z4*10%) -> 1.6770833 | AO4: =IF($Z4="",0,IF($U4="",0,$U4)) -> 1
A5: 3 | D5: Mobile App iOS | F5: Competitive | N5: 1 | O5: 3 | P5: 10 | Q5: 10 | S5: 5 | U5: 5 | V5: =SUM(M5:U5) -> 34 | W5: =V5 - (V5 * (SUBSTITUTE(SUBSTITUTE($W$2, "Optimistic (", ""), "%)", "") / 100)) -> 17 | X5: =V5 + (W5 * (SUBSTITUTE(SUBSTITUTE($W$2, "Optimistic (", ""), "%)", "") / 100)) -> 42.5 | Y5: =(W5+(4*V5)+X5)/6 -> 32.583333 | Z5: =Y5/2 -> 16.291667 | AE5: =IF($Z5="",0,IF($M5="",0,$M5)) -> 0 | AF5: =IF(OR($Z5="",$N5=""),0,$Z5*5%) -> 0.81458333 | AG5: =IF(OR($Z5="",$O5=""),0,$Z5*10%) -> 1.6291667 | AH5: =IF($Z5="",0,IF(AND($P5="",$Q5=""),($Z5-$AE5-$AF5-$AG5-$AI5-$AK5-$AL5-$AM5-$AN5-$AO5),IF($P5="",0,IF($Q5="",($Z5-$AE5-$AF5-$AG5-$AI5-$AK5-$AL5-$AM5-$AN5-$AO5),($Z5-$AE5-$AF5-$AG5-$AI5-$AK5-$AL5-$AM5-$AN5-$AO5)*40%/(40%+15%))))) -> 3.7015152 | AI5: =IF($Z5="",0,IF($P5="",0,0.5)) -> 0.5 | AJ5: =IF($Z5="",0,IF(AND($P5="",$Q5=""),0,IF($Q5="",0,IF($P5="",($Z5-$AE5-$AF5-$AG5-$AI5-$AK5-$AL5-$AM5-$AN5-$AO5),($Z5-$AE5-$AF5-$AG5-$AI5-$AK5-$AL5-$AM5-$AN5-$AO5)*15%/(40%+15%))))) -> 1.3880682 | AK5: =IF($Z5="",0,$Z5*15%) -> 2.44375 | AL5: =IF($Z5="",0,IF($R5="",0,$R5)) -> 0 | AM5: =IF(OR($Z5="",$S5=""),0,$Z5*5%) -> 0.81458333 | AN5: =IF(OR($Z5="",$T5=""),0,$Z5*10%) -> 0 | AO5: =IF($Z5="",0,IF($U5="",0,$U5)) -> 5
A6: 4 | D6: Journals for Mobile iOS | F6: Competitive | N6: 1 | O6: 1 | P6: 3 | Q6: 2 | S6: 1 | T6: 3 | U6: 1 | V6: =SUM(M6:U6) -> 12 | W6: =V6 - (V6 * (SUBSTITUTE(SUBSTITUTE($W$2, "Optimistic (", ""), "%)", "") / 100)) -> 6 | X6: =V6 + (W6 * (SUBSTITUTE(SUBSTITUTE($W$2, "Optimistic (", ""), "%)", "") / 100)) -> 15 | Y6: =(W6+(4*V6)+X6)/6 -> 11.5 | Z6: =Y6/2 -> 5.75 | AE6: =IF($Z6="",0,IF($M6="",0,$M6)) -> 0 | AF6: =IF(OR($Z6="",$N6=""),0,$Z6*5%) -> 0.2875 | AG6: =IF(OR($Z6="",$O6=""),0,$Z6*10%) -> 0.575 | AH6: =IF($Z6="",0,IF(AND($P6="",$Q6=""),($Z6-$AE6-$AF6-$AG6-$AI6-$AK6-$AL6-$AM6-$AN6-$AO6),IF($P6="",0,IF($Q6="",($Z6-$AE6-$AF6-$AG6-$AI6-$AK6-$AL6-$AM6-$AN6-$AO6),($Z6-$AE6-$AF6-$AG6-$AI6-$AK6-$AL6-$AM6-$AN6-$AO6)*40%/(40%+15%))))) -> 1.2090909 | AI6: =IF($Z6="",0,IF($P6="",0,0.5)) -> 0.5 | AJ6: =IF($Z6="",0,IF(AND($P6="",$Q6=""),0,IF($Q6="",0,IF($P6="",($Z6-$AE6-$AF6-$AG6-$AI6-$AK6-$AL6-$AM6-$AN6-$AO6),($Z6-$AE6-$AF6-$AG6-$AI6-$AK6-$AL6-$AM6-$AN6-$AO6)*15%/(40%+15%))))) -> 0.45340909 | AK6: =IF($Z6="",0,$Z6*15%) -> 0.8625 | AL6: =IF($Z6="",0,IF($R6="",0,$R6)) -> 0 | AM6: =IF(OR($Z6="",$S6=""),0,$Z6*5%) -> 0.2875 | AN6: =IF(OR($Z6="",$T6=""),0,$Z6*10%) -> 0.575 | AO6: =IF($Z6="",0,IF($U6="",0,$U6)) -> 1
A7: 5 | D7: User Remarks Traceability | F7: Colgate | N7: 1 | O7: 2 | P7: 15 | Q7: 3 | S7: 2 | T7: 3 | U7: 1 | V7: =SUM(M7:U7) -> 27 | W7: =V7 - (V7 * (SUBSTITUTE(SUBSTITUTE($W$2, "Optimistic (", ""), "%)", "") / 100)) -> 13.5 | X7: =V7 + (W7 * (SUBSTITUTE(SUBSTITUTE($W$2, "Optimistic (", ""), "%)", "") / 100)) -> 33.75 | Y7: =(W7+(4*V7)+X7)/6 -> 25.875 | Z7: =Y7/2 -> 12.9375 | AE7: =IF($Z7="",0,IF($M7="",0,$M7)) -> 0 | AF7: =IF(OR($Z7="",$N7=""),0,$Z7*5%) -> 0.646875 | AG7: =IF(OR($Z7="",$O7=""),0,$Z7*10%) -> 1.29375 | AH7: =IF($Z7="",0,IF(AND($P7="",$Q7=""),($Z7-$AE7-$AF7-$AG7-$AI7-$AK7-$AL7-$AM7-$AN7-$AO7),IF($P7="",0,IF($Q7="",($Z7-$AE7-$AF7-$AG7-$AI7-$AK7-$AL7-$AM7-$AN7-$AO7),($Z7-$AE7-$AF7-$AG7-$AI7-$AK7-$AL7-$AM7-$AN7-$AO7)*40%/(40%+15%))))) -> 4.0840909 | AI7: =IF($Z7="",0,IF($P7="",0,0.5)) -> 0.5 | AJ7: =IF($Z7="",0,IF(AND($P7="",$Q7=""),0,IF($Q7="",0,IF($P7="",($Z7-$AE7-$AF7-$AG7-$AI7-$AK7-$AL7-$AM7-$AN7-$AO7),($Z7-$AE7-$AF7-$AG7-$AI7-$AK7-$AL7-$AM7-$AN7-$AO7)*15%/(40%+15%))))) -> 1.5315341 | AK7: =IF($Z7="",0,$Z7*15%) -> 1.940625 | AL7: =IF($Z7="",0,IF($R7="",0,$R7)) -> 0 | AM7: =IF(OR($Z7="",$S7=""),0,$Z7*5%) -> 0.646875 | AN7: =IF(OR($Z7="",$T7=""),0,$Z7*10%) -> 1.29375 | AO7: =IF($Z7="",0,IF($U7="",0,$U7)) -> 1
A8: 6 | D8: Calculated tags | F8: Client Feedback - Demo | N8: 2 | O8: 3 | P8: 38 | Q8: 5 | S8: 3 | V8: =SUM(M8:U8) -> 51 | W8: =V8 - (V8 * (SUBSTITUTE(SUBSTITUTE($W$2, "Optimistic (", ""), "%)", "") / 100)) -> 25.5 | X8: =V8 + (W8 * (SUBSTITUTE(SUBSTITUTE($W$2, "Optimistic (", ""), "%)", "") / 100)) -> 63.75 | Y8: =(W8+(4*V8)+X8)/6 -> 48.875 | Z8: =Y8/2 -> 24.4375 | AE8: =IF($Z8="",0,IF($M8="",0,$M8)) -> 0 | AF8: =IF(OR($Z8="",$N8=""),0,$Z8*5%) -> 1.221875 | AG8: =IF(OR($Z8="",$O8=""),0,$Z8*10%) -> 2.44375 | AH8: =IF($Z8="",0,IF(AND($P8="",$Q8=""),($Z8-$AE8-$AF8-$AG8-$AI8-$AK8-$AL8-$AM8-$AN8-$AO8),IF($P8="",0,IF($Q8="",($Z8-$AE8-$AF8-$AG8-$AI8-$AK8-$AL8-$AM8-$AN8-$AO8),($Z8-$AE8-$AF8-$AG8-$AI8-$AK8-$AL8-$AM8-$AN8-$AO8)*40%/(40%+15%))))) -> 11.188636 | AI8: =IF($Z8="",0,IF($P8="",0,0.5)) -> 0.5 | AJ8: =IF($Z8="",0,IF(AND($P8="",$Q8=""),0,IF($Q8="",0,IF($P8="",($Z8-$AE8-$AF8-$AG8-$AI8-$AK8-$AL8-$AM8-$AN8-$AO8),($Z8-$AE8-$AF8-$AG8-$AI8-$AK8-$AL8-$AM8-$AN8-$AO8)*15%/(40%+15%))))) -> 4.1957386 | AK8: =IF($Z8="",0,$Z8*15%) -> 3.665625 | AL8: =IF($Z8="",0,IF($R8="",0,$R8)) -> 0 | AM8: =IF(OR($Z8="",$S8=""),0,$Z8*5%) -> 1.221875 | AN8: =IF(OR($Z8="",$T8=""),0,$Z8*10%) -> 0 | AO8: =IF($Z8="",0,IF($U8="",0,$U8)) -> 0
A9: 7 | D9: Attachments at remarks from approver1, approver2 | F9: Ashghal | P9: 15 | Q9: 3 | S9: 2 | V9: =SUM(M9:U9) -> 20 | W9: =V9 - (V9 * (SUBSTITUTE(SUBSTITUTE($W$2, "Optimistic (", ""), "%)", "") / 100)) -> 10 | X9: =V9 + (W9 * (SUBSTITUTE(SUBSTITUTE($W$2, "Optimistic (", ""), "%)", "") / 100)) -> 25 | Y9: =(W9+(4*V9)+X9)/6 -> 19.166667 | Z9: =Y9/2 -> 9.5833333 | AE9: =IF($Z9="",0,IF($M9="",0,$M9)) -> 0 | AF9: =IF(OR($Z9="",$N9=""),0,$Z9*5%) -> 0 | AG9: =IF(OR($Z9="",$O9=""),0,$Z9*10%) -> 0 | AH9: =IF($Z9="",0,IF(AND($P9="",$Q9=""),($Z9-$AE9-$AF9-$AG9-$AI9-$AK9-$AL9-$AM9-$AN9-$AO9),IF($P9="",0,IF($Q9="",($Z9-$AE9-$AF9-$AG9-$AI9-$AK9-$AL9-$AM9-$AN9-$AO9),($Z9-$AE9-$AF9-$AG9-$AI9-$AK9-$AL9-$AM9-$AN9-$AO9)*40%/(40%+15%))))) -> 5.2121212 | AI9: =IF($Z9="",0,IF($P9="",0,0.5)) -> 0.5 | AJ9: =IF($Z9="",0,IF(AND($P9="",$Q9=""),0,IF($Q9="",0,IF($P9="",($Z9-$AE9-$AF9-$AG9-$AI9-$AK9-$AL9-$AM9-$AN9-$AO9),($Z9-$AE9-$AF9-$AG9-$AI9-$AK9-$AL9-$AM9-$AN9-$AO9)*15%/(40%+15%))))) -> 1.9545455 | AK9: =IF($Z9="",0,$Z9*15%) -> 1.4375 | AL9: =IF($Z9="",0,IF($R9="",0,$R9)) -> 0 | AM9: =IF(OR($Z9="",$S9=""),0,$Z9*5%) -> 0.47916667 | AN9: =IF(OR($Z9="",$T9=""),0,$Z9*10%) -> 0 | AO9: =IF($Z9="",0,IF($U9="",0,$U9)) -> 0
A10: 8 | D10: Delete option to admin (to delete unclaimed checklists) Data Collector -> Inbox | F10: EVTL | N10: 1 | O10: 1 | P10: 8 | Q10: 2 | S10: 1 | V10: =SUM(M10:U10) -> 13 | W10: =V10 - (V10 * (SUBSTITUTE(SUBSTITUTE($W$2, "Optimistic (", ""), "%)", "") / 100)) -> 6.5 | X10: =V10 + (W10 * (SUBSTITUTE(SUBSTITUTE($W$2, "Optimistic (", ""), "%)", "") / 100)) -> 16.25 | Y10: =(W10+(4*V10)+X10)/6 -> 12.458333 | Z10: =Y10/2 -> 6.2291667 | AE10: =IF($Z10="",0,IF($M10="",0,$M10)) -> 0 | AF10: =IF(OR($Z10="",$N10=""),0,$Z10*5%) -> 0.31145833 | AG10: =IF(OR($Z10="",$O10=""),0,$Z10*10%) -> 0.62291667 | AH10: =IF($Z10="",0,IF(AND($P10="",$Q10=""),($Z10-$AE10-$AF10-$AG10-$AI10-$AK10-$AL10-$AM10-$AN10-$AO10),IF($P10="",0,IF($Q10="",($Z10-$AE10-$AF10-$AG10-$AI10-$AK10-$AL10-$AM10-$AN10-$AO10),($Z10-$AE10-$AF10-$AG10-$AI10-$AK10-$AL10-$AM10-$AN10-$AO10)*40%/(40%+15%))))) -> 2.5810606 | AI10: =IF($Z10="",0,IF($P10="",0,0.5)) -> 0.5 | AJ10: =IF($Z10="",0,IF(AND($P10="",$Q10=""),0,IF($Q10="",0,IF($P10="",($Z10-$AE10-$AF10-$AG10-$AI10-$AK10-$AL10-$AM10-$AN10-$AO10),($Z10-$AE10-$AF10-$AG10-$AI10-$AK10-$AL10-$AM10-$AN10-$AO10)*15%/(40%+15%))))) -> 0.96789773 | AK10: =IF($Z10="",0,$Z10*15%) -> 0.934375 | AL10: =IF($Z10="",0,IF($R10="",0,$R10)) -> 0 | AM10: =IF(OR($Z10="",$S10=""),0,$Z10*5%) -> 0.31145833 | AN10: =IF(OR($Z10="",$T10=""),0,$Z10*10%) -> 0 | AO10: =IF($Z10="",0,IF($U10="",0,$U10)) -> 0
